Workbook

Sheet SO Domestic PL (S&D)
A1: Scenario : Local Sales - Stock UOM and Sales UOM (Similar) DOC NO : SORD-2425-00089
A2: Sales Order
A3: GST Sales | D3: 2 | E3: (1 - Local Sales,2 Interstate Sales, 3 Export Sales) | J3: Cur. | K3: INR | M3: Ex. Rate | N3: 1
A4: S. No. | B4: Item | C4: Rev | D4: Item Desc. | E4: Stk. UOM | F4: Sale. UOM | G4: Order Qty (Sale UOM) | H4: Unit Price | I4: Gross Amt. | J4: TD% | K4: SD% | L4: CD% | M4: TD Asbl. Val. | N4: TD Amt. | O4: SD Asbl. Val. | P4: SD Amt. | Q4: CD Asbl. Val. | R4: CD Amt. | S4: Disc. Amt. | T4: Disc.Amt.Per.Qty | U4: Sales Val. | V4: HSN | W4: Tax Rate | X4: CGST | Y4: SGST | Z4: IGST | AA4: UTGST | AB4: CESS % | AC4: CESS AMT | AD4: Tax amt | AE4: Net Amt | AF4: Weight/Vol | AG4: Sales Amt (BC) | AH4: Conv. Factor | AI4: Eqv. Stock Qty | AJ4: Before Stock Qty | AK4: Before Stock Cost | AL4: After Stock Qty | AM4: Warehouse | AN4: Promotional Type | AO4: CESS PCT | AP4: CESS AMT | AQ4: PriceClass
A5: 1 | B5: HK-LOT-FIFO-LOT-10001(FG) | C5: 0 | D5: HK-LOT-FIFO-LOT-10001(FG) | E5: NOS | F5: NOS | G5: 44 | H5: 3321 | I5: =G5*H5 -> 187660 | J5: 10 | K5: 2 | L5: 4 | M5: =I5 -> 187660 | N5: =ROUND((M5*J5)/100,2) -> 1876.6 | O5: =I5-N5 -> 185783.4 | P5: =ROUND((O5*K5)/100,2) -> 3715.67 | Q5: =ROUND(O5-P5,2) -> 182067.73 | R5: =ROUND((Q5*L5)/100,2) -> 7282.71 | S5: =N5+P5+R5 -> 12874.98 | T5: =ROUND(S5/G5,2) -> 292.61 | U5: =(I5-S5) -> 174785.02 | V5: HSN1 | W5: 0.12 | X5: =IF(OR($D$3=1,$D$3=4),ROUND((U5*W5)/2,2),0) -> 0 | Y5: =IF($D$3=1,ROUND(((U5*W5)/2),2),0) -> 0 | Z5: =IF($D$3=2,ROUND(((U5*W5)),2),0) -> 20974.2 | AA5: =IF($D$3=4,ROUND(((U5*W5)/2),2),0) -> 0 | AB5: 0.06 | AC5: =IF($D$3=5,ROUND(((U5*AB5)/2),2),0) -> 0 | AD5: =X5+Y5+Z5+AA5+AC5 -> 20974.2 | AE5: =U5+AD5 -> 195759.22 | AF5: 120 | AG5: =U5*$N$3 -> 174785.02 | AH5: 1 | AI5: =G5/AH5 -> 44 | AJ5: 848 | AK5: 235.36857 | AL5: =ROUND(AJ5-G5,0) -> 804 | AM5: F100 | AN5: Sales Regular | AO5: 0 | AP5: =ROUND(((AO5*U5)/100),2) -> 0 | AQ5: DOMESTIC
A6: 2 | B6: HK-FG-PRICELIST-DISSIMILAR UOM-10001 | C6: 0 | D6: HK-FG-PRICELIST-DISSIMILAR UOM-10001 | E6: KGS | F6: NOS | G6: 53 | H6: 5472 | I6: =G6*H6 -> 81779 | J6: 10 | K6: 7 | L6: 9 | M6: =I6 -> 81779 | N6: =ROUND((M6*J6)/100,2) -> 817.79 | O6: =I6-N6 -> 80961.21 | P6: =ROUND((O6*K6)/100,2) -> 5667.28 | Q6: =ROUND(O6-P6,2) -> 75293.93 | R6: =ROUND((Q6*L6)/100,2) -> 6776.45 | S6: =N6+P6+R6 -> 13261.52 | T6: =ROUND(S6/G6,2) -> 250.22 | U6: =(I6-S6) -> 68517.48 | V6: HSN1 | W6: 0.12 | X6: =IF(OR($D$3=1,$D$3=4),ROUND((U6*W6)/2,2),0) -> 0 | Y6: =IF($D$3=1,ROUND(((U6*W6)/2),2),0) -> 0 | Z6: =IF($D$3=2,ROUND(((U6*W6)),2),0) -> 8222.1 | AA6: =IF($D$3=4,ROUND(((U6*W6)/2),2),0) -> 0 | AB6: 0.06 | AC6: =IF($D$3=5,ROUND(((U6*AB6)/2),2),0) -> 0 | AD6: =X6+Y6+Z6+AA6+AC6 -> 8222.1 | AE6: =U6+AD6 -> 76739.58 | AF6: 120 | AG6: =U6*$N$3 -> 68517.48 | AH6: 3 | AI6: =ROUND(G6/AH6,3) -> 17.667 | AJ6: 1375.002 | AK6: 123 | AL6: =ROUND((AJ6-AI6),3) -> 1357.335 | AM6: F100 | AN6: Sales Regular | AO6: 0 | AP6: =ROUND(((AO6*U6)/100),2) -> 0 | AQ6: DOMESTIC
Q7: DISC AMOUNT | Z7: NET AMOUNT | AE7: =SUM(AE5:AE6) -> 272498.8 | AF7: SALES AMOUNT | AG7: =AG5 -> 174785.02

Sheet SO Export PL (S&D)
A1: Scenario : Local Sales - Stock UOM and Sales UOM (Similar) DOC NO : SORD-2425-00089
A2: Sales Order
A3: GST Sales | D3: 3 | E3: (1 - Local Sales,2 Interstate Sales, 3 Export Sales) | J3: Cur. | K3: INR | M3: Ex. Rate | N3: 1
A4: S. No. | B4: Item | C4: Rev | D4: Item Desc. | E4: Stk. UOM | F4: Sale. UOM | G4: Order Qty (Sale UOM) | H4: Unit Price | I4: Gross Amt. | J4: TD% | K4: SD% | L4: CD% | M4: TD Asbl. Val. | N4: TD Amt. | O4: SD Asbl. Val. | P4: SD Amt. | Q4: CD Asbl. Val. | R4: CD Amt. | S4: Disc. Amt. | T4: Disc.Amt.Per.Qty | U4: Sales Val. | V4: HSN | W4: Tax Rate | X4: CGST | Y4: SGST | Z4: IGST | AA4: UTGST | AB4: CESS % | AC4: CESS AMT | AD4: Tax amt | AE4: Net Amt | AF4: Weight/Vol | AG4: Sales Amt (BC) | AH4: Conv. Factor | AI4: Eqv. Stock Qty | AJ4: Before Stock Qty | AK4: Before Stock Cost | AL4: After Stock Qty | AM4: Warehouse | AN4: Promotional Type | AO4: CESS PCT | AP4: CESS AMT | AQ4: PriceClass
A5: 1 | B5: HK-LOT-FIFO-LOT-10001(FG) | C5: 0 | D5: HK-LOT-FIFO-LOT-10001(FG) | E5: NOS | F5: NOS | G5: 5 | H5: 47 | I5: =G5*H5 -> 160 | J5: 10 | K5: 3 | L5: 4 | M5: =I5 -> 160 | N5: =ROUND((M5*J5)/100,2) -> 1.6 | O5: =I5-N5 -> 158.4 | P5: =ROUND((O5*K5)/100,2) -> 4.75 | Q5: =ROUND(O5-P5,2) -> 153.65 | R5: =ROUND((Q5*L5)/100,2) -> 6.15 | S5: =N5+P5+R5 -> 12.5 | T5: =ROUND(S5/G5,2) -> 2.5 | U5: =(I5-S5) -> 147.5 | V5: HSN1 | W5: 0.12 | X5: =IF(OR($D$3=1,$D$3=4),ROUND((U5*W5)/2,2),0) -> 0 | Y5: =IF($D$3=1,ROUND(((U5*W5)/2),2),0) -> 0 | Z5: =IF($D$3=2,ROUND(((U5*W5)),2),0) -> 0 | AA5: =IF($D$3=4,ROUND(((U5*W5)/2),2),0) -> 0 | AB5: 0.06 | AC5: =IF($D$3=5,ROUND(((U5*AB5)/2),2),0) -> 0 | AD5: =X5+Y5+Z5+AA5+AC5 -> 0 | AE5: =U5+AD5 -> 147.5 | AF5: 120 | AG5: =U5*$N$3 -> 147.5 | AH5: 1 | AI5: =G5/AH5 -> 5 | AJ5: 848 | AK5: 235.36857 | AL5: =ROUND(AJ5-G5,0) -> 843 | AM5: F100 | AN5: Sales Regular | AO5: 0 | AP5: =ROUND(((AO5*U5)/100),2) -> 0 | AQ5: DOMESTIC
A6: 2 | B6: HK-FG-PRICELIST-DISSIMILAR UOM-10001 | C6: 0 | D6: HK-FG-PRICELIST-DISSIMILAR UOM-10001 | E6: KGS | F6: NOS | G6: 89 | H6: 27 | I6: =G6*H6 -> 3738 | J6: 10 | K6: 7 | L6: 9 | M6: =I6 -> 3738 | N6: =ROUND((M6*J6)/100,2) -> 37.38 | O6: =I6-N6 -> 3700.62 | P6: =ROUND((O6*K6)/100,2) -> 259.04 | Q6: =ROUND(O6-P6,2) -> 3441.58 | R6: =ROUND((Q6*L6)/100,2) -> 309.74 | S6: =N6+P6+R6 -> 606.16 | T6: =ROUND(S6/G6,2) -> 6.81 | U6: =(I6-S6) -> 3131.84 | V6: HSN1 | W6: 0.05 | X6: =IF(OR($D$3=1,$D$3=4),ROUND((U6*W6)/2,2),0) -> 0 | Y6: =IF($D$3=1,ROUND(((U6*W6)/2),2),0) -> 0 | Z6: =IF($D$3=2,ROUND(((U6*W6)),2),0) -> 0 | AA6: =IF($D$3=4,ROUND(((U6*W6)/2),2),0) -> 0 | AB6: 0.06 | AC6: =IF($D$3=5,ROUND(((U6*AB6)/2),2),0) -> 0 | AD6: =X6+Y6+Z6+AA6+AC6 -> 0 | AE6: =U6+AD6 -> 3131.84 | AF6: 120 | AG6: =U6*$N$3 -> 3131.84 | AH6: 3 | AI6: =ROUND(G6/AH6,3) -> 29.667 | AJ6: 1375.002 | AK6: 123 | AL6: =ROUND((AJ6-AI6),3) -> 1345.335 | AM6: F100 | AN6: Sales Regular | AO6: 0 | AP6: =ROUND(((AO6*U6)/100),2) -> 0 | AQ6: DOMESTIC
Q7: DISC AMOUNT | Z7: NET AMOUNT | AE7: =SUM(AE5:AE6) -> 3279.34 | AF7: SALES AMOUNT | AG7: =AG5 -> 147.5

Sheet SO Domestic CP (S&D)
A1: Scenario : Local Sales - Stock UOM and Sales UOM (Similar) DOC NO : SORD-2425-00089
A2: Sales Order
A3: GST Sales | D3: 2 | E3: (1 - Local Sales,2 Interstate Sales, 3 Export Sales) | J3: Cur. | K3: INR | M3: Ex. Rate | N3: 1
A4: S. No. | B4: Item | C4: Rev | D4: Item Desc. | E4: Stk. UOM | F4: Sale. UOM | G4: Order Qty (Sale UOM) | H4: Unit Price | I4: Gross Amt. | J4: TD% | K4: SD% | L4: CD% | M4: TD Asbl. Val. | N4: TD Amt. | O4: SD Asbl. Val. | P4: SD Amt. | Q4: CD Asbl. Val. | R4: CD Amt. | S4: Disc. Amt. | T4: Disc.Amt.Per.Qty | U4: Sales Val. | V4: HSN | W4: Tax Rate | X4: CGST | Y4: SGST | Z4: IGST | AA4: UTGST | AB4: CESS % | AC4: CESS AMT | AD4: Tax amt | AE4: Net Amt | AF4: Weight/Vol | AG4: Sales Amt (BC) | AH4: Conv. Factor | AI4: Eqv. Stock Qty | AJ4: Before Stock Qty | AK4: Before Stock Cost | AL4: After Stock Qty | AM4: Warehouse | AN4: Promotional Type | AO4: CESS PCT | AP4: CESS AMT | AQ4: PriceClass
A5: 1 | B5: HK-FIFO-SER-BATCH-10001(FG) | C5: 0 | D5: HK-FIFO-SER-BATCH-10001(FG) | E5: NOS | F5: NOS | G5: 21 | H5: 4265 | I5: =G5*H5 -> 86982 | J5: 1 | K5: 2 | L5: 4 | M5: =I5 -> 86982 | N5: =ROUND((M5*J5)/100,2) -> 869.82 | O5: =I5-N5 -> 86112.18 | P5: =ROUND((O5*K5)/100,2) -> 1722.24 | Q5: =ROUND(O5-P5,2) -> 84389.94 | R5: =ROUND((Q5*L5)/100,2) -> 3375.6 | S5: =N5+P5+R5 -> 5967.66 | T5: =ROUND(S5/G5,2) -> 284.17 | U5: =(I5-S5) -> 81014.34 | V5: HSN1 | W5: 0.05 | X5: =IF(OR($D$3=1,$D$3=4),ROUND((U5*W5)/2,2),0) -> 0 | Y5: =IF($D$3=1,ROUND(((U5*W5)/2),2),0) -> 0 | Z5: =IF($D$3=2,ROUND(((U5*W5)),2),0) -> 4050.72 | AA5: =IF($D$3=4,ROUND(((U5*W5)/2),2),0) -> 0 | AB5: 0.06 | AC5: =IF($D$3=5,ROUND(((U5*AB5)/2),2),0) -> 0 | AD5: =X5+Y5+Z5+AA5+AC5 -> 4050.72 | AE5: =U5+AD5 -> 85065.06 | AF5: 120 | AG5: =U5*$N$3 -> 81014.34 | AH5: 1 | AI5: =G5/AH5 -> 21 | AJ5: 848 | AK5: 235.36857 | AL5: =ROUND(AJ5-G5,0) -> 827 | AM5: F100 | AN5: Sales Regular | AO5: 0 | AP5: =ROUND(((AO5*U5)/100),2) -> 0 | AQ5: DOMESTIC
A6: 2 | B6: HK-FG-CATALOG-DISSIMILAR-10001 | C6: 0 | D6: HK-FG-CATALOG-DISSIMILAR-10001 | E6: KGS | F6: NOS | G6: 35 | H6: 1543 | I6: =G6*H6 -> 53970 | J6: 1 | K6: 7 | L6: 9 | M6: =I6 -> 53970 | N6: =ROUND((M6*J6)/100,2) -> 539.7 | O6: =I6-N6 -> 53430.3 | P6: =ROUND((O6*K6)/100,2) -> 3740.12 | Q6: =ROUND(O6-P6,2) -> 49690.18 | R6: =ROUND((Q6*L6)/100,2) -> 4472.12 | S6: =N6+P6+R6 -> 8751.94 | T6: =ROUND(S6/G6,2) -> 250.06 | U6: =(I6-S6) -> 45218.06 | V6: HSN1 | W6: 0.12 | X6: =IF(OR($D$3=1,$D$3=4),ROUND((U6*W6)/2,2),0) -> 0 | Y6: =IF($D$3=1,ROUND(((U6*W6)/2),2),0) -> 0 | Z6: =IF($D$3=2,ROUND(((U6*W6)),2),0) -> 5426.17 | AA6: =IF($D$3=4,ROUND(((U6*W6)/2),2),0) -> 0 | AB6: 0.06 | AC6: =IF($D$3=5,ROUND(((U6*AB6)/2),2),0) -> 0 | AD6: =X6+Y6+Z6+AA6+AC6 -> 5426.17 | AE6: =U6+AD6 -> 50644.23 | AF6: 120 | AG6: =U6*$N$3 -> 45218.06 | AH6: 3 | AI6: =ROUND(G6/AH6,3) -> 11.667 | AJ6: 1375.002 | AK6: 123 | AL6: =ROUND((AJ6-AI6),3) -> 1363.335 | AM6: F100 | AN6: Sales Regular | AO6: 0 | AP6: =ROUND(((AO6*U6)/100),2) -> 0 | AQ6: DOMESTIC
Q7: DISC AMOUNT | Z7: NET AMOUNT | AE7: =SUM(AE5:AE6) -> 135709.29 | AF7: SALES AMOUNT | AG7: =AG5 -> 81014.34

Sheet SO Export CP (S&D)
A1: Scenario : Local Sales - Stock UOM and Sales UOM (Similar) DOC NO : SORD-2425-00089
A2: Sales Order
A3: GST Sales | D3: 3 | E3: (1 - Local Sales,2 Interstate Sales, 3 Export Sales) | J3: Cur. | K3: INR | M3: Ex. Rate | N3: 1
A4: S. No. | B4: Item | C4: Rev | D4: Item Desc. | E4: Stk. UOM | F4: Sale. UOM | G4: Order Qty (Sale UOM) | H4: Unit Price | I4: Gross Amt. | J4: TD% | K4: SD% | L4: CD% | M4: TD Asbl. Val. | N4: TD Amt. | O4: SD Asbl. Val. | P4: SD Amt. | Q4: CD Asbl. Val. | R4: CD Amt. | S4: Disc. Amt. | T4: Disc.Amt.Per.Qty | U4: Sales Val. | V4: HSN | W4: Tax Rate | X4: CGST | Y4: SGST | Z4: IGST | AA4: UTGST | AB4: CESS % | AC4: CESS AMT | AD4: Tax amt | AE4: Net Amt | AF4: Weight/Vol | AG4: Sales Amt (BC) | AH4: Conv. Factor | AI4: Eqv. Stock Qty | AJ4: Before Stock Qty | AK4: Before Stock Cost | AL4: After Stock Qty | AM4: Warehouse | AN4: Promotional Type | AO4: CESS PCT | AP4: CESS AMT | AQ4: PriceClass
A5: 1 | B5: HK-FIFO-SER-BATCH-10001(FG) | C5: 0 | D5: HK-FIFO-SER-BATCH-10001(FG) | E5: NOS | F5: NOS | G5: 11 | H5: 32 | I5: =G5*H5 -> 275 | J5: 1 | K5: 3 | L5: 4 | M5: =I5 -> 275 | N5: =ROUND((M5*J5)/100,2) -> 2.75 | O5: =I5-N5 -> 272.25 | P5: =ROUND((O5*K5)/100,2) -> 8.17 | Q5: =ROUND(O5-P5,2) -> 264.08 | R5: =ROUND((Q5*L5)/100,2) -> 10.56 | S5: =N5+P5+R5 -> 21.48 | T5: =ROUND(S5/G5,2) -> 1.95 | U5: =(I5-S5) -> 253.52 | V5: HSN1 | W5: 0.12 | X5: =IF(OR($D$3=1,$D$3=4),ROUND((U5*W5)/2,2),0) -> 0 | Y5: =IF($D$3=1,ROUND(((U5*W5)/2),2),0) -> 0 | Z5: =IF($D$3=2,ROUND(((U5*W5)),2),0) -> 0 | AA5: =IF($D$3=4,ROUND(((U5*W5)/2),2),0) -> 0 | AB5: 0.06 | AC5: =IF($D$3=5,ROUND(((U5*AB5)/2),2),0) -> 0 | AD5: =X5+Y5+Z5+AA5+AC5 -> 0 | AE5: =U5+AD5 -> 253.52 | AF5: 120 | AG5: =U5*$N$3 -> 253.52 | AH5: 1 | AI5: =G5/AH5 -> 11 | AJ5: 848 | AK5: 235.36857 | AL5: =ROUND(AJ5-G5,0) -> 837 | AM5: F100 | AN5: Sales Regular | AO5: 0 | AP5: =ROUND(((AO5*U5)/100),2) -> 0 | AQ5: DOMESTIC
A6: 2 | B6: HK-FG-CATALOG-DISSIMILAR-10001 | C6: 0 | D6: HK-FG-CATALOG-DISSIMILAR-10001 | E6: KGS | F6: NOS | G6: 15 | H6: 42 | I6: =G6*H6 -> 480 | J6: 1 | K6: 7 | L6: 9 | M6: =I6 -> 480 | N6: =ROUND((M6*J6)/100,2) -> 4.8 | O6: =I6-N6 -> 475.2 | P6: =ROUND((O6*K6)/100,2) -> 33.26 | Q6: =ROUND(O6-P6,2) -> 441.94 | R6: =ROUND((Q6*L6)/100,2) -> 39.77 | S6: =N6+P6+R6 -> 77.83 | T6: =ROUND(S6/G6,2) -> 5.19 | U6: =(I6-S6) -> 402.17 | V6: HSN1 | W6: 0.05 | X6: =IF(OR($D$3=1,$D$3=4),ROUND((U6*W6)/2,2),0) -> 0 | Y6: =IF($D$3=1,ROUND(((U6*W6)/2),2),0) -> 0 | Z6: =IF($D$3=2,ROUND(((U6*W6)),2),0) -> 0 | AA6: =IF($D$3=4,ROUND(((U6*W6)/2),2),0) -> 0 | AB6: 0.06 | AC6: =IF($D$3=5,ROUND(((U6*AB6)/2),2),0) -> 0 | AD6: =X6+Y6+Z6+AA6+AC6 -> 0 | AE6: =U6+AD6 -> 402.17 | AF6: 120 | AG6: =U6*$N$3 -> 402.17 | AH6: 3 | AI6: =ROUND(G6/AH6,3) -> 5 | AJ6: 1375.002 | AK6: 123 | AL6: =ROUND((AJ6-AI6),3) -> 1370.002 | AM6: F100 | AN6: Sales Regular | AO6: 0 | AP6: =ROUND(((AO6*U6)/100),2) -> 0 | AQ6: DOMESTIC
Q7: DISC AMOUNT | Z7: NET AMOUNT | AE7: =SUM(AE5:AE6) -> 655.69 | AF7: SALES AMOUNT | AG7: =AG5 -> 253.52

Sheet SO Export SP (S&D)
A1: Scenario : Local Sales - Stock UOM and Sales UOM (Similar) DOC NO : SORD-2425-00089
A2: Sales Order
A3: GST Sales | D3: 3 | E3: (1 - Local Sales,2 Interstate Sales, 3 Export Sales) | J3: Cur. | K3: INR | M3: Ex. Rate | N3: 1
A4: S. No. | B4: Item | C4: Rev | D4: Item Desc. | E4: Stk. UOM | F4: Sale. UOM | G4: Order Qty (Sale UOM) | H4: Unit Price | I4: Gross Amt. | J4: TD% | K4: SD% | L4: CD% | M4: TD Asbl. Val. | N4: TD Amt. | O4: SD Asbl. Val. | P4: SD Amt. | Q4: CD Asbl. Val. | R4: CD Amt. | S4: Disc. Amt. | T4: Disc.Amt.Per.Qty | U4: Sales Val. | V4: HSN | W4: Tax Rate | X4: CGST | Y4: SGST | Z4: IGST | AA4: UTGST | AB4: CESS % | AC4: CESS AMT | AD4: Tax amt | AE4: Net Amt | AF4: Weight/Vol | AG4: Sales Amt (BC) | AH4: Conv. Factor | AI4: Eqv. Stock Qty | AJ4: Before Stock Qty | AK4: Before Stock Cost | AL4: After Stock Qty | AM4: Warehouse | AN4: Promotional Type | AO4: CESS PCT | AP4: CESS AMT | AQ4: PriceClass
A5: 1 | B5: HK-SER-MAC-10001(FG) | C5: 0 | D5: HK-SER-MAC-10001(FG) | E5: NOS | F5: NOS | G5: 22 | H5: 25 | I5: =G5*H5 -> 792 | J5: 1 | K5: 3 | L5: 4 | M5: =I5 -> 792 | N5: =ROUND((M5*J5)/100,2) -> 7.92 | O5: =I5-N5 -> 784.08 | P5: =ROUND((O5*K5)/100,2) -> 23.52 | Q5: =ROUND(O5-P5,2) -> 760.56 | R5: =ROUND((Q5*L5)/100,2) -> 30.42 | S5: =N5+P5+R5 -> 61.86 | T5: =ROUND(S5/G5,2) -> 2.81 | U5: =(I5-S5) -> 730.14 | V5: HSN1 | W5: 0.12 | X5: =IF(OR($D$3=1,$D$3=4),ROUND((U5*W5)/2,2),0) -> 0 | Y5: =IF($D$3=1,ROUND(((U5*W5)/2),2),0) -> 0 | Z5: =IF($D$3=2,ROUND(((U5*W5)),2),0) -> 0 | AA5: =IF($D$3=4,ROUND(((U5*W5)/2),2),0) -> 0 | AB5: 0.06 | AC5: =IF($D$3=5,ROUND(((U5*AB5)/2),2),0) -> 0 | AD5: =X5+Y5+Z5+AA5+AC5 -> 0 | AE5: =U5+AD5 -> 730.14 | AF5: 120 | AG5: =U5*$N$3 -> 730.14 | AH5: 1 | AI5: =G5/AH5 -> 22 | AJ5: 848 | AK5: 235.36857 | AL5: =ROUND(AJ5-G5,0) -> 826 | AM5: F100 | AN5: Sales Regular | AO5: 0 | AP5: =ROUND(((AO5*U5)/100),2) -> 0 | AQ5: DOMESTIC
A6: 2 | B6: HK-FG-STD-PRICE-DISSIMILAR ITEM-10001 | C6: 0 | D6: HK-FG-STD-PRICE-DISSIMILAR ITEM-10001 | E6: KGS | F6: NOS | G6: 12 | H6: 32 | I6: =G6*H6 -> 204 | J6: 1 | K6: 7 | L6: 9 | M6: =I6 -> 204 | N6: =ROUND((M6*J6)/100,2) -> 2.04 | O6: =I6-N6 -> 201.96 | P6: =ROUND((O6*K6)/100,2) -> 14.14 | Q6: =ROUND(O6-P6,2) -> 187.82 | R6: =ROUND((Q6*L6)/100,2) -> 16.9 | S6: =N6+P6+R6 -> 33.08 | T6: =ROUND(S6/G6,2) -> 2.76 | U6: =(I6-S6) -> 170.92 | V6: HSN1 | W6: 0.05 | X6: =IF(OR($D$3=1,$D$3=4),ROUND((U6*W6)/2,2),0) -> 0 | Y6: =IF($D$3=1,ROUND(((U6*W6)/2),2),0) -> 0 | Z6: =IF($D$3=2,ROUND(((U6*W6)),2),0) -> 0 | AA6: =IF($D$3=4,ROUND(((U6*W6)/2),2),0) -> 0 | AB6: 0.06 | AC6: =IF($D$3=5,ROUND(((U6*AB6)/2),2),0) -> 0 | AD6: =X6+Y6+Z6+AA6+AC6 -> 0 | AE6: =U6+AD6 -> 170.92 | AF6: 120 | AG6: =U6*$N$3 -> 170.92 | AH6: 3 | AI6: =ROUND(G6/AH6,3) -> 4 | AJ6: 1375.002 | AK6: 123 | AL6: =ROUND((AJ6-AI6),3) -> 1371.002 | AM6: F100 | AN6: Sales Regular | AO6: 0 | AP6: =ROUND(((AO6*U6)/100),2) -> 0 | AQ6: DOMESTIC
Q7: DISC AMOUNT | Z7: NET AMOUNT | AE7: =SUM(AE5:AE6) -> 901.06 | AF7: SALES AMOUNT | AG7: =AG5 -> 730.14

Sheet SO Domestic SP (S&D)
A1: Scenario : Local Sales - Stock UOM and Sales UOM (Similar) DOC NO : SORD-2425-00089
A2: Sales Order
A3: GST Sales | D3: 2 | E3: (1 - Local Sales,2 Interstate Sales, 3 Export Sales) | J3: Cur. | K3: INR | M3: Ex. Rate | N3: 1
A4: S. No. | B4: Item | C4: Rev | D4: Item Desc. | E4: Stk. UOM | F4: Sale. UOM | G4: Order Qty (Sale UOM) | H4: Unit Price | I4: Gross Amt. | J4: TD% | K4: SD% | L4: CD% | M4: TD Asbl. Val. | N4: TD Amt. | O4: SD Asbl. Val. | P4: SD Amt. | Q4: CD Asbl. Val. | R4: CD Amt. | S4: Disc. Amt. | T4: Disc.Amt.Per.Qty | U4: Sales Val. | V4: HSN | W4: Tax Rate | X4: CGST | Y4: SGST | Z4: IGST | AA4: UTGST | AB4: CESS % | AC4: CESS AMT | AD4: Tax amt | AE4: Net Amt | AF4: Weight/Vol | AG4: Sales Amt (BC) | AH4: Conv. Factor | AI4: Eqv. Stock Qty | AJ4: Before Stock Qty | AK4: Before Stock Cost | AL4: After Stock Qty | AM4: Warehouse | AN4: Promotional Type | AO4: CESS PCT | AP4: CESS AMT | AQ4: PriceClass
A5: 1 | B5: HK-SER-MAC-10001(FG) | C5: 0 | D5: HK-SER-MAC-10001(FG) | E5: NOS | F5: NOS | G5: 12 | H5: 2135 | I5: =G5*H5 -> 37440 | J5: 1 | K5: 2 | L5: 4 | M5: =I5 -> 37440 | N5: =ROUND((M5*J5)/100,2) -> 374.4 | O5: =I5-N5 -> 37065.6 | P5: =ROUND((O5*K5)/100,2) -> 741.31 | Q5: =ROUND(O5-P5,2) -> 36324.29 | R5: =ROUND((Q5*L5)/100,2) -> 1452.97 | S5: =N5+P5+R5 -> 2568.68 | T5: =ROUND(S5/G5,2) -> 214.06 | U5: =(I5-S5) -> 34871.32 | V5: HSN1 | W5: 0.12 | X5: =IF(OR($D$3=1,$D$3=4),ROUND((U5*W5)/2,2),0) -> 0 | Y5: =IF($D$3=1,ROUND(((U5*W5)/2),2),0) -> 0 | Z5: =IF($D$3=2,ROUND(((U5*W5)),2),0) -> 4184.56 | AA5: =IF($D$3=4,ROUND(((U5*W5)/2),2),0) -> 0 | AB5: 0.06 | AC5: =IF($D$3=5,ROUND(((U5*AB5)/2),2),0) -> 0 | AD5: =X5+Y5+Z5+AA5+AC5 -> 4184.56 | AE5: =U5+AD5 -> 39055.88 | AF5: 120 | AG5: =U5*$N$3 -> 34871.32 | AH5: 1 | AI5: =G5/AH5 -> 12 | AJ5: 848 | AK5: 235.36857 | AL5: =ROUND(AJ5-G5,0) -> 836 | AM5: F100 | AN5: Sales Regular | AO5: 0 | AP5: =ROUND(((AO5*U5)/100),2) -> 0 | AQ5: DOMESTIC
A6: 2 | B6: HK-FG-STD-PRICE-DISSIMILAR ITEM-10001 | C6: 0 | D6: HK-FG-STD-PRICE-DISSIMILAR ITEM-10001 | E6: KGS | F6: NOS | G6: 14 | H6: 1542 | I6: =G6*H6 -> 44184 | J6: 1 | K6: 7 | L6: 9 | M6: =I6 -> 44184 | N6: =ROUND((M6*J6)/100,2) -> 441.84 | O6: =I6-N6 -> 43742.16 | P6: =ROUND((O6*K6)/100,2) -> 3061.95 | Q6: =ROUND(O6-P6,2) -> 40680.21 | R6: =ROUND((Q6*L6)/100,2) -> 3661.22 | S6: =N6+P6+R6 -> 7165.01 | T6: =ROUND(S6/G6,2) -> 511.79 | U6: =(I6-S6) -> 37018.99 | V6: HSN1 | W6: 0.05 | X6: =IF(OR($D$3=1,$D$3=4),ROUND((U6*W6)/2,2),0) -> 0 | Y6: =IF($D$3=1,ROUND(((U6*W6)/2),2),0) -> 0 | Z6: =IF($D$3=2,ROUND(((U6*W6)),2),0) -> 1850.95 | AA6: =IF($D$3=4,ROUND(((U6*W6)/2),2),0) -> 0 | AB6: 0.06 | AC6: =IF($D$3=5,ROUND(((U6*AB6)/2),2),0) -> 0 | AD6: =X6+Y6+Z6+AA6+AC6 -> 1850.95 | AE6: =U6+AD6 -> 38869.94 | AF6: 120 | AG6: =U6*$N$3 -> 37018.99 | AH6: 3 | AI6: =ROUND(G6/AH6,3) -> 4.667 | AJ6: 1375.002 | AK6: 123 | AL6: =ROUND((AJ6-AI6),3) -> 1370.335 | AM6: F100 | AN6: Sales Regular | AO6: 0 | AP6: =ROUND(((AO6*U6)/100),2) -> 0 | AQ6: DOMESTIC
Q7: DISC AMOUNT | Z7: NET AMOUNT | AE7: =SUM(AE5:AE6) -> 77925.82 | AF7: SALES AMOUNT | AG7: =AG5 -> 34871.32

Sheet SO Export RC (S&D)
A1: Scenario : Local Sales - Stock UOM and Sales UOM (Similar) DOC NO : SORD-2425-00089
A2: Sales Order
A3: GST Sales | D3: 3 | E3: (1 - Local Sales,2 Interstate Sales, 3 Export Sales) | J3: Cur. | K3: INR | M3: Ex. Rate | N3: 1
A4: S. No. | B4: Item | C4: Rev | D4: Item Desc. | E4: Stk. UOM | F4: Sale. UOM | G4: Order Qty (Sale UOM) | H4: Unit Price | I4: Gross Amt. | J4: TD% | K4: SD% | L4: CD% | M4: TD Asbl. Val. | N4: TD Amt. | O4: SD Asbl. Val. | P4: SD Amt. | Q4: CD Asbl. Val. | R4: CD Amt. | S4: Disc. Amt. | T4: Disc.Amt.Per.Qty | U4: Sales Val. | V4: HSN | W4: Tax Rate | X4: CGST | Y4: SGST | Z4: IGST | AA4: UTGST | AB4: CESS % | AC4: CESS AMT | AD4: Tax amt | AE4: Net Amt | AF4: Weight/Vol | AG4: Sales Amt (BC) | AH4: Conv. Factor | AI4: Eqv. Stock Qty | AJ4: Before Stock Qty | AK4: Before Stock Cost | AL4: After Stock Qty | AM4: Warehouse | AN4: Promotional Type | AO4: CESS PCT | AP4: CESS AMT | AQ4: PriceClass
A5: 1 | B5: HK-LOT-MAC-10001(FG) | C5: 0 | D5: HK-LOT-MAC-10001(FG) | E5: NOS | F5: NOS | G5: 10 | H5: 36 | I5: =G5*H5 -> 150 | J5: 10 | K5: 2 | L5: 4 | M5: =I5 -> 150 | N5: =ROUND((M5*J5)/100,2) -> 6 | O5: =I5-N5 -> 144 | P5: =ROUND((O5*K5)/100,2) -> 2.88 | Q5: =ROUND(O5-P5,2) -> 141.12 | R5: =ROUND((Q5*L5)/100,2) -> 5.64 | S5: =N5+P5+R5 -> 14.52 | T5: =ROUND(S5/G5,2) -> 1.45 | U5: =(I5-S5) -> 135.48 | V5: HSN1 | W5: 0.12 | X5: =IF(OR($D$3=1,$D$3=4),ROUND((U5*W5)/2,2),0) -> 0 | Y5: =IF($D$3=1,ROUND(((U5*W5)/2),2),0) -> 0 | Z5: =IF($D$3=2,ROUND(((U5*W5)),2),0) -> 0 | AA5: =IF($D$3=4,ROUND(((U5*W5)/2),2),0) -> 0 | AB5: 0.06 | AC5: =IF($D$3=5,ROUND(((U5*AB5)/2),2),0) -> 0 | AD5: =X5+Y5+Z5+AA5+AC5 -> 0 | AE5: =U5+AD5 -> 135.48 | AF5: 120 | AG5: =U5*$N$3 -> 135.48 | AH5: 1 | AI5: =G5/AH5 -> 10 | AJ5: 848 | AK5: 235.36857 | AL5: =ROUND(AJ5-G5,0) -> 838 | AM5: F100 | AN5: Sales Regular | AO5: 0 | AP5: =ROUND(((AO5*U5)/100),2) -> 0 | AQ5: DOMESTIC
A6: 2 | B6: HK-FG-RC-DISSIMILAR ITEM-10001 | C6: 0 | D6: HK-FG-RC-DISSIMILAR ITEM-10001 | E6: KGS | F6: NOS | G6: 10 | H6: 17 | I6: =G6*H6 -> 330 | J6: 12 | K6: 7 | L6: 9 | M6: =I6 -> 330 | N6: =ROUND((M6*J6)/100,2) -> 6.6 | O6: =I6-N6 -> 323.4 | P6: =ROUND((O6*K6)/100,2) -> 22.64 | Q6: =ROUND(O6-P6,2) -> 300.76 | R6: =ROUND((Q6*L6)/100,2) -> 27.07 | S6: =N6+P6+R6 -> 56.31 | T6: =ROUND(S6/G6,2) -> 5.63 | U6: =(I6-S6) -> 273.69 | V6: HSN1 | W6: 0.05 | X6: =IF(OR($D$3=1,$D$3=4),ROUND((U6*W6)/2,2),0) -> 0 | Y6: =IF($D$3=1,ROUND(((U6*W6)/2),2),0) -> 0 | Z6: =IF($D$3=2,ROUND(((U6*W6)),2),0) -> 0 | AA6: =IF($D$3=4,ROUND(((U6*W6)/2),2),0) -> 0 | AB6: 0.06 | AC6: =IF($D$3=5,ROUND(((U6*AB6)/2),2),0) -> 0 | AD6: =X6+Y6+Z6+AA6+AC6 -> 0 | AE6: =U6+AD6 -> 273.69 | AF6: 120 | AG6: =U6*$N$3 -> 273.69 | AH6: 3 | AI6: =ROUND(G6/AH6,3) -> 3.333 | AJ6: 1375.002 | AK6: 123 | AL6: =ROUND((AJ6-AI6),3) -> 1371.669 | AM6: F100 | AN6: Sales Regular | AO6: 0 | AP6: =ROUND(((AO6*U6)/100),2) -> 0 | AQ6: DOMESTIC
Q7: DISC AMOUNT | Z7: NET AMOUNT | AE7: =SUM(AE5:AE6) -> 409.17 | AF7: SALES AMOUNT | AG7: =AG5 -> 135.48

Sheet ShipSet
A1: Scenario : Local Sales - Stock UOM and Sales UOM (Similar) DOC NO : SORD-2425-00089
A2: Sales Order
A3: GST Sales | D3: 2 | E3: (1 - Local Sales,2 Interstate Sales, 3 Export Sales) | J3: Cur. | K3: INR | M3: Ex. Rate | N3: 1
A4: S. No. | B4: Item | C4: Rev | D4: Item Desc. | E4: Stk. UOM | F4: Sale. UOM | G4: Order Qty (Sale UOM) | H4: Unit Price | I4: Gross Amt. | J4: TD% | K4: SD% | L4: CD% | M4: TD Asbl. Val. | N4: TD Amt. | O4: SD Asbl. Val. | P4: SD Amt. | Q4: CD Asbl. Val. | R4: CD Amt. | S4: Disc. Amt. | T4: Disc.Amt.Per.Qty | U4: Sales Val. | V4: HSN | W4: Tax Rate | X4: CGST | Y4: SGST | Z4: IGST | AA4: UTGST | AB4: CESS % | AC4: CESS AMT | AD4: Tax amt | AE4: Net Amt | AF4: Weight/Vol | AG4: Sales Amt (BC) | AH4: Conv. Factor | AI4: Eqv. Stock Qty | AJ4: Before Stock Qty | AK4: Before Stock Cost | AL4: After Stock Qty | AM4: Warehouse | AN4: Promotional Type | AO4: CESS PCT | AP4: CESS AMT | AQ4: PriceClass
A5: 1 | B5: HK-TVS-FG-10001 | C5: 0 | D5: HK-TVS-FG-10001 | E5: NOS | F5: NOS | G5: 10 | H5: 6300 | I5: =G5*H5 -> 63000 | J5: 5 | K5: 2 | L5: 4 | M5: =I5 -> 63000 | N5: =ROUND((M5*J5)/100,2) -> 3150 | O5: =I5-N5 -> 59850 | P5: =ROUND((O5*K5)/100,2) -> 1197 | Q5: =ROUND(O5-P5,2) -> 58653 | R5: =ROUND((Q5*L5)/100,2) -> 2346.12 | S5: =N5+P5+R5 -> 6693.12 | T5: =ROUND(S5/G5,2) -> 669.31 | U5: =(I5-S5) -> 56306.88 | V5: HSN1 | W5: 0.12 | X5: =IF(OR($D$3=1,$D$3=4),ROUND((U5*W5)/2,2),0) -> 0 | Y5: =IF($D$3=1,ROUND(((U5*W5)/2),2),0) -> 0 | Z5: =IF($D$3=2,ROUND(((U5*W5)),2),0) -> 6756.83 | AA5: =IF($D$3=4,ROUND(((U5*W5)/2),2),0) -> 0 | AB5: 0.06 | AC5: =IF($D$3=5,ROUND(((U5*AB5)/2),2),0) -> 0 | AD5: =X5+Y5+Z5+AA5+AC5 -> 6756.83 | AE5: =U5+AD5 -> 63063.71 | AF5: 120 | AG5: =U5*$N$3 -> 56306.88 | AH5: 1 | AI5: =G5/AH5 -> 10 | AJ5: 848 | AK5: 235.36857 | AL5: =ROUND(AJ5-G5,0) -> 838 | AM5: F100 | AN5: Sales Regular | AO5: 0 | AP5: =ROUND(((AO5*U5)/100),2) -> 0 | AQ5: DOMESTIC
A6: 2 | B6: HK-TVS-FG-10002 | C6: 0 | D6: HK-TVS-FG-10002 | E6: KGS | F6: NOS | G6: 10 | H6: 9000 | I6: =G6*H6 -> 90000 | J6: 2 | K6: 7 | L6: 9 | M6: =I6 -> 90000 | N6: =ROUND((M6*J6)/100,2) -> 1800 | O6: =I6-N6 -> 88200 | P6: =ROUND((O6*K6)/100,2) -> 6174 | Q6: =ROUND(O6-P6,2) -> 82026 | R6: =ROUND((Q6*L6)/100,2) -> 7382.34 | S6: =N6+P6+R6 -> 15356.34 | T6: =ROUND(S6/G6,2) -> 1535.63 | U6: =(I6-S6) -> 74643.66 | V6: HSN1 | W6: 0.05 | X6: =IF(OR($D$3=1,$D$3=4),ROUND((U6*W6)/2,2),0) -> 0 | Y6: =IF($D$3=1,ROUND(((U6*W6)/2),2),0) -> 0 | Z6: =IF($D$3=2,ROUND(((U6*W6)),2),0) -> 3732.18 | AA6: =IF($D$3=4,ROUND(((U6*W6)/2),2),0) -> 0 | AB6: 0.06 | AC6: =IF($D$3=5,ROUND(((U6*AB6)/2),2),0) -> 0 | AD6: =X6+Y6+Z6+AA6+AC6 -> 3732.18 | AE6: =U6+AD6 -> 78375.84 | AF6: 120 | AG6: =U6*$N$3 -> 74643.66 | AH6: 3 | AI6: =ROUND(G6/AH6,3) -> 3.333 | AJ6: 1375.002 | AK6: 123 | AL6: =ROUND((AJ6-AI6),3) -> 1371.669 | AM6: F100 | AN6: Sales Regular | AO6: 0 | AP6: =ROUND(((AO6*U6)/100),2) -> 0 | AQ6: DOMESTIC
Q7: DISC AMOUNT | Z7: NET AMOUNT | AE7: =SUM(AE5:AE6) -> 141439.55 | AF7: SALES AMOUNT | AG7: =AG5 -> 56306.88

Sheet Different Price Class (RC)
A1: Scenario : Local Sales - Stock UOM and Sales UOM (Similar) DOC NO : SORD-2425-00089
A2: Sales Order
A3: GST Sales | D3: 2 | E3: (1 - Local Sales,2 Interstate Sales, 3 Export Sales) | J3: Cur. | K3: INR | M3: Ex. Rate | N3: 1
A4: S. No. | B4: Item | C4: Rev | D4: Item Desc. | E4: Stk. UOM | F4: Sale. UOM | G4: Order Qty (Sale UOM) | H4: Unit Price | I4: Gross Amt. | J4: TD% | K4: SD% | L4: CD% | M4: TD Asbl. Val. | N4: TD Amt. | O4: SD Asbl. Val. | P4: SD Amt. | Q4: CD Asbl. Val. | R4: CD Amt. | S4: Disc. Amt. | T4: Disc.Amt.Per.Qty | U4: Sales Val. | V4: HSN | W4: Tax Rate | X4: CGST | Y4: SGST | Z4: IGST | AA4: UTGST | AB4: CESS % | AC4: CESS AMT | AD4: Tax amt | AE4: Net Amt | AF4: Weight/Vol | AG4: Sales Amt (BC) | AH4: Conv. Factor | AI4: Eqv. Stock Qty | AJ4: Before Stock Qty | AK4: Before Stock Cost | AL4: After Stock Qty | AM4: Warehouse | AN4: Promotional Type | AO4: CESS PCT | AP4: CESS AMT | AQ4: PriceClass
A5: 1 | B5: HK-LOT-MAC-10001(FG) | C5: 0 | D5: HK-LOT-MAC-10001(FG) | E5: NOS | F5: NOS | G5: 10 | H5: 9000 | I5: =G5*H5 -> 31200 | J5: 2 | K5: 2 | L5: 4 | M5: =I5 -> 31200 | N5: =ROUND((M5*J5)/100,2) -> 1248 | O5: =I5-N5 -> 29952 | P5: =ROUND((O5*K5)/100,2) -> 599.04 | Q5: =ROUND(O5-P5,2) -> 29352.96 | R5: =ROUND((Q5*L5)/100,2) -> 1174.12 | S5: =N5+P5+R5 -> 3021.16 | T5: =ROUND(S5/G5,2) -> 302.12 | U5: =(I5-S5) -> 28178.84 | V5: HSN1 | W5: 0.12 | X5: =IF(OR($D$3=1,$D$3=4),ROUND((U5*W5)/2,2),0) -> 0 | Y5: =IF($D$3=1,ROUND(((U5*W5)/2),2),0) -> 0 | Z5: =IF($D$3=2,ROUND(((U5*W5)),2),0) -> 3381.46 | AA5: =IF($D$3=4,ROUND(((U5*W5)/2),2),0) -> 0 | AB5: 0.06 | AC5: =IF($D$3=5,ROUND(((U5*AB5)/2),2),0) -> 0 | AD5: =X5+Y5+Z5+AA5+AC5 -> 3381.46 | AE5: =U5+AD5 -> 31560.3 | AF5: 120 | AG5: =U5*$N$3 -> 28178.84 | AH5: 1 | AI5: =G5/AH5 -> 10 | AJ5: 848 | AK5: 235.36857 | AL5: =ROUND(AJ5-G5,0) -> 838 | AM5: F100 | AN5: Sales Regular | AO5: 0 | AP5: =ROUND(((AO5*U5)/100),2) -> 0 | AQ5: SPARE
A6: 2 | B6: HK-FG-RC-DISSIMILAR ITEM-10001 | C6: 0 | D6: HK-FG-RC-DISSIMILAR ITEM-10001 | E6: KGS | F6: NOS | G6: 10 | H6: 6300 | I6: =G6*H6 -> 63000 | J6: 5 | K6: 7 | L6: 9 | M6: =I6 -> 63000 | N6: =ROUND((M6*J6)/100,2) -> 3150 | O6: =I6-N6 -> 59850 | P6: =ROUND((O6*K6)/100,2) -> 4189.5 | Q6: =ROUND(O6-P6,2) -> 55660.5 | R6: =ROUND((Q6*L6)/100,2) -> 5009.45 | S6: =N6+P6+R6 -> 12348.95 | T6: =ROUND(S6/G6,2) -> 1234.9 | U6: =(I6-S6) -> 26175.04 | V6: HSN1 | W6: 0.12 | X6: =IF(OR($D$3=1,$D$3=4),ROUND((U6*W6)/2,2),0) -> 0 | Y6: =IF($D$3=1,ROUND(((U6*W6)/2),2),0) -> 0 | Z6: =IF($D$3=2,ROUND(((U6*W6)),2),0) -> 3141 | AA6: =IF($D$3=4,ROUND(((U6*W6)/2),2),0) -> 0 | AB6: 0.06 | AC6: =IF($D$3=5,ROUND(((U6*AB6)/2),2),0) -> 0 | AD6: =X6+Y6+Z6+AA6+AC6 -> 3141 | AE6: =U6+AD6 -> 29316.04 | AF6: 120 | AG6: =U6*$N$3 -> 26175.04 | AH6: 3 | AI6: =ROUND(G6/AH6,3) -> 3.333 | AJ6: 1375.002 | AK6: 123 | AL6: =ROUND((AJ6-AI6),3) -> 1371.669 | AM6: F100 | AN6: Sales Regular | AO6: 0 | AP6: =ROUND(((AO6*U6)/100),2) -> 0 | AQ6: SPARE
Q7: DISC AMOUNT | Z7: NET AMOUNT | AE7: =SUM(AE5:AE6) -> 60876.34 | AF7: SALES AMOUNT | AG7: =AG5 -> 28178.84

Sheet SO Domestic RC (S&D)
A1: Scenario : Local Sales - Stock UOM and Sales UOM (Similar) DOC NO : SORD-2425-00089
A2: Sales Order
A3: GST Sales | D3: 2 | E3: (1 - Local Sales,2 Interstate Sales, 3 Export Sales) | J3: Cur. | K3: INR | M3: Ex. Rate | N3: 1
A4: S. No. | B4: Item | C4: Rev | D4: Item Desc. | E4: Stk. UOM | F4: Sale. UOM | G4: Order Qty (Sale UOM) | H4: Unit Price | I4: Gross Amt. | J4: TD% | K4: SD% | L4: CD% | M4: TD Asbl. Val. | N4: TD Amt. | O4: SD Asbl. Val. | P4: SD Amt. | Q4: CD Asbl. Val. | R4: CD Amt. | S4: Disc. Amt. | T4: Disc.Amt.Per.Qty | U4: Sales Val. | V4: HSN | W4: Tax Rate | X4: CGST | Y4: SGST | Z4: IGST | AA4: UTGST | AB4: CESS % | AC4: CESS AMT | AD4: Tax amt | AE4: Net Amt | AF4: Weight/Vol | AG4: Sales Amt (BC) | AH4: Conv. Factor | AI4: Eqv. Stock Qty | AJ4: Before Stock Qty | AK4: Before Stock Cost | AL4: After Stock Qty | AM4: Warehouse | AN4: Promotional Type | AO4: CESS PCT | AP4: CESS AMT | AQ4: PriceClass
A5: 1 | B5: HK-LOT-MAC-10001(FG) | C5: 0 | D5: HK-LOT-MAC-10001(FG) | E5: NOS | F5: NOS | G5: 10 | H5: 3120 | I5: =G5*H5 -> 31200 | J5: 4 | K5: 2 | L5: 4 | M5: =I5 -> 31200 | N5: =ROUND((M5*J5)/100,2) -> 1248 | O5: =I5-N5 -> 29952 | P5: =ROUND((O5*K5)/100,2) -> 599.04 | Q5: =ROUND(O5-P5,2) -> 29352.96 | R5: =ROUND((Q5*L5)/100,2) -> 1174.12 | S5: =N5+P5+R5 -> 3021.16 | T5: =ROUND(S5/G5,2) -> 302.12 | U5: =(I5-S5) -> 28178.84 | V5: HSN1 | W5: 0.12 | X5: =IF(OR($D$3=1,$D$3=4),ROUND((U5*W5)/2,2),0) -> 0 | Y5: =IF($D$3=1,ROUND(((U5*W5)/2),2),0) -> 0 | Z5: =IF($D$3=2,ROUND(((U5*W5)),2),0) -> 3381.46 | AA5: =IF($D$3=4,ROUND(((U5*W5)/2),2),0) -> 0 | AB5: 0.06 | AC5: =IF($D$3=5,ROUND(((U5*AB5)/2),2),0) -> 0 | AD5: =X5+Y5+Z5+AA5+AC5 -> 3381.46 | AE5: =U5+AD5 -> 31560.3 | AF5: 120 | AG5: =U5*$N$3 -> 28178.84 | AH5: 1 | AI5: =G5/AH5 -> 10 | AJ5: 848 | AK5: 235.36857 | AL5: =ROUND(AJ5-G5,0) -> 838 | AM5: F100 | AN5: Sales Regular | AO5: 0 | AP5: =ROUND(((AO5*U5)/100),2) -> 0 | AQ5: DOMESTIC
A6: 2 | B6: HK-FG-RC-DISSIMILAR ITEM-10001 | C6: 0 | D6: HK-FG-RC-DISSIMILAR ITEM-10001 | E6: KGS | F6: NOS | G6: 10 | H6: 3156 | I6: =G6*H6 -> 31560 | J6: 2 | K6: 7 | L6: 9 | M6: =I6 -> 31560 | N6: =ROUND((M6*J6)/100,2) -> 631.2 | O6: =I6-N6 -> 30928.8 | P6: =ROUND((O6*K6)/100,2) -> 2165.02 | Q6: =ROUND(O6-P6,2) -> 28763.78 | R6: =ROUND((Q6*L6)/100,2) -> 2588.74 | S6: =N6+P6+R6 -> 5384.96 | T6: =ROUND(S6/G6,2) -> 538.5 | U6: =(I6-S6) -> 26175.04 | V6: HSN1 | W6: 0.12 | X6: =IF(OR($D$3=1,$D$3=4),ROUND((U6*W6)/2,2),0) -> 0 | Y6: =IF($D$3=1,ROUND(((U6*W6)/2),2),0) -> 0 | Z6: =IF($D$3=2,ROUND(((U6*W6)),2),0) -> 3141 | AA6: =IF($D$3=4,ROUND(((U6*W6)/2),2),0) -> 0 | AB6: 0.06 | AC6: =IF($D$3=5,ROUND(((U6*AB6)/2),2),0) -> 0 | AD6: =X6+Y6+Z6+AA6+AC6 -> 3141 | AE6: =U6+AD6 -> 29316.04 | AF6: 120 | AG6: =U6*$N$3 -> 0 | AH6: 3 | AI6: =ROUND(G6/AH6,3) -> 3.333 | AJ6: 1375.002 | AK6: 123 | AL6: =ROUND((AJ6-AI6),3) -> 1371.669 | AM6: F100 | AN6: Sales Regular | AO6: 0 | AP6: =ROUND(((AO6*U6)/100),2) -> 0 | AQ6: DOMESTIC
Q7: DISC AMOUNT | Z7: NET AMOUNT | AE7: =SUM(AE5:AE6) -> 60876.34 | AF7: SALES AMOUNT | AG7: =AG5 -> 0

Sheet SO Export UD (S&D)
A1: Scenario : Local Sales - Stock UOM and Sales UOM (Similar) DOC NO : SORD-2425-00089
A2: Sales Order
A3: GST Sales | D3: 3 | E3: (1 - Local Sales,2 Interstate Sales, 3 Export Sales) | J3: Cur. | K3: INR | M3: Ex. Rate | N3: 1
A4: S. No. | B4: Item | C4: Rev | D4: Item Desc. | E4: Stk. UOM | F4: Sale. UOM | G4: Order Qty (Sale UOM) | H4: Unit Price | I4: Gross Amt. | J4: TD% | K4: SD% | L4: CD% | M4: TD Asbl. Val. | N4: TD Amt. | O4: SD Asbl. Val. | P4: SD Amt. | Q4: CD Asbl. Val. | R4: CD Amt. | S4: Disc. Amt. | T4: Disc.Amt.Per.Qty | U4: Sales Val. | V4: HSN | W4: Tax Rate | X4: CGST | Y4: SGST | Z4: IGST | AA4: UTGST | AB4: CESS % | AC4: CESS AMT | AD4: Tax amt | AE4: Net Amt | AF4: Weight/Vol | AG4: Sales Amt (BC) | AH4: Conv. Factor | AI4: Eqv. Stock Qty | AJ4: Before Stock Qty | AK4: Before Stock Cost | AL4: After Stock Qty | AM4: Warehouse | AN4: Promotional Type | AO4: CESS PCT | AP4: CESS AMT | AQ4: PriceClass
A5: 1 | B5: HK-FIFO-LOT-BATCH-10001(FG) | C5: 0 | D5: HK-FIFO-LOT-BATCH-10001(FG) | E5: NOS | F5: NOS | G5: 12 | H5: 23 | I5: =G5*H5 -> 276 | J5: 1 | K5: 2 | L5: 4 | M5: =I5 -> 276 | N5: =ROUND((M5*J5)/100,2) -> 2.76 | O5: =I5-N5 -> 273.24 | P5: =ROUND((O5*K5)/100,2) -> 5.46 | Q5: =ROUND(O5-P5,2) -> 267.78 | R5: =ROUND((Q5*L5)/100,2) -> 10.71 | S5: =N5+P5+R5 -> 18.93 | T5: =ROUND(S5/G5,2) -> 1.58 | U5: =(I5-S5) -> 257.07 | V5: HSN1 | W5: 0.12 | X5: =IF(OR($D$3=1,$D$3=4),ROUND((U5*W5)/2,2),0) -> 0 | Y5: =IF($D$3=1,ROUND(((U5*W5)/2),2),0) -> 0 | Z5: =IF($D$3=2,ROUND(((U5*W5)),2),0) -> 0 | AA5: =IF($D$3=4,ROUND(((U5*W5)/2),2),0) -> 0 | AB5: 0.06 | AC5: =IF($D$3=5,ROUND(((U5*AB5)/2),2),0) -> 0 | AD5: =X5+Y5+Z5+AA5+AC5 -> 0 | AE5: =U5+AD5 -> 257.07 | AF5: 120 | AG5: =U5*$N$3 -> 257.07 | AH5: 1 | AI5: =G5/AH5 -> 12 | AJ5: 848 | AK5: 235.36857 | AL5: =ROUND(AJ5-G5,0) -> 836 | AM5: F100 | AN5: Sales Regular | AO5: 0 | AP5: =ROUND(((AO5*U5)/100),2) -> 0 | AQ5: DOMESTIC
A6: 2 | B6: HK-FG-DISSIMILAR-10001 | C6: 0 | D6: HK-FG-DISSIMILAR-10001 | E6: KGS | F6: NOS | G6: 13 | H6: 34 | I6: =G6*H6 -> 442 | J6: 2 | K6: 7 | L6: 9 | M6: =I6 -> 442 | N6: =ROUND((M6*J6)/100,2) -> 8.84 | O6: =I6-N6 -> 433.16 | P6: =ROUND((O6*K6)/100,2) -> 30.32 | Q6: =ROUND(O6-P6,2) -> 402.84 | R6: =ROUND((Q6*L6)/100,2) -> 36.26 | S6: =N6+P6+R6 -> 75.42 | T6: =ROUND(S6/G6,2) -> 5.8 | U6: =(I6-S6) -> 366.58 | V6: HSN1 | W6: 0.05 | X6: =IF(OR($D$3=1,$D$3=4),ROUND((U6*W6)/2,2),0) -> 0 | Y6: =IF($D$3=1,ROUND(((U6*W6)/2),2),0) -> 0 | Z6: =IF($D$3=2,ROUND(((U6*W6)),2),0) -> 0 | AA6: =IF($D$3=4,ROUND(((U6*W6)/2),2),0) -> 0 | AB6: 0.06 | AC6: =IF($D$3=5,ROUND(((U6*AB6)/2),2),0) -> 0 | AD6: =X6+Y6+Z6+AA6+AC6 -> 0 | AE6: =U6+AD6 -> 366.58 | AF6: 120 | AG6: =U6*$N$3 -> 366.58 | AH6: 3 | AI6: =ROUND(G6/AH6,3) -> 4.333 | AJ6: 1375.002 | AK6: 123 | AL6: =ROUND((AJ6-AI6),3) -> 1370.669 | AM6: F100 | AN6: Sales Regular | AO6: 0 | AP6: =ROUND(((AO6*U6)/100),2) -> 0 | AQ6: DOMESTIC
Q7: DISC AMOUNT | S7: =SUM(S5:S6) -> 94.35 | Z7: NET AMOUNT | AE7: =SUM(AE5:AE6) -> 623.65 | AF7: SALES AMOUNT | AG7: =AG5 -> 257.07

Sheet SO Domestic UD (S&D)
A1: Scenario : Local Sales - Stock UOM and Sales UOM (Similar) DOC NO : SORD-2425-00089
A2: Sales Order
A3: GST Sales | D3: 2 | E3: (1 - Local Sales,2 Interstate Sales, 3 Export Sales) | J3: Cur. | K3: INR | M3: Ex. Rate | N3: 1
A4: S. No. | B4: Item | C4: Rev | D4: Item Desc. | E4: Stk. UOM | F4: Sale. UOM | G4: Order Qty (Sale UOM) | H4: Unit Price | I4: Gross Amt. | J4: TD% | K4: SD% | L4: CD% | M4: TD Asbl. Val. | N4: TD Amt. | O4: SD Asbl. Val. | P4: SD Amt. | Q4: CD Asbl. Val. | R4: CD Amt. | S4: Disc. Amt. | T4: Disc.Amt.Per.Qty | U4: Sales Val. | V4: HSN | W4: Tax Rate | X4: CGST | Y4: SGST | Z4: IGST | AA4: UTGST | AB4: CESS % | AC4: CESS AMT | AD4: Tax amt | AE4: Net Amt | AF4: Weight/Vol | AG4: Sales Amt (BC) | AH4: Conv. Factor | AI4: Eqv. Stock Qty | AJ4: Before Stock Qty | AK4: Before Stock Cost | AL4: After Stock Qty | AM4: Warehouse | AN4: Promotional Type | AO4: CESS PCT | AP4: CESS AMT | AQ4: PriceClass
A5: 1 | B5: HK-FIFO-LOT-BATCH-10001(FG) | C5: 0 | D5: HK-FIFO-LOT-BATCH-10001(FG) | E5: NOS | F5: NOS | G5: 10 | H5: 1234 | I5: =G5*H5 -> 12340 | J5: 1 | K5: 2 | L5: 4 | M5: =I5 -> 12340 | N5: =ROUND((M5*J5)/100,2) -> 123.4 | O5: =I5-N5 -> 12216.6 | P5: =ROUND((O5*K5)/100,2) -> 244.33 | Q5: =ROUND(O5-P5,2) -> 11972.27 | R5: =ROUND((Q5*L5)/100,2) -> 478.89 | S5: =N5+P5+R5 -> 846.62 | T5: =ROUND(S5/G5,2) -> 84.66 | U5: =(I5-S5) -> 11493.38 | V5: HSN1 | W5: 0.12 | X5: =IF(OR($D$3=1,$D$3=4),ROUND((U5*W5)/2,2),0) -> 0 | Y5: =IF($D$3=1,ROUND(((U5*W5)/2),2),0) -> 0 | Z5: =IF($D$3=2,ROUND(((U5*W5)),2),0) -> 1379.21 | AA5: =IF($D$3=4,ROUND(((U5*W5)/2),2),0) -> 0 | AB5: 0.06 | AC5: =IF($D$3=5,ROUND(((U5*AB5)/2),2),0) -> 0 | AD5: =X5+Y5+Z5+AA5+AC5 -> 1379.21 | AE5: =U5+AD5 -> 12872.59 | AF5: 120 | AG5: =U5*$N$3 -> 11493.38 | AH5: 1 | AI5: =G5/AH5 -> 10 | AJ5: 848 | AK5: 235.36857 | AL5: =ROUND(AJ5-G5,0) -> 838 | AM5: F100 | AN5: Sales Regular | AO5: 0 | AP5: =ROUND(((AO5*U5)/100),2) -> 0 | AQ5: DOMESTIC
A6: 2 | B6: HK-FG-DISSIMILAR-10001 | C6: 0 | D6: HK-FG-DISSIMILAR-10001 | E6: KGS | F6: NOS | G6: 10 | H6: 3214 | I6: =G6*H6 -> 32140 | J6: 2 | K6: 7 | L6: 9 | M6: =I6 -> 32140 | N6: =ROUND((M6*J6)/100,2) -> 642.8 | O6: =I6-N6 -> 31497.2 | P6: =ROUND((O6*K6)/100,2) -> 2204.8 | Q6: =ROUND(O6-P6,2) -> 29292.4 | R6: =ROUND((Q6*L6)/100,2) -> 2636.32 | S6: =N6+P6+R6 -> 5483.92 | T6: =ROUND(S6/G6,2) -> 548.39 | U6: =(I6-S6) -> 26656.08 | V6: HSN1 | W6: 0.05 | X6: =IF(OR($D$3=1,$D$3=4),ROUND((U6*W6)/2,2),0) -> 0 | Y6: =IF($D$3=1,ROUND(((U6*W6)/2),2),0) -> 0 | Z6: =IF($D$3=2,ROUND(((U6*W6)),2),0) -> 1332.8 | AA6: =IF($D$3=4,ROUND(((U6*W6)/2),2),0) -> 0 | AB6: 0.06 | AC6: =IF($D$3=5,ROUND(((U6*AB6)/2),2),0) -> 0 | AD6: =X6+Y6+Z6+AA6+AC6 -> 1332.8 | AE6: =U6+AD6 -> 27988.88 | AF6: 120 | AG6: =U6*$N$3 -> 26656.08 | AH6: 3 | AI6: =ROUND(G6/AH6,3) -> 3.333 | AJ6: 1375.002 | AK6: 123 | AL6: =ROUND((AJ6-AI6),3) -> 1371.669 | AM6: F100 | AN6: Sales Regular | AO6: 0 | AP6: =ROUND(((AO6*U6)/100),2) -> 0 | AQ6: DOMESTIC
Q7: DISC AMOUNT | Z7: NET AMOUNT | AE7: =SUM(AE5:AE6) -> 40861.47 | AF7: SALES AMOUNT | AG7: =AG5 -> 11493.38

Sheet Case 1
A1: Scenario : Local Sales - Stock UOM and Sales UOM (Similar) DOC NO : SORD-2425-00089
A2: Sales Order
A3: GST Sales | D3: 2 | E3: (1 - Local Sales,2 Interstate Sales, 3 Export Sales) | J3: Cur. | K3: INR | M3: Ex. Rate | N3: 1
A4: S. No. | B4: Item | C4: Rev | D4: Item Desc. | E4: Stk. UOM | F4: Sale. UOM | G4: Order Qty (Sale UOM) | H4: Unit Price | I4: Gross Amt. | J4: TD% | K4: SD% | L4: CD% | M4: TD Asbl. Val. | N4: TD Amt. | O4: SD Asbl. Val. | P4: SD Amt. | Q4: CD Asbl. Val. | R4: CD Amt. | S4: Disc. Amt. | T4: Disc.Amt.Per.Qty | U4: Sales Val. | V4: HSN | W4: Tax Rate | X4: CGST | Y4: SGST | Z4: IGST | AA4: UTGST | AB4: CESS % | AC4: CESS AMT | AD4: Tax amt | AE4: Net Amt | AF4: Weight/Vol | AG4: Sales Amt (BC) | AH4: Conv. Factor | AI4: Eqv. Stock Qty | AJ4: Before Stock Qty | AK4: Before Stock Cost | AL4: After Stock Qty | AM4: Warehouse | AN4: Promotional Type | AO4: CESS PCT | AP4: CESS AMT | AQ4: PriceClass
A5: 1 | B5: HK-FIFO-LOT-BATCH-10001(FG) | C5: 0 | D5: HK-FIFO-LOT-BATCH-10001(FG) | E5: NOS | F5: NOS | G5: 10 | H5: 1234 | I5: =G5*H5 -> 12340 | J5: 1 | K5: 2 | L5: 4 | M5: =I5 -> 12340 | N5: =ROUND((M5*J5)/100,2) -> 123.4 | O5: =I5-N5 -> 12216.6 | P5: =ROUND((O5*K5)/100,2) -> 244.33 | Q5: =ROUND(O5-P5,2) -> 11972.27 | R5: =ROUND((Q5*L5)/100,2) -> 478.89 | S5: =N5+P5+R5 -> 846.62 | T5: =ROUND(S5/G5,2) -> 84.66 | U5: =(I5-S5) -> 11493.38 | V5: HSN1 | W5: 0.12 | X5: =IF(OR($D$3=1,$D$3=4),ROUND((U5*W5)/2,2),0) -> 0 | Y5: =IF($D$3=1,ROUND(((U5*W5)/2),2),0) -> 0 | Z5: =IF($D$3=2,ROUND(((U5*W5)),2),0) -> 1379.21 | AA5: =IF($D$3=4,ROUND(((U5*W5)/2),2),0) -> 0 | AB5: 0.06 | AC5: =IF($D$3=5,ROUND(((U5*AB5)/2),2),0) -> 0 | AD5: =X5+Y5+Z5+AA5+AC5 -> 1379.21 | AE5: =U5+AD5 -> 12872.59 | AF5: 120 | AG5: =U5*$N$3 -> 11493.38 | AH5: 1 | AI5: =G5/AH5 -> 10 | AJ5: 848 | AK5: 235.36857 | AL5: =ROUND(AJ5-G5,0) -> 902 | AM5: F100 | AN5: Sales Regular | AO5: 0 | AP5: =ROUND(((AO5*U5)/100),2) -> 0 | AQ5: DOMESTIC
A6: 2 | B6: HK-FG-DISSIMILAR-10001 | C6: 0 | D6: HK-FG-DISSIMILAR-10001 | E6: KGS | F6: NOS | G6: 10 | H6: 3214 | I6: =G6*H6 -> 32140 | J6: 2 | K6: 7 | L6: 9 | M6: =I6 -> 32140 | N6: =ROUND((M6*J6)/100,2) -> 642.8 | O6: =I6-N6 -> 31497.2 | P6: =ROUND((O6*K6)/100,2) -> 2204.8 | Q6: =ROUND(O6-P6,2) -> 29292.4 | R6: =ROUND((Q6*L6)/100,2) -> 2636.32 | S6: =N6+P6+R6 -> 5483.92 | T6: =ROUND(S6/G6,2) -> 548.39 | U6: =(I6-S6) -> 26656.08 | V6: HSN1 | W6: 0.05 | X6: =IF(OR($D$3=1,$D$3=4),ROUND((U6*W6)/2,2),0) -> 0 | Y6: =IF($D$3=1,ROUND(((U6*W6)/2),2),0) -> 0 | Z6: =IF($D$3=2,ROUND(((U6*W6)),2),0) -> 1332.8 | AA6: =IF($D$3=4,ROUND(((U6*W6)/2),2),0) -> 0 | AB6: 0.06 | AC6: =IF($D$3=5,ROUND(((U6*AB6)/2),2),0) -> 0 | AD6: =X6+Y6+Z6+AA6+AC6 -> 1332.8 | AE6: =U6+AD6 -> 27988.88 | AF6: 120 | AG6: =U6*$N$3 -> 26656.08 | AH6: 3 | AI6: =ROUND(G6/AH6,3) -> 3.333 | AJ6: 1375.002 | AK6: 123 | AL6: =ROUND((AJ6-AI6),3) -> 1371.669 | AM6: F100 | AN6: Sales Regular | AO6: 0 | AP6: =ROUND(((AO6*U6)/100),2) -> 0 | AQ6: DOMESTIC
Q7: DISC AMOUNT | Z7: NET AMOUNT | AE7: =SUM(AE5:AE6) -> 40861.47 | AF7: SALES AMOUNT | AG7: =AG5 -> 11493.38

Sheet Item Stocks
A1: S. No. | B1: Item | C1: Rev | D1: Item Desc. | E1: Order Qty | F1: Unit Cost | G1: Before Stock Qty | H1: After Stock Qty
A2: ='Case 1'!A5 -> 1 | B2: ='Case 1'!B5 -> HK-FIFO-LOT-BATCH-10001(FG) | C2: ='Case 1'!C5 -> 0 | D2: ='Case 1'!D5 -> HK-FIFO-LOT-BATCH-10001(FG) | E2: 20 | F2: ='Case 1'!H5 -> 1234 | G2: 2954.00 | H2: =G2-E2 -> 4547
A3: ='Case 1'!A6 -> 2 | B3: ='Case 1'!B6 -> HK-FG-DISSIMILAR-10001 | C3: ='Case 1'!C6 -> 0 | D3: ='Case 1'!D6 -> HK-FG-DISSIMILAR-10001 | E3: 30 | F3: ='Case 1'!H6 -> 3214 | G3: 675 | H3: =G3-E3 -> 645

Sheet SO UTGST
A1: Scenario : Local Sales - Stock UOM and Sales UOM (Similar) DOC NO : SORD-2425-00089
A2: Sales Order
A3: GST Sales | D3: 4 | E3: (1 - Local Sales,2 Interstate Sales, 3 Export Sales) | J3: Cur. | K3: INR | M3: Ex. Rate | N3: 1
A4: S. No. | B4: Item | C4: Rev | D4: Item Desc. | E4: Stk. UOM | F4: Sale. UOM | G4: Order Qty (Sale UOM) | H4: Unit Price | I4: Gross Amt. | J4: TD% | K4: SD% | L4: CD% | M4: TD Asbl. Val. | N4: TD Amt. | O4: SD Asbl. Val. | P4: SD Amt. | Q4: CD Asbl. Val. | R4: CD Amt. | S4: Disc. Amt. | T4: Disc.Amt.Per.Qty | U4: Sales Val. | V4: HSN | W4: Tax Rate | X4: CGST | Y4: SGST | Z4: IGST | AA4: UTGST | AB4: CESS % | AC4: CESS AMT | AD4: Tax amt | AE4: Net Amt | AF4: Weight/Vol | AG4: Sales Amt (BC) | AH4: Conv. Factor | AI4: Eqv. Stock Qty | AJ4: Before Stock Qty | AK4: Before Stock Cost | AL4: After Stock Qty | AM4: Warehouse | AN4: Promotional Type | AO4: CESS PCT | AP4: CESS AMT | AQ4: PriceClass
A5: 1 | B5: HK-FIFO-LOT-BATCH-10001(FG) | C5: 0 | D5: HK-FIFO-LOT-BATCH-10001(FG) | E5: NOS | F5: NOS | G5: 10 | H5: 1234 | I5: =G5*H5 -> 12340 | J5: 1 | K5: 2 | L5: 4 | M5: =I5 -> 12340 | N5: =ROUND((M5*J5)/100,2) -> 123.4 | O5: =I5-N5 -> 12216.6 | P5: =ROUND((O5*K5)/100,2) -> 244.33 | Q5: =ROUND(O5-P5,2) -> 11972.27 | R5: =ROUND((Q5*L5)/100,2) -> 478.89 | S5: =N5+P5+R5 -> 846.62 | T5: =ROUND(S5/G5,2) -> 84.66 | U5: =(I5-S5) -> 11493.38 | V5: (740410)-18% | W5: 0.12 | X5: =IF(OR($D$3=1,$D$3=4),ROUND((U5*W5)/2,2),0) -> 689.6 | Y5: =IF($D$3=1,ROUND(((U5*W5)/2),2),0) -> 0 | Z5: =IF($D$3=2,ROUND(((U5*W5)),2),0) -> 0 | AA5: =IF($D$3=4,ROUND(((U5*W5)/2),2),0) -> 689.6 | AB5: 0.06 | AC5: =IF($D$3=5,ROUND(((U5*AB5)/2),2),0) -> 0 | AD5: =X5+Y5+Z5+AA5+AC5 -> 1379.2 | AE5: =U5+AD5 -> 12872.58 | AF5: 120 | AG5: =U5*$N$3 -> 11493.38 | AH5: 1 | AI5: =G5/AH5 -> 10 | AJ5: 848 | AK5: 235.36857 | AL5: =ROUND(AJ5-G5,0) -> 838 | AM5: F100 | AN5: Sales Regular | AO5: 0 | AP5: =ROUND(((AO5*U5)/100),2) -> 0 | AQ5: DOMESTIC
A6: 2 | B6: HK-FG-DISSIMILAR-10001 | C6: 0 | D6: HK-FG-DISSIMILAR-10001 | E6: KGS | F6: NOS | G6: 20 | H6: 3214 | I6: =G6*H6 -> 64280 | J6: 2 | K6: 7 | L6: 9 | M6: =I6 -> 64280 | N6: =ROUND((M6*J6)/100,2) -> 1285.6 | O6: =I6-N6 -> 62994.4 | P6: =ROUND((O6*K6)/100,2) -> 4409.61 | Q6: =ROUND(O6-P6,2) -> 58584.79 | R6: =ROUND((Q6*L6)/100,2) -> 5272.63 | S6: =N6+P6+R6 -> 10967.84 | T6: =ROUND(S6/G6,2) -> 548.39 | U6: =(I6-S6) -> 53312.16 | V6: 772213 | W6: 0.05 | X6: =IF(OR($D$3=1,$D$3=4),ROUND((U6*W6)/2,2),0) -> 1332.8 | Y6: =IF($D$3=1,ROUND(((U6*W6)/2),2),0) -> 0 | Z6: =IF($D$3=2,ROUND(((U6*W6)),2),0) -> 0 | AA6: =IF($D$3=4,ROUND(((U6*W6)/2),2),0) -> 1332.8 | AB6: 0.06 | AC6: =IF($D$3=5,ROUND(((U6*AB6)/2),2),0) -> 0 | AD6: =X6+Y6+Z6+AA6+AC6 -> 2665.6 | AE6: =U6+AD6 -> 55977.76 | AF6: 120 | AG6: =U6*$N$3 -> 53312.16 | AH6: 3 | AI6: =ROUND(G6/AH6,3) -> 6.667 | AJ6: 1375.002 | AK6: 123 | AL6: =ROUND((AJ6-AI6),3) -> 1368.335 | AM6: F100 | AN6: Sales Regular | AO6: 0 | AP6: =ROUND(((AO6*U6)/100),2) -> 0 | AQ6: DOMESTIC
Q7: DISC AMOUNT | S7: =SUM(S5:S6) -> 11814.46 | Z7: NET AMOUNT | AE7: =SUM(AE5:AE6) -> 68850.34 | AF7: SALES AMOUNT | AG7: =AG5 -> 11493.38

Sheet Free Sample
A1: Scenario : Local Sales - Stock UOM and Sales UOM (Similar) DOC NO : SORD-2425-00089
A2: Sales Order
A3: GST Sales | D3: 2 | E3: (1 - Local Sales,2 Interstate Sales, 3 Export Sales) | J3: Cur. | K3: INR | M3: Ex. Rate | N3: 1
A4: S. No. | B4: Item | C4: Rev | D4: Item Desc. | E4: Stk. UOM | F4: Sale. UOM | G4: Order Qty (Sale UOM) | H4: Unit Price | I4: Gross Amt. | J4: TD% | K4: SD% | L4: CD% | M4: TD Asbl. Val. | N4: TD Amt. | O4: SD Asbl. Val. | P4: SD Amt. | Q4: CD Asbl. Val. | R4: CD Amt. | S4: Disc. Amt. | T4: Disc.Amt.Per.Qty | U4: Sales Val. | V4: HSN | W4: Tax Rate | X4: CGST | Y4: SGST | Z4: IGST | AA4: UTGST | AB4: CESS % | AC4: CESS AMT | AD4: Tax amt | AE4: Net Amt | AF4: Weight/Vol | AG4: Sales Amt (BC) | AH4: Conv. Factor | AI4: Eqv. Stock Qty | AJ4: Before Stock Qty | AK4: Before Stock Cost | AL4: After Stock Qty | AM4: Warehouse | AN4: Promotional Type | AO4: CESS PCT | AP4: CESS AMT | AQ4: PriceClass
A5: 1 | B5: HK-FIFO-LOT-BATCH-10001(FG) | C5: 0 | D5: HK-FIFO-LOT-BATCH-10001(FG) | E5: NOS | F5: NOS | G5: 10 | H5: 2333 | I5: =G5*H5 -> 23330 | J5: 0 | K5: 0 | L5: 0 | M5: =I5 -> 23330 | N5: =ROUND((M5*J5)/100,2) -> 0 | O5: =I5-N5 -> 23330 | P5: =ROUND((O5*K5)/100,2) -> 0 | Q5: =ROUND(O5-P5,2) -> 23330 | R5: =ROUND((Q5*L5)/100,2) -> 0 | S5: =N5+P5+R5 -> 0 | T5: =ROUND(S5/G5,2) -> 0 | U5: =(I5-S5) -> 23330 | V5: HSN1 | W5: 0.12 | X5: =IF(OR($D$3=1,$D$3=4),ROUND((U5*W5)/2,2),0) -> 0 | Y5: =IF($D$3=1,ROUND(((U5*W5)/2),2),0) -> 0 | Z5: =IF($D$3=2,ROUND(((U5*W5)),2),0) -> 2799.6 | AA5: =IF($D$3=4,ROUND(((U5*W5)/2),2),0) -> 0 | AB5: 0.06 | AC5: =IF($D$3=5,ROUND(((U5*AB5)/2),2),0) -> 0 | AD5: =X5+Y5+Z5+AA5+AC5 -> 2799.6 | AE5: =U5+AD5 -> 26129.6 | AF5: 120 | AG5: =U5*$N$3 -> 23330 | AH5: 1 | AI5: =G5/AH5 -> 10 | AJ5: 848 | AK5: 235.36857 | AL5: =ROUND(AJ5-G5,0) -> 838 | AM5: F100 | AN5: Sales Regular | AO5: 0 | AP5: =ROUND(((AO5*U5)/100),2) -> 0 | AQ5: DOMESTIC
A6: 2 | B6: HK-FG-DISSIMILAR-10001 | C6: 0 | D6: HK-FG-DISSIMILAR-10001 | E6: KGS | F6: NOS | G6: 10 | H6: 4319 | I6: =G6*H6 -> 43190 | J6: 0 | K6: 0 | L6: 0 | M6: =I6 -> 43190 | N6: =ROUND((M6*J6)/100,2) -> 0 | O6: =I6-N6 -> 43190 | P6: =ROUND((O6*K6)/100,2) -> 0 | Q6: =ROUND(O6-P6,2) -> 43190 | R6: =ROUND((Q6*L6)/100,2) -> 0 | S6: =N6+P6+R6 -> 0 | T6: =ROUND(S6/G6,2) -> 0 | U6: =(I6-S6) -> 43190 | V6: HSN1 | W6: 0.05 | X6: =IF(OR($D$3=1,$D$3=4),ROUND((U6*W6)/2,2),0) -> 0 | Y6: =IF($D$3=1,ROUND(((U6*W6)/2),2),0) -> 0 | Z6: =IF($D$3=2,ROUND(((U6*W6)),2),0) -> 2159.5 | AA6: =IF($D$3=4,ROUND(((U6*W6)/2),2),0) -> 0 | AB6: 0.06 | AC6: =IF($D$3=5,ROUND(((U6*AB6)/2),2),0) -> 0 | AD6: =X6+Y6+Z6+AA6+AC6 -> 2159.5 | AE6: =U6+AD6 -> 45349.5 | AF6: 120 | AG6: =U6*$N$3 -> 43190 | AH6: 3 | AI6: =ROUND(G6/AH6,3) -> 3.333 | AJ6: 1375.002 | AK6: 123 | AL6: =ROUND((AJ6-AI6),3) -> 1371.669 | AM6: F100 | AN6: Sales Regular | AO6: 0 | AP6: =ROUND(((AO6*U6)/100),2) -> 0 | AQ6: DOMESTIC
Q7: DISC AMOUNT | Z7: NET AMOUNT | AE7: =SUM(AE5:AE6) -> 71479.1 | AF7: SALES AMOUNT | AG7: =AG5 -> 23330

Sheet Free Replacement
A1: Scenario : Local Sales - Stock UOM and Sales UOM (Similar) DOC NO : SORD-2425-00089
A2: Sales Order
A3: GST Sales | D3: 2 | E3: (1 - Local Sales,2 Interstate Sales, 3 Export Sales) | J3: Cur. | K3: INR | M3: Ex. Rate | N3: 1
A4: S. No. | B4: Item | C4: Rev | D4: Item Desc. | E4: Stk. UOM | F4: Sale. UOM | G4: Order Qty (Sale UOM) | H4: Unit Price | I4: Gross Amt. | J4: TD% | K4: SD% | L4: CD% | M4: TD Asbl. Val. | N4: TD Amt. | O4: SD Asbl. Val. | P4: SD Amt. | Q4: CD Asbl. Val. | R4: CD Amt. | S4: Disc. Amt. | T4: Disc.Amt.Per.Qty | U4: Sales Val. | V4: HSN | W4: Tax Rate | X4: CGST | Y4: SGST | Z4: IGST | AA4: UTGST | AB4: CESS % | AC4: CESS AMT | AD4: Tax amt | AE4: Net Amt | AF4: Weight/Vol | AG4: Sales Amt (BC) | AH4: Conv. Factor | AI4: Eqv. Stock Qty | AJ4: Before Stock Qty | AK4: Before Stock Cost | AL4: After Stock Qty | AM4: Warehouse | AN4: Promotional Type | AO4: CESS PCT | AP4: CESS AMT | AQ4: PriceClass
A5: 1 | B5: HK-FIFO-LOT-BATCH-10001(FG) | C5: 0 | D5: HK-FIFO-LOT-BATCH-10001(FG) | E5: NOS | F5: NOS | G5: 10 | H5: 1500 | I5: =G5*H5 -> 15000 | J5: 0 | K5: 0 | L5: 0 | M5: =I5 -> 15000 | N5: =ROUND((M5*J5)/100,2) -> 0 | O5: =I5-N5 -> 15000 | P5: =ROUND((O5*K5)/100,2) -> 0 | Q5: =ROUND(O5-P5,2) -> 15000 | R5: =ROUND((Q5*L5)/100,2) -> 0 | S5: =N5+P5+R5 -> 0 | T5: =ROUND(S5/G5,2) -> 0 | U5: =(I5-S5) -> 15000 | V5: HSN1 | W5: 0.12 | X5: =IF(OR($D$3=1,$D$3=4),ROUND((U5*W5)/2,2),0) -> 0 | Y5: =IF($D$3=1,ROUND(((U5*W5)/2),2),0) -> 0 | Z5: =IF($D$3=2,ROUND(((U5*W5)),2),0) -> 1800 | AA5: =IF($D$3=4,ROUND(((U5*W5)/2),2),0) -> 0 | AB5: 0.06 | AC5: =IF($D$3=5,ROUND(((U5*AB5)/2),2),0) -> 0 | AD5: =X5+Y5+Z5+AA5+AC5 -> 1800 | AE5: =U5+AD5 -> 16800 | AF5: 120 | AG5: =U5*$N$3 -> 15000 | AH5: 1 | AI5: =G5/AH5 -> 10 | AJ5: 848 | AK5: 235.36857 | AL5: =ROUND(AJ5-G5,0) -> 838 | AM5: F100 | AN5: Sales Regular | AO5: 0 | AP5: =ROUND(((AO5*U5)/100),2) -> 0 | AQ5: DOMESTIC
A6: 2 | B6: HK-FG-DISSIMILAR-10001 | C6: 0 | D6: HK-FG-DISSIMILAR-10001 | E6: KGS | F6: NOS | G6: 10 | H6: 2000 | I6: =G6*H6 -> 20000 | J6: 0 | K6: 0 | L6: 0 | M6: =I6 -> 20000 | N6: =ROUND((M6*J6)/100,2) -> 0 | O6: =I6-N6 -> 20000 | P6: =ROUND((O6*K6)/100,2) -> 0 | Q6: =ROUND(O6-P6,2) -> 20000 | R6: =ROUND((Q6*L6)/100,2) -> 0 | S6: =N6+P6+R6 -> 0 | T6: =ROUND(S6/G6,2) -> 0 | U6: =(I6-S6) -> 20000 | V6: HSN1 | W6: 0.05 | X6: =IF(OR($D$3=1,$D$3=4),ROUND((U6*W6)/2,2),0) -> 0 | Y6: =IF($D$3=1,ROUND(((U6*W6)/2),2),0) -> 0 | Z6: =IF($D$3=2,ROUND(((U6*W6)),2),0) -> 1000 | AA6: =IF($D$3=4,ROUND(((U6*W6)/2),2),0) -> 0 | AB6: 0.06 | AC6: =IF($D$3=5,ROUND(((U6*AB6)/2),2),0) -> 0 | AD6: =X6+Y6+Z6+AA6+AC6 -> 1000 | AE6: =U6+AD6 -> 21000 | AF6: 120 | AG6: =U6*$N$3 -> 20000 | AH6: 3 | AI6: =ROUND(G6/AH6,3) -> 3.333 | AJ6: 1375.002 | AK6: 123 | AL6: =ROUND((AJ6-AI6),3) -> 1371.669 | AM6: F100 | AN6: Sales Regular | AO6: 0 | AP6: =ROUND(((AO6*U6)/100),2) -> 0 | AQ6: DOMESTIC
Q7: DISC AMOUNT | Z7: NET AMOUNT | AE7: =SUM(AE5:AE6) -> 37800 | AF7: SALES AMOUNT | AG7: =AG5 -> 15000

Sheet SCRAP
A1: Scenario : Local Sales - Stock UOM and Sales UOM (Similar) DOC NO : SORD-2425-00089
A2: Sales Order
A3: GST Sales | D3: 2 | E3: (1 - Local Sales,2 Interstate Sales, 3 Import Sales) | J3: Cur. | K3: INR | M3: Ex. Rate | N3: 1
A4: S. No. | B4: Item | C4: Rev | D4: Item Desc. | E4: Stk. UOM | F4: Sale. UOM | G4: Order Qty (Sale UOM) | H4: Unit Price | I4: Gross Amt. | J4: TD% | K4: SD% | L4: CD% | M4: TD Asbl. Val. | N4: TD Amt. | O4: SD Asbl. Val. | P4: SD Amt. | Q4: CD Asbl. Val. | R4: CD Amt. | S4: Disc. Amt. | T4: Disc.Amt.Per.Qty | U4: Sales Val. | V4: HSN | W4: Tax Rate | X4: CGST | Y4: SGST | Z4: IGST | AA4: UTGST | AB4: CESS % | AC4: CESS AMT | AD4: Tax amt | AE4: Net Amt | AF4: Weight/Vol | AG4: Sales Amt (BC) | AH4: Conv. Factor | AI4: Eqv. Stock Qty | AJ4: Before Stock Qty | AK4: Before Stock Cost | AL4: After Stock Qty | AM4: Warehouse | AN4: Promotional Type | AO4: CESS PCT | AP4: CESS AMT | AQ4: PriceClass
A5: 1 | B5: HK-TVS-SCRAP-10001 | C5: 0 | D5: HK-TVS-SCRAP-10001 | E5: KGS | F5: KGS | G5: 10 | H5: 1500 | I5: =G5*H5 -> 15000 | J5: 1 | K5: 2 | L5: 9 | M5: =I5 -> 15000 | N5: =ROUND((M5*J5)/100,2) -> 150 | O5: =I5-N5 -> 14850 | P5: =ROUND((O5*K5)/100,2) -> 297 | Q5: =ROUND(O5-P5,2) -> 14553 | R5: =ROUND((Q5*L5)/100,2) -> 1309.77 | S5: =N5+P5+R5 -> 1756.77 | T5: =ROUND(S5/G5,2) -> 175.68 | U5: =(I5-S5) -> 13243.23 | V5: HSN1 | W5: 0.05 | X5: =IF(OR($D$3=1,$D$3=4),ROUND((U5*W5)/2,2),0) -> 0 | Y5: =IF($D$3=1,ROUND(((U5*W5)/2),2),0) -> 0 | Z5: =IF($D$3=2,ROUND(((U5*W5)),2),0) -> 662.16 | AA5: =IF($D$3=4,ROUND(((U5*W5)/2),2),0) -> 0 | AB5: 0.06 | AC5: =IF($D$3=5,ROUND(((U5*AB5)/2),2),0) -> 0 | AD5: =X5+Y5+Z5+AA5+AC5 -> 662.16 | AE5: =U5+AD5 -> 13905.39 | AF5: 120 | AG5: =U5*$N$3 -> 13243.23 | AH5: 1 | AI5: =G5/AH5 -> 10 | AJ5: 848 | AK5: 235.36857 | AL5: =ROUND(AJ5-G5,0) -> 838 | AM5: F100 | AN5: Sales Regular | AO5: 0 | AP5: =ROUND(((AO5*U5)/100),2) -> 0 | AQ5: DOMESTIC
Q6: DISC AMOUNT | Z6: NET AMOUNT | AB6: =SUM(AB5:AB5) -> 0.06 | AC6: SALES AMOUNT | AD6: =AD5 -> 662.16

Sheet SERVICE
A1: Scenario : Local Sales - Stock UOM and Sales UOM (Similar) DOC NO : SORD-2425-00089
A2: Sales Order
A3: GST Sales | D3: 2 | E3: (1 - Local Sales,2 Interstate Sales, 3 Import Sales) | J3: Cur. | K3: INR | M3: Ex. Rate | N3: 1
A4: S. No. | B4: Item | C4: Rev | D4: Item Desc. | E4: Stk. UOM | F4: Sale. UOM | G4: Order Qty (Sale UOM) | H4: Unit Price | I4: Gross Amt. | J4: TD% | K4: SD% | L4: CD% | M4: TD Asbl. Val. | N4: TD Amt. | O4: SD Asbl. Val. | P4: SD Amt. | Q4: CD Asbl. Val. | R4: CD Amt. | S4: Disc. Amt. | T4: Disc.Amt.Per.Qty | U4: Sales Val. | V4: HSN | W4: Tax Rate | X4: CGST | Y4: SGST | Z4: IGST | AA4: UTGST | AB4: CESS % | AC4: CESS AMT | AD4: Tax amt | AE4: Net Amt | AF4: Weight/Vol | AG4: Sales Amt (BC) | AH4: Conv. Factor | AI4: Eqv. Stock Qty | AJ4: Before Stock Qty | AK4: Before Stock Cost | AL4: After Stock Qty | AM4: Warehouse | AN4: Promotional Type | AO4: CESS PCT | AP4: CESS AMT | AQ4: PriceClass
A5: 1 | B5: TVS-SER-10001 | C5: 0 | D5: TVS-SER-10001 | E5: NOS | F5: NOS | G5: 10 | H5: 1500 | I5: =G5*H5 -> 15000 | J5: 2 | K5: 3 | L5: 7 | M5: =I5 -> 15000 | N5: =ROUND((M5*J5)/100,2) -> 300 | O5: =I5-N5 -> 14700 | P5: =ROUND((O5*K5)/100,2) -> 441 | Q5: =ROUND(O5-P5,2) -> 14259 | R5: =ROUND((Q5*L5)/100,2) -> 998.13 | S5: =N5+P5+R5 -> 1739.13 | T5: =ROUND(S5/G5,2) -> 173.91 | U5: =(I5-S5) -> 13260.87 | V5: HSN1 | W5: 0.05 | X5: =IF(OR($D$3=1,$D$3=4),ROUND((U5*W5)/2,2),0) -> 0 | Y5: =IF($D$3=1,ROUND(((U5*W5)/2),2),0) -> 0 | Z5: =IF($D$3=2,ROUND(((U5*W5)),2),0) -> 663.04 | AA5: =IF($D$3=4,ROUND(((U5*W5)/2),2),0) -> 0 | AB5: 0.06 | AC5: =IF($D$3=5,ROUND(((U5*AB5)/2),2),0) -> 0 | AD5: =X5+Y5+Z5+AA5+AC5 -> 663.04 | AE5: =U5+AD5 -> 13923.91 | AF5: 120 | AG5: =U5*$N$3 -> 13260.87 | AH5: 1 | AI5: =G5/AH5 -> 10 | AJ5: 848 | AK5: 235.36857 | AL5: =ROUND(AJ5-G5,0) -> 838 | AM5: F100 | AN5: Sales Regular | AO5: 0 | AP5: =ROUND(((AO5*U5)/100),2) -> 0 | AQ5: DOMESTIC
Q6: DISC AMOUNT | Z6: NET AMOUNT | AB6: =SUM(AB5:AB5) -> 0.06 | AC6: SALES AMOUNT | AD6: =AD5 -> 663.04

Sheet PROMOTIONAL
A1: Scenario : Local Sales - Stock UOM and Sales UOM (Similar) DOC NO : SORD-2425-00089
A2: Sales Order
A3: GST Sales | D3: 2 | E3: (1 - Local Sales,2 Interstate Sales, 3 Import Sales) | J3: Cur. | K3: INR | M3: Ex. Rate | N3: 1
A4: S. No. | B4: Item | C4: Rev | D4: Item Desc. | E4: Stk. UOM | F4: Sale. UOM | G4: Order Qty (Sale UOM) | H4: Unit Price | I4: Gross Amt. | J4: TD% | K4: SD% | L4: CD% | M4: TD Asbl. Val. | N4: TD Amt. | O4: SD Asbl. Val. | P4: SD Amt. | Q4: CD Asbl. Val. | R4: CD Amt. | S4: Disc. Amt. | T4: Disc.Amt.Per.Qty | U4: Sales Val. | V4: HSN | W4: Tax Rate | X4: CGST | Y4: SGST | Z4: IGST | AA4: UTGST | AB4: CESS % | AC4: CESS AMT | AD4: Tax amt | AE4: Net Amt | AF4: Weight/Vol | AG4: Sales Amt (BC) | AH4: Conv. Factor | AI4: Eqv. Stock Qty | AJ4: Before Stock Qty | AK4: Before Stock Cost | AL4: After Stock Qty | AM4: Warehouse | AN4: Promotional Type | AO4: CESS PCT | AP4: CESS AMT | AQ4: PriceClass
A5: 1 | B5: HK-FIFO-LOT-BATCH-10001(FG) | C5: 0 | D5: HK-FIFO-LOT-BATCH-10001(FG) | E5: NOS | F5: NOS | G5: 10 | H5: 1500 | I5: =G5*H5 -> 15000 | J5: 1 | K5: 5 | L5: 7 | M5: =I5 -> 15000 | N5: =ROUND((M5*J5)/100,2) -> 150 | O5: =I5-N5 -> 14850 | P5: =ROUND((O5*K5)/100,2) -> 742.5 | Q5: =ROUND(O5-P5,2) -> 14107.5 | R5: =ROUND((Q5*L5)/100,2) -> 987.53 | S5: =N5+P5+R5 -> 1880.03 | T5: =ROUND(S5/G5,2) -> 188 | U5: =(I5-S5) -> 13119.97 | V5: HSN1 | W5: 0.12 | X5: =IF(OR($D$3=1,$D$3=4),ROUND((U5*W5)/2,2),0) -> 0 | Y5: =IF($D$3=1,ROUND(((U5*W5)/2),2),0) -> 0 | Z5: =IF($D$3=2,ROUND(((U5*W5)),2),0) -> 1574.4 | AA5: =IF($D$3=4,ROUND(((U5*W5)/2),2),0) -> 0 | AB5: 0.06 | AC5: =IF($D$3=5,ROUND(((U5*AB5)/2),2),0) -> 0 | AD5: =X5+Y5+Z5+AA5+AC5 -> 1574.4 | AE5: =U5+AD5 -> 14694.37 | AF5: 120 | AG5: =U5*$N$3 -> 13119.97 | AH5: 1 | AI5: =G5/AH5 -> 10 | AJ5: 848 | AK5: 235.36857 | AL5: =ROUND(AJ5-G5,0) -> 838 | AM5: F100 | AN5: Sales Regular | AO5: 0 | AP5: =ROUND(((AO5*U5)/100),2) -> 0 | AQ5: DOMESTIC
A6: 2 | B6: PRO-10001 | C6: 0 | D6: PROMOTIONAL-10001 | E6: NOS | F6: NOS | G6: 10 | H6: 2000 | I6: =G6*H6 -> 20000 | J6: 0 | K6: 0 | L6: 0 | M6: =I6 -> 20000 | N6: =ROUND((M6*J6)/100,2) -> 0 | O6: =I6-N6 -> 20000 | P6: =ROUND((O6*K6)/100,2) -> 0 | Q6: =ROUND(O6-P6,2) -> 20000 | R6: =ROUND((Q6*L6)/100,2) -> 0 | S6: =N6+P6+R6 -> 0 | T6: =ROUND(S6/G6,2) -> 0 | U6: =(I6-S6) -> 20000 | V6: HSN1 | W6: 0.05 | X6: =IF(OR($D$3=1,$D$3=4),ROUND((U6*W6)/2,2),0) -> 0 | Y6: =IF($D$3=1,ROUND(((U6*W6)/2),2),0) -> 0 | Z6: =IF($D$3=2,ROUND(((U6*W6)),2),0) -> 1000 | AA6: =IF($D$3=4,ROUND(((U6*W6)/2),2),0) -> 0 | AB6: 0.06 | AC6: =IF($D$3=5,ROUND(((U6*AB6)/2),2),0) -> 0 | AD6: =X6+Y6+Z6+AA6+AC6 -> 1000 | AE6: =U6+AD6 -> 21000 | AF6: 120 | AG6: =U6*$N$3 -> 20000 | AH6: 3 | AI6: =ROUND(G6/AH6,3) -> 3.333 | AJ6: 1375.002 | AK6: 123 | AL6: =ROUND((AJ6-AI6),3) -> 1371.669 | AM6: F100 | AN6: Promotional | AO6: 0 | AP6: =ROUND(((AO6*U6)/100),2) -> 0 | AQ6: DOMESTIC
Q7: DISC AMOUNT | Z7: NET AMOUNT | AE7: =AE5 -> 14694.37 | AF7: SALES AMOUNT | AG7: =AG5 -> 13119.97

Sheet Local Customer
A1: Scenario : Local Sales - Stock UOM and Sales UOM (Similar) DOC NO : SORD-2425-00089
A2: Sales Order
A3: GST Sales | D3: 1 | E3: (1 - Local Sales,2 Interstate Sales, 3 Import Sales) | J3: Cur. | K3: INR | M3: Ex. Rate | N3: 1
A4: S. No. | B4: Item | C4: Rev | D4: Item Desc. | E4: Stk. UOM | F4: Sale. UOM | G4: Order Qty (Sale UOM) | H4: Unit Price | I4: Gross Amt. | J4: TD% | K4: SD% | L4: CD% | M4: TD Asbl. Val. | N4: TD Amt. | O4: SD Asbl. Val. | P4: SD Amt. | Q4: CD Asbl. Val. | R4: CD Amt. | S4: Disc. Amt. | T4: Disc.Amt.Per.Qty | U4: Sales Val. | V4: HSN | W4: Tax Rate | X4: CGST | Y4: SGST | Z4: IGST | AA4: UTGST | AB4: CESS % | AC4: CESS AMT | AD4: Tax amt | AE4: Net Amt | AF4: Weight/Vol | AG4: Sales Amt (BC) | AH4: Conv. Factor | AI4: Eqv. Stock Qty | AJ4: Before Stock Qty | AK4: Before Stock Cost | AL4: After Stock Qty | AM4: Warehouse | AN4: Promotional Type | AO4: CESS PCT | AP4: CESS AMT | AQ4: PriceClass
A5: 1 | B5: HK-FIFO-LOT-BATCH-10001(FG) | C5: 0 | D5: HK-FIFO-LOT-BATCH-10001(FG) | E5: NOS | F5: NOS | G5: 10 | H5: 1500 | I5: =G5*H5 -> 15000 | J5: 2 | K5: 3 | L5: 5 | M5: =I5 -> 15000 | N5: =ROUND((M5*J5)/100,2) -> 300 | O5: =I5-N5 -> 14700 | P5: =ROUND((O5*K5)/100,2) -> 441 | Q5: =ROUND(O5-P5,2) -> 14259 | R5: =ROUND((Q5*L5)/100,2) -> 712.95 | S5: =ROUND(N5+P5+R5,2) -> 1453.95 | T5: =ROUND(S5/G5,2) -> 145.4 | U5: =(I5-S5) -> 13546.05 | V5: HSN1 | W5: 0.12 | X5: =IF(OR($D$3=1,$D$3=4),ROUND((U5*W5)/2,2),0) -> 812.76 | Y5: =IF($D$3=1,ROUND(((U5*W5)/2),2),0) -> 812.76 | Z5: =IF($D$3=2,ROUND(((U5*W5)),2),0) -> 0 | AA5: =IF($D$3=4,ROUND(((U5*W5)/2),2),0) -> 0 | AB5: 0.06 | AC5: =IF($D$3=5,ROUND(((U5*AB5)/2),2),0) -> 0 | AD5: =X5+Y5+Z5+AA5+AC5 -> 1625.52 | AE5: =U5+AD5 -> 15171.57 | AF5: 120 | AG5: =U5*$N$3 -> 13546.05 | AH5: 1 | AI5: =G5/AH5 -> 10 | AJ5: 848 | AK5: 235.36857 | AL5: =ROUND(AJ5-G5,0) -> 838 | AM5: F100 | AN5: Sales Regular | AO5: 0 | AP5: =ROUND(((AO5*U5)/100),2) -> 0 | AQ5: DOMESTIC
A6: 2 | B6: HK-FG-DISSIMILAR-10001 | C6: 0 | D6: HK-FG-DISSIMILAR-10001 | E6: KGS | F6: NOS | G6: 10 | H6: 2000 | I6: =G6*H6 -> 20000 | J6: 5 | K6: 7 | L6: 9 | M6: =I6 -> 20000 | N6: =ROUND((M6*J6)/100,2) -> 1000 | O6: =I6-N6 -> 19000 | P6: =ROUND((O6*K6)/100,2) -> 1330 | Q6: =ROUND(O6-P6,2) -> 17670 | R6: =ROUND((Q6*L6)/100,2) -> 1590.3 | S6: =ROUND(N6+P6+R6,2) -> 3920.3 | T6: =ROUND(S6/G6,2) -> 392.03 | U6: =(I6-S6) -> 16079.7 | V6: HSN1 | W6: 0.05 | X6: =IF(OR($D$3=1,$D$3=4),ROUND((U6*W6)/2,2),0) -> 401.99 | Y6: =IF($D$3=1,ROUND(((U6*W6)/2),2),0) -> 401.99 | Z6: =IF($D$3=2,ROUND(((U6*W6)),2),0) -> 0 | AA6: =IF($D$3=4,ROUND(((U6*W6)/2),2),0) -> 0 | AB6: 0.06 | AC6: =IF($D$3=5,ROUND(((U6*AB6)/2),2),0) -> 0 | AD6: =X6+Y6+Z6+AA6+AC6 -> 803.98 | AE6: =U6+AD6 -> 16883.68 | AF6: 120 | AG6: =U6*$N$3 -> 16079.7 | AH6: 3 | AI6: =ROUND(G6/AH6,3) -> 3.333 | AJ6: 1375.002 | AK6: 123 | AL6: =ROUND((AJ6-AI6),3) -> 1371.669 | AM6: F100 | AN6: Sales Regular | AO6: 0 | AP6: =ROUND(((AO6*U6)/100),2) -> 0 | AQ6: DOMESTIC
Q7: DISC AMOUNT | Z7: NET AMOUNT | AE7: =SUM(AE5:AE6) -> 32055.25 | AF7: SALES AMOUNT | AG7: =AG5 -> 13546.05

Sheet SEZ Customer
A1: Scenario : Local Sales - Stock UOM and Sales UOM (Similar) DOC NO : SORD-2425-00089
A2: Sales Order
A3: GST Sales | D3: 1 | E3: (1 - Local Sales,2 Interstate Sales, 3 Import Sales) | J3: Cur. | K3: INR | M3: Ex. Rate | N3: 1
A4: S. No. | B4: Item | C4: Rev | D4: Item Desc. | E4: Stk. UOM | F4: Sale. UOM | G4: Order Qty (Sale UOM) | H4: Unit Price | I4: Gross Amt. | J4: TD% | K4: SD% | L4: CD% | M4: TD Asbl. Val. | N4: TD Amt. | O4: SD Asbl. Val. | P4: SD Amt. | Q4: CD Asbl. Val. | R4: CD Amt. | S4: Disc. Amt. | T4: Disc.Amt.Per.Qty | U4: Sales Val. | V4: HSN | W4: Tax Rate | X4: CGST | Y4: SGST | Z4: IGST | AA4: Tax amt | AB4: Net Amt | AC4: Weight/Vol | AD4: Sales Amt (BC) | AE4: Conv. Factor | AF4: Eqv. Stock Qty | AG4: Before Stock Qty | AH4: Before Stock Cost | AI4: After Stock Qty | AJ4: Warehouse | AK4: Promotional Type | AL4: CESS PCT | AM4: CESS AMT | AN4: PriceClass
A5: 1 | B5: HK-FIFO-LOT-BATCH-10001(FG) | C5: 0 | D5: HK-FIFO-LOT-BATCH-10001(FG) | E5: NOS | F5: NOS | G5: 10 | H5: 1500 | I5: =G5*H5 -> 15000 | J5: 1 | K5: 3 | L5: 5 | M5: =I5 -> 15000 | N5: =ROUND((M5*J5)/100,2) -> 150 | O5: =I5-N5 -> 14850 | P5: =ROUND((O5*K5)/100,2) -> 445.5 | Q5: =ROUND(O5-P5,2) -> 14404.5 | R5: =ROUND((Q5*L5)/100,2) -> 720.23 | S5: =ROUND(N5+P5+R5,2) -> 1315.73 | T5: =ROUND(S5/G5,2) -> 131.57 | U5: =(I5-S5) -> 13684.27 | V5: HSN1 | W5: 0.12 | X5: 0 | Y5: 0 | Z5: 0 | AA5: 0 | AB5: =U5+AA5 -> 13684.27 | AC5: 120 | AD5: =U5*$N$3 -> 13684.27 | AE5: 1 | AF5: =G5/AE5 -> 10 | AG5: 848 | AH5: 235.36857 | AI5: =ROUND(AG5-G5,0) -> 902 | AJ5: F100 | AK5: Sales Regular | AL5: 0 | AM5: =ROUND(((AL5*U5)/100),2) -> 0 | AN5: DOMESTIC
A6: 2 | B6: HK-FG-DISSIMILAR-10001 | C6: 0 | D6: HK-FG-DISSIMILAR-10001 | E6: KGS | F6: NOS | G6: 10 | H6: 2000 | I6: =G6*H6 -> 20000 | J6: 2 | K6: 1 | L6: 3 | M6: =I6 -> 20000 | N6: =ROUND((M6*J6)/100,2) -> 400 | O6: =I6-N6 -> 19600 | P6: =ROUND((O6*K6)/100,2) -> 196 | Q6: =ROUND(O6-P6,2) -> 19404 | R6: =ROUND((Q6*L6)/100,2) -> 582.12 | S6: =ROUND(N6+P6+R6,2) -> 1178.12 | T6: =ROUND(S6/G6,2) -> 117.81 | U6: =(I6-S6) -> 18821.88 | V6: HSN1 | W6: 0.05 | X6: 0 | Y6: 0 | Z6: 0 | AA6: 0 | AB6: =U6+AA6 -> 18821.88 | AC6: 120 | AD6: =U6*$N$3 -> 18821.88 | AE6: 3 | AF6: =ROUND(G6/AE6,3) -> 3.333 | AG6: 1375.002 | AH6: 123 | AI6: =ROUND((AG6-AF6),3) -> 1371.669 | AJ6: F100 | AK6: Sales Regular | AL6: 0 | AM6: =ROUND(((AL6*U6)/100),2) -> 0 | AN6: DOMESTIC
Q7: DISC AMOUNT | Z7: NET AMOUNT | AB7: =SUM(AB5:AB6) -> 32506.15 | AC7: SALES AMOUNT | AD7: =AD5 -> 13684.27

Sheet CESS
A1: Scenario : Local Sales - Stock UOM and Sales UOM (Similar) DOC NO : SORD-2425-00089
A2: Sales Order
A3: GST Sales | D3: 2 | E3: (1 - Local Sales,2 Interstate Sales, 3 Import Sales) | J3: Cur. | K3: INR | M3: Ex. Rate | N3: 1
A4: S. No. | B4: Item | C4: Rev | D4: Item Desc. | E4: Stk. UOM | F4: Sale. UOM | G4: Order Qty (Sale UOM) | H4: Unit Price | I4: Gross Amt. | J4: TD% | K4: SD% | L4: CD% | M4: TD Asbl. Val. | N4: TD Amt. | O4: SD Asbl. Val. | P4: SD Amt. | Q4: CD Asbl. Val. | R4: CD Amt. | S4: Disc. Amt. | T4: Disc.Amt.Per.Qty | U4: Sales Val. | V4: HSN | W4: Tax Rate | X4: CGST | Y4: SGST | Z4: IGST | AA4: UTGST | AB4: CESS % | AC4: CESS AMT | AD4: Tax amt | AE4: Net Amt | AF4: Weight/Vol | AG4: Sales Amt (BC) | AH4: Conv. Factor | AI4: Eqv. Stock Qty | AJ4: Before Stock Qty | AK4: Before Stock Cost | AL4: After Stock Qty | AM4: Warehouse | AN4: Promotional Type | AO4: CESS PCT | AP4: CESS AMT | AQ4: PriceClass
A5: 1 | B5: HK-FIFO-LOT-BATCH-10001(FG) | C5: 0 | D5: HK-FIFO-LOT-BATCH-10001(FG) | E5: NOS | F5: NOS | G5: 10 | H5: 1500 | I5: =G5*H5 -> 15000 | J5: 2 | K5: 3 | L5: 5 | M5: =I5 -> 15000 | N5: =ROUND((M5*J5)/100,2) -> 300 | O5: =I5-N5 -> 14700 | P5: =ROUND((O5*K5)/100,2) -> 441 | Q5: =ROUND(O5-P5,2) -> 14259 | R5: =ROUND((Q5*L5)/100,2) -> 712.95 | S5: =ROUND(N5+P5+R5,2) -> 1453.95 | T5: =ROUND(S5/G5,2) -> 145.4 | U5: =(I5-S5) -> 13546.05 | V5: HSN1 | W5: 0.12 | X5: =IF(OR($D$3=1,$D$3=4),ROUND((U5*W5)/2,2),0) -> 0 | Y5: =IF($D$3=1,ROUND(((U5*W5)/2),2),0) -> 0 | Z5: =IF($D$3=2,ROUND(((U5*W5)),2),0) -> 1625.53 | AA5: =IF($D$3=4,ROUND(((U5*W5)/2),2),0) -> 0 | AB5: 0.06 | AC5: =IF($D$3=5,ROUND(((U5*AB5)/2),2),0) -> 0 | AD5: =X5+Y5+Z5+AA5+AC5 -> 1625.53 | AE5: =U5+AD5 -> 15171.58 | AF5: 120 | AG5: =U5*$N$3 -> 13546.05 | AH5: 1 | AI5: =G5/AH5 -> 10 | AJ5: 848 | AK5: 235.36857 | AL5: =ROUND(AJ5-G5,0) -> 838 | AM5: F100 | AN5: Sales Regular | AO5: 0 | AP5: =ROUND(((AO5*U5)/100),2) -> 0 | AQ5: DOMESTIC
A6: 2 | B6: HK-USRDFN-10001 | C6: 0 | D6: HK-USERDEFINED-10001 | E6: NOS | F6: NOS | G6: 10 | H6: 2000 | I6: =G6*H6 -> 20000 | J6: 0 | K6: 0 | L6: 0 | M6: =I6 -> 20000 | N6: =ROUND((M6*J6)/100,2) -> 0 | O6: =I6-N6 -> 20000 | P6: =ROUND((O6*K6)/100,2) -> 0 | Q6: =ROUND(O6-P6,2) -> 20000 | R6: =ROUND((Q6*L6)/100,2) -> 0 | S6: =ROUND(N6+P6+R6,2) -> 0 | T6: =ROUND(S6/G6,2) -> 0 | U6: =(I6-S6) -> 20000 | V6: HSN1 | W6: 0.05 | X6: =IF(OR($D$3=1,$D$3=4),ROUND((U6*W6)/2,2),0) -> 0 | Y6: =IF($D$3=1,ROUND(((U6*W6)/2),2),0) -> 0 | Z6: =IF($D$3=2,ROUND(((U6*W6)),2),0) -> 1000 | AA6: =IF($D$3=4,ROUND(((U6*W6)/2),2),0) -> 0 | AB6: 0.06 | AC6: =IF($D$3=5,ROUND(((U6*AB6)/2),2),0) -> 0 | AD6: =X6+Y6+Z6+AA6+AC6 -> 1000 | AE6: =U6+AD6 -> 21000 | AF6: 120 | AG6: =U6*$N$3 -> 20000 | AH6: 3 | AI6: =ROUND(G6/AH6,3) -> 3.333 | AJ6: 1375.002 | AK6: 123 | AL6: =ROUND((AJ6-AI6),3) -> 1371.669 | AM6: F100 | AN6: Promotional | AO6: 6 | AP6: =ROUND(((AO6*U6)/100),2) -> 1200 | AQ6: DOMESTIC
Q7: DISC AMOUNT | Z7: NET AMOUNT | AE7: =SUM(AE5:AE6) -> 36171.58 | AF7: SALES AMOUNT | AG7: =AG5 -> 13546.05

Sheet Demo Exhibition
A1: Scenario : Local Sales - Stock UOM and Sales UOM (Similar) DOC NO : SORD-2425-00089
A2: Sales Order
A3: GST Sales | D3: 2 | E3: (1 - Local Sales,2 Interstate Sales, 3 Export Sales, 4 UTGST) | J3: Cur. | K3: INR | M3: Ex. Rate | N3: 1
A4: S. No. | B4: Item | C4: Rev | D4: Item Desc. | E4: Stk. UOM | F4: Sale. UOM | G4: Order Qty (Sale UOM) | H4: Unit Price | I4: Gross Amt. | J4: TD% | K4: SD% | L4: CD% | M4: TD Asbl. Val. | N4: TD Amt. | O4: SD Asbl. Val. | P4: SD Amt. | Q4: CD Asbl. Val. | R4: CD Amt. | S4: Disc. Amt. | T4: Disc.Amt.Per.Qty | U4: Sales Val. | V4: HSN | W4: Tax Rate | X4: CGST | Y4: SGST | Z4: IGST | AA4: UTGST | AB4: CESS % | AC4: CESS AMT | AD4: Tax amt | AE4: Net Amt | AF4: Weight/Vol | AG4: Sales Amt (BC) | AH4: Conv. Factor | AI4: Eqv. Stock Qty | AJ4: Before Stock Qty | AK4: Before Stock Cost | AL4: After Stock Qty | AM4: Warehouse | AN4: Promotional Type | AO4: CESS PCT | AP4: CESS AMT | AQ4: PriceClass
A5: 1 | B5: HK-FIFO-LOT-BATCH-10001(FG) | C5: 0 | D5: HK-FIFO-LOT-BATCH-10001(FG) | E5: NOS | F5: NOS | G5: 10 | H5: 1500 | I5: =G5*H5 -> 15000 | J5: 0 | K5: 0 | L5: 0 | M5: =I5 -> 15000 | N5: =ROUND((M5*J5)/100,2) -> 0 | O5: =I5-N5 -> 15000 | P5: =ROUND((O5*K5)/100,2) -> 0 | Q5: =ROUND(O5-P5,2) -> 15000 | R5: =ROUND((Q5*L5)/100,2) -> 0 | S5: =N5+P5+R5 -> 0 | T5: =S5/G5 -> 0 | U5: =(I5-S5) -> 15000 | V5: HSN1 | W5: 0.12 | X5: =IF(OR($D$3=1,$D$3=4),ROUND((U5*W5)/2,2),0) -> 0 | Y5: =IF($D$3=1,ROUND(((U5*W5)/2),2),0) -> 0 | Z5: =IF($D$3=2,ROUND(((U5*W5)),2),0) -> 1800 | AA5: =IF($D$3=4,ROUND(((U5*W5)/2),2),0) -> 0 | AB5: 0.06 | AC5: =IF($D$3=5,ROUND(((U5*AB5)/2),2),0) -> 0 | AD5: =X5+Y5+Z5+AA5+AC5 -> 1800 | AE5: =U5+AD5 -> 16800 | AF5: 120 | AG5: =U5*$N$3 -> 15000 | AH5: 1 | AI5: =G5/AH5 -> 10 | AJ5: 848 | AK5: 235.36857 | AL5: =ROUND(AJ5-G5,0) -> 838 | AM5: F100 | AN5: Sales Regular | AO5: 0 | AP5: =ROUND(((AO5*U5)/100),2) -> 0 | AQ5: DOMESTIC
A6: 2 | B6: HK-FG-DISSIMILAR-10001 | C6: 0 | D6: HK-FG-DISSIMILAR-10001 | E6: KGS | F6: NOS | G6: 10 | H6: 2000 | I6: =G6*H6 -> 20000 | J6: 0 | K6: 0 | L6: 0 | M6: =I6 -> 20000 | N6: =ROUND((M6*J6)/100,2) -> 0 | O6: =I6-N6 -> 20000 | P6: =ROUND((O6*K6)/100,2) -> 0 | Q6: =ROUND(O6-P6,2) -> 20000 | R6: =ROUND((Q6*L6)/100,2) -> 0 | S6: =N6+P6+R6 -> 0 | T6: =S6/G6 -> 0 | U6: =(I6-S6) -> 20000 | V6: HSN1 | W6: 0.05 | X6: =IF(OR($D$3=1,$D$3=4),ROUND((U6*W6)/2,2),0) -> 0 | Y6: =IF($D$3=1,ROUND(((U6*W6)/2),2),0) -> 0 | Z6: =IF($D$3=2,ROUND(((U6*W6)),2),0) -> 1000 | AA6: =IF($D$3=4,ROUND(((U6*W6)/2),2),0) -> 0 | AB6: 0.06 | AC6: =IF($D$3=5,ROUND(((U6*AB6)/2),2),0) -> 0 | AD6: =X6+Y6+Z6+AA6+AC6 -> 1000 | AE6: =U6+AD6 -> 21000 | AF6: 120 | AG6: =U6*$N$3 -> 20000 | AH6: 3 | AI6: =ROUND(G6/AH6,3) -> 3.333 | AJ6: 1375.002 | AK6: 123 | AL6: =ROUND((AJ6-AI6),3) -> 1371.669 | AM6: F100 | AN6: Sales Regular | AO6: 0 | AP6: =ROUND(((AO6*U6)/100),2) -> 0 | AQ6: DOMESTIC
Q7: DISC AMOUNT | Z7: NET AMOUNT | AE7: =SUM(AE5:AE6) -> 37800 | AF7: SALES AMOUNT | AG7: =AG5 -> 15000

Sheet CHARGES
A1: Scenario : Local Sales - Stock UOM and Sales UOM (Similar) DOC NO : SORD-2425-00089
A2: Sales Order
A3: GST Sales | D3: 2 | E3: (1 - Local Sales,2 Interstate Sales, 3 Import Sales) | J3: Cur. | K3: INR | M3: Ex. Rate | N3: 1
A4: S. No. | B4: Item | C4: Rev | D4: Item Desc. | E4: Stk. UOM | F4: Sale. UOM | G4: Order Qty (Sale UOM) | H4: Unit Price | I4: Gross Amt. | J4: TD% | K4: SD% | L4: CD% | M4: TD Asbl. Val. | N4: TD Amt. | O4: SD Asbl. Val. | P4: SD Amt. | Q4: CD Asbl. Val. | R4: CD Amt. | S4: Disc. Amt. | T4: Disc.Amt.Per.Qty | U4: Sales Val. | V4: HSN | W4: Tax Rate | X4: CGST | Y4: SGST | Z4: IGST | AA4: UTGST | AB4: CESS % | AC4: CESS AMT | AD4: Tax amt | AE4: Net Amt | AF4: Weight/Vol | AG4: Sales Amt (BC) | AH4: Conv. Factor | AI4: Eqv. Stock Qty | AJ4: Before Stock Qty | AK4: Before Stock Cost | AL4: After Stock Qty | AM4: Warehouse | AN4: Promotional Type | AO4: CESS PCT | AP4: CESS AMT | AQ4: PriceClass
A5: 1 | B5: HK-FIFO-LOT-BATCH-10001(FG) | C5: 0 | D5: HK-FIFO-LOT-BATCH-10001(FG) | E5: NOS | F5: NOS | G5: 10 | H5: 1679 | I5: =G5*H5 -> 16790 | J5: 12.5 | K5: 11.3 | L5: 25.6 | M5: =I5 -> 16790 | N5: =ROUND((M5*J5)/100,2) -> 2098.75 | O5: =I5-N5 -> 14691.25 | P5: =ROUND((O5*K5)/100,2) -> 1660.11 | Q5: =ROUND(O5-P5,2) -> 13031.14 | R5: =ROUND((Q5*L5)/100,2) -> 3335.97 | S5: =ROUND(N5+P5+R5,2) -> 7094.83 | T5: =ROUND(S5/G5,2) -> 709.48 | U5: =(I5-S5) -> 9695.17 | V5: HSN1 | W5: 0.12 | X5: =IF(OR($D$3=1,$D$3=4),ROUND((U5*W5)/2,2),0) -> 0 | Y5: =IF($D$3=1,ROUND(((U5*W5)/2),2),0) -> 0 | Z5: =IF($D$3=2,ROUND(((U5*W5)),2),0) -> 1163.42 | AA5: =IF($D$3=4,ROUND(((U5*W5)/2),2),0) -> 0 | AB5: 0.06 | AC5: =IF($D$3=5,ROUND(((U5*AB5)/2),2),0) -> 0 | AD5: =X5+Y5+Z5+AA5+AC5 -> 1163.42 | AE5: =U5+AD5 -> 10858.59 | AF5: 120 | AG5: =U5*$N$3 -> 9695.17 | AH5: 1 | AI5: =G5/AH5 -> 10 | AJ5: 848 | AK5: 235.36857 | AL5: =ROUND(AJ5-G5,0) -> 838 | AM5: F100 | AN5: Sales Regular | AO5: 0 | AP5: =ROUND(((AO5*U5)/100),2) -> 0 | AQ5: DOMESTIC
A6: 2 | B6: HK-FG-DISSIMILAR-10001 | C6: 0 | D6: HK-FG-DISSIMILAR-10001 | E6: KGS | F6: NOS | G6: 10 | H6: 2367 | I6: =G6*H6 -> 23670 | J6: 1.2 | K6: 1.34 | L6: 1.65 | M6: =I6 -> 23670 | N6: =ROUND((M6*J6)/100,2) -> 284.04 | O6: =I6-N6 -> 23385.96 | P6: =ROUND((O6*K6)/100,2) -> 313.37 | Q6: =ROUND(O6-P6,2) -> 23072.59 | R6: =ROUND((Q6*L6)/100,2) -> 380.7 | S6: =N6+P6+R6 -> 978.11 | T6: =ROUND(S6/G6,2) -> 97.81 | U6: =(I6-S6) -> 22691.89 | V6: HSN1 | W6: 0.05 | X6: =IF(OR($D$3=1,$D$3=4),ROUND((U6*W6)/2,2),0) -> 0 | Y6: =IF($D$3=1,ROUND(((U6*W6)/2),2),0) -> 0 | Z6: =IF($D$3=2,ROUND(((U6*W6)),2),0) -> 1134.59 | AA6: =IF($D$3=4,ROUND(((U6*W6)/2),2),0) -> 0 | AB6: 0.06 | AC6: =IF($D$3=5,ROUND(((U6*AB6)/2),2),0) -> 0 | AD6: =X6+Y6+Z6+AA6+AC6 -> 1134.59 | AE6: =U6+AD6 -> 23826.48 | AF6: 120 | AG6: =U6*$N$3 -> 22691.89 | AH6: 3 | AI6: =ROUND(G6/AH6,3) -> 3.333 | AJ6: 1375.002 | AK6: 123 | AL6: =ROUND((AJ6-AI6),3) -> 1371.669 | AM6: F100 | AN6: Sales Regular | AO6: 0 | AP6: =ROUND(((AO6*U6)/100),2) -> 0 | AQ6: DOMESTIC
I7: =SUM(I5:I6) -> 40460 | Q7: DISC AMOUNT | U7: =SUM(U5:U6) -> 32387.06 | Z7: NET AMOUNT | AE7: =SUM(AE5:AE6) -> 34685.07 | AF7: SALES AMOUNT | AG7: =AG5 -> 9695.17
C9: Charges
C10: Sno | D10: Item | E10: Rev | F10: Desc | G10: Basiss | H10: Pct | I10: Value | J10: SAC | K10: Tax Rate | L10: CGST | M10: SGST | N10: IGST | O10: Tax amt
C11: 1 | D11: TVS-CH-00002 | E11: 0 | F11: FRIEGHT CHARGES | G11: % | H11: 20 | I11: =ROUND(((U7*H11)/100),2) -> 6477.41 | J11: 4901 | K11: 0.12 | L11: =IF($D$3=1,ROUND(((I11*K11)/2),2),0) -> 0 | M11: =IF($D$3=1,ROUND(((I11*K11)/2),2),0) -> 0 | N11: =IF($D$3=2,ROUND(((I11*K11)),2),0) -> 777.29 | O11: =L11+M11+N11 -> 777.29
C12: 2 | D12: TVS-CH-00003 | E12: 0 | F12: PACKING CHARGES | G12: Value | I12: 15000 | J12: 112341 | K12: 0.12 | L12: =IF($D$3=1,ROUND(((I12*K12)/2),2),0) -> 0 | M12: =IF($D$3=1,ROUND(((I12*K12)/2),2),0) -> 0 | N12: =IF($D$3=2,ROUND(((I12*K12)),2),0) -> 1800 | O12: =L12+M12+N12 -> 1800
H13: Total | I13: =SUM(I11:I12) -> 21477.41 | L13: =SUM(L11:L12) -> 0 | M13: =SUM(M11:M12) -> 0 | N13: =SUM(N11:N12) -> 2577.29 | O13: =SUM(O11:O12) -> 2577.29

Sheet SO Amendment Disc UTGST
A1: Scenario : Local Sales - Stock UOM and Sales UOM (Similar) DOC NO : SORD-2425-00089
A2: Sales Order
A3: GST Sales | D3: 4 | E3: (1 - Local Sales,2 Interstate Sales, 3 Export Sales) | J3: Cur. | K3: INR | M3: Ex. Rate | N3: 1
A4: S. No. | B4: Item | C4: Rev | D4: Item Desc. | E4: Stk. UOM | F4: Sale. UOM | G4: Order Qty (Sale UOM) | H4: Unit Price | I4: Gross Amt. | J4: TD% | K4: SD% | L4: CD% | M4: TD Asbl. Val. | N4: TD Amt. | O4: SD Asbl. Val. | P4: SD Amt. | Q4: CD Asbl. Val. | R4: CD Amt. | S4: Disc. Amt. | T4: Disc.Amt.Per.Qty | U4: Sales Val. | V4: HSN | W4: Tax Rate | X4: CGST | Y4: SGST | Z4: IGST | AA4: UTGST | AB4: CESS % | AC4: CESS AMT | AD4: Tax amt | AE4: Net Amt | AF4: Weight/Vol | AG4: Sales Amt (BC) | AH4: Conv. Factor | AI4: Eqv. Stock Qty | AJ4: Before Stock Qty | AK4: Before Stock Cost | AL4: After Stock Qty | AM4: Warehouse | AN4: Promotional Type | AO4: CESS PCT | AP4: CESS AMT | AQ4: PriceClass | AR4: New Order Qty (Sale UOM) | AS4: New Unit Price | AT4: New Gross Amt. | AU4: New TD% | AV4: New SD% | AW4: New CD% | AX4: New TD Asbl. Val. | AY4: New TD Amt. | AZ4: New SD Asbl. Val. | BA4: New SD Amt. | BB4: New CD Asbl. Val. | BC4: New CD Amt. | BD4: New Disc. Amt. | BE4: New Disc.Amt.Per.Qty | BF4: New Sales Val. | BG4: New HSN | BH4: New Tax Rate | BI4: New CGST | BJ4: New SGST | BK4: New IGST | BL4: New UTGST | BM4: New CESS % | BN4: New CESS AMT | BO4: New Tax amt | BP4: New Net Amt | BQ4: Weight/Vol | BR4: New Sales Amt (BC) | BS4: New PriceClass
A5: ='SO UTGST'!A5 -> 1 | B5: ='SO UTGST'!B5 -> HK-FIFO-LOT-BATCH-10001(FG) | C5: ='SO UTGST'!C5 -> 0 | D5: ='SO UTGST'!D5 -> HK-FIFO-LOT-BATCH-10001(FG) | E5: ='SO UTGST'!E5 -> NOS | F5: ='SO UTGST'!F5 -> NOS | G5: ='SO UTGST'!G5 -> 10 | H5: ='SO UTGST'!H5 -> 1234 | ... V5: ='SO UTGST'!V5 -> (740410)-18% | W5: 0.12 | X5: ='SO UTGST'!X5 -> 689.6 | Y5: ='SO UTGST'!Y5 -> 0 | Z5: ='SO UTGST'!Z5 -> 0 | AA5: ='SO UTGST'!AA5 -> 689.6 | AB5: 0.06 | AC5: ='SO UTGST'!AC5 -> 0 | AD5: ='SO UTGST'!AD5 -> 1379.2 | AE5: ='SO UTGST'!AE5 -> 12872.58 | AF5: ='SO UTGST'!AF5 -> 120 | AG5: ='SO UTGST'!AG5 -> 11493.38 | AH5: ='SO UTGST'!AH5 -> 1 | AI5: ='SO UTGST'!AI5 -> 10 | AJ5: ='SO UTGST'!AJ5 -> 848 | ... AQ5: ='SO UTGST'!AQ5 -> DOMESTIC | AR5: 10 | AS5: 1234 | AT5: =AR5*AS5 -> 12340 | AU5: 11 | AV5: 12 | AW5: 14 | AX5: =AT5 -> 12340 | AY5: =ROUND((AX5*AU5)/100,2) -> 1357.4 | AZ5: =AT5-AY5 -> 10982.6 | BA5: =ROUND((AZ5*AV5)/100,2) -> 1317.91 | BB5: =ROUND(AZ5-BA5,2) -> 9664.69 | BC5: =ROUND((BB5*AW5)/100,2) -> 1353.06 | BD5: =AY5+BA5+BC5 -> 4028.37 | BE5: =ROUND(BD5/AR5,2) -> 402.84 | BF5: =(AT5-BD5) -> 8311.63 | BG5: (740410)-18% | BH5: 0.12 | BI5: =IF(OR($D$3=1,$D$3=4),ROUND((BF5*BH5)/2,2),0) -> 498.7 | BJ5: =IF($D$3=1,ROUND(((BF5*BH5)/2),2),0) -> 0 | BK5: =IF($D$3=2,ROUND(((BF5*BH5)),2),0) -> 0 | BL5: =IF($D$3=4,ROUND(((BF5*BH5)/2),2),0) -> 498.7 | BM5: 0.06 | BN5: =IF($D$3=5,ROUND(((BF5*BM5)/2),2),0) -> 0 | BO5: =BI5+BJ5+BK5+BL5+BN5 -> 997.4 | BP5: =BF5+BO5 -> 9309.03 | BQ5: 120 | BR5: =BF5*$N$3 -> 8311.63 | BS5: DOMESTIC
A6: ='SO UTGST'!A6 -> 2 | B6: ='SO UTGST'!B6 -> HK-FG-DISSIMILAR-10001 | C6: ='SO UTGST'!C6 -> 0 | D6: ='SO UTGST'!D6 -> HK-FG-DISSIMILAR-10001 | E6: ='SO UTGST'!E6 -> KGS | F6: ='SO UTGST'!F6 -> NOS | G6: ='SO UTGST'!G6 -> 20 | H6: ='SO UTGST'!H6 -> 3214 | ... V6: ='SO UTGST'!V6 -> 772213 | W6: 0.05 | X6: ='SO UTGST'!X6 -> 1332.8 | Y6: ='SO UTGST'!Y6 -> 0 | Z6: ='SO UTGST'!Z6 -> 0 | AA6: ='SO UTGST'!AA6 -> 1332.8 | AB6: 0.06 | AC6: ='SO UTGST'!AC6 -> 0 | AD6: ='SO UTGST'!AD6 -> 2665.6 | AE6: ='SO UTGST'!AE6 -> 55977.76 | AF6: ='SO UTGST'!AF6 -> 120 | AG6: ='SO UTGST'!AG6 -> 53312.16 | AH6: ='SO UTGST'!AH6 -> 3 | AI6: ='SO UTGST'!AI6 -> 6.667 | AJ6: ='SO UTGST'!AJ6 -> 1375.002 | ... AQ6: ='SO UTGST'!AQ6 -> DOMESTIC | AR6: 20 | AS6: 3214 | AT6: =AR6*AS6 -> 64280 | AU6: 12 | AV6: 17 | AW6: 19 | AX6: =AT6 -> 64280 | AY6: =ROUND((AX6*AU6)/100,2) -> 7713.6 | AZ6: =AT6-AY6 -> 56566.4 | BA6: =ROUND((AZ6*AV6)/100,2) -> 9616.29 | BB6: =ROUND(AZ6-BA6,2) -> 46950.11 | BC6: =ROUND((BB6*AW6)/100,2) -> 8920.52 | BD6: =AY6+BA6+BC6 -> 26250.41 | BE6: =ROUND(BD6/AR6,2) -> 1312.52 | BF6: =(AT6-BD6) -> 38029.59 | BG6: 772213 | BH6: 0.05 | BI6: =IF(OR($D$3=1,$D$3=4),ROUND((BF6*BH6)/2,2),0) -> 950.74 | BJ6: =IF($D$3=1,ROUND(((BF6*BH6)/2),2),0) -> 0 | BK6: =IF($D$3=2,ROUND(((BF6*BH6)),2),0) -> 0 | BL6: =IF($D$3=4,ROUND(((BF6*BH6)/2),2),0) -> 950.74 | BM6: 0.06 | BN6: =IF($D$3=5,ROUND(((BF6*BM6)/2),2),0) -> 0 | BO6: =BI6+BJ6+BK6+BL6+BN6 -> 1901.48 | BP6: =BF6+BO6 -> 39931.07 | BQ6: 120 | BR6: =BF6*$N$3 -> 38029.59 | BS6: DOMESTIC
Q7: DISC AMOUNT | S7: =SUM(S5:S6) -> 11814.46 | Z7: NET AMOUNT | AE7: =SUM(AE5:AE6) -> 68850.34 | AF7: SALES AMOUNT | AG7: =AG5 -> 11493.38 | BB7: DISC AMOUNT | BD7: =SUM(BD5:BD6) -> 30278.78 | BK7: NET AMOUNT | BP7: =SUM(BP5:BP6) -> 49240.1 | BQ7: SALES AMOUNT | BR7: =BR5 -> 8311.63

Sheet SO Amendment Price UTGST
A1: Scenario : Local Sales - Stock UOM and Sales UOM (Similar) DOC NO : SORD-2425-00089
A2: Sales Order
A3: GST Sales | D3: 4 | E3: (1 - Local Sales,2 Interstate Sales, 3 Export Sales) | J3: Cur. | K3: INR | M3: Ex. Rate | N3: 1
A4: S. No. | B4: Item | C4: Rev | D4: Item Desc. | E4: Stk. UOM | F4: Sale. UOM | G4: Order Qty (Sale UOM) | H4: Unit Price | I4: Gross Amt. | J4: TD% | K4: SD% | L4: CD% | M4: TD Asbl. Val. | N4: TD Amt. | O4: SD Asbl. Val. | P4: SD Amt. | Q4: CD Asbl. Val. | R4: CD Amt. | S4: Disc. Amt. | T4: Disc.Amt.Per.Qty | U4: Sales Val. | V4: HSN | W4: Tax Rate | X4: CGST | Y4: SGST | Z4: IGST | AA4: UTGST | AB4: CESS % | AC4: CESS AMT | AD4: Tax amt | AE4: Net Amt | AF4: Weight/Vol | AG4: Sales Amt (BC) | AH4: Conv. Factor | AI4: Eqv. Stock Qty | AJ4: Before Stock Qty | AK4: Before Stock Cost | AL4: After Stock Qty | AM4: Warehouse | AN4: Promotional Type | AO4: CESS PCT | AP4: CESS AMT | AQ4: PriceClass | AR4: New Order Qty (Sale UOM) | AS4: New Unit Price | AT4: New Gross Amt. | AU4: New TD% | AV4: New SD% | AW4: New CD% | AX4: New TD Asbl. Val. | AY4: New TD Amt. | AZ4: New SD Asbl. Val. | BA4: New SD Amt. | BB4: New CD Asbl. Val. | BC4: New CD Amt. | BD4: New Disc. Amt. | BE4: New Disc.Amt.Per.Qty | BF4: New Sales Val. | BG4: New HSN | BH4: New Tax Rate | BI4: New CGST | BJ4: New SGST | BK4: New IGST | BL4: New UTGST | BM4: New CESS % | BN4: New CESS AMT | BO4: New Tax amt | BP4: New Net Amt | BQ4: Weight/Vol | BR4: New Sales Amt (BC) | BS4: New PriceClass
A5: ='SO UTGST'!A5 -> 1 | B5: ='SO UTGST'!B5 -> HK-FIFO-LOT-BATCH-10001(FG) | C5: ='SO UTGST'!C5 -> 0 | D5: ='SO UTGST'!D5 -> HK-FIFO-LOT-BATCH-10001(FG) | E5: ='SO UTGST'!E5 -> NOS | F5: ='SO UTGST'!F5 -> NOS | G5: ='SO UTGST'!G5 -> 10 | H5: ='SO UTGST'!H5 -> 1234 | ... V5: ='SO UTGST'!V5 -> (740410)-18% | W5: 0.12 | X5: ='SO UTGST'!X5 -> 689.6 | Y5: ='SO UTGST'!Y5 -> 0 | Z5: ='SO UTGST'!Z5 -> 0 | AA5: ='SO UTGST'!AA5 -> 689.6 | AB5: 0.06 | AC5: ='SO UTGST'!AC5 -> 0 | AD5: ='SO UTGST'!AD5 -> 1379.2 | AE5: ='SO UTGST'!AE5 -> 12872.58 | AF5: ='SO UTGST'!AF5 -> 120 | AG5: ='SO UTGST'!AG5 -> 11493.38 | AH5: ='SO UTGST'!AH5 -> 1 | AI5: ='SO UTGST'!AI5 -> 10 | AJ5: ='SO UTGST'!AJ5 -> 848 | ... AQ5: ='SO UTGST'!AQ5 -> DOMESTIC | AR5: 10 | AS5: 2678 | AT5: =AR5*AS5 -> 26780 | AU5: 1 | AV5: 2 | AW5: 4 | AX5: =AT5 -> 26780 | AY5: =ROUND((AX5*AU5)/100,2) -> 267.8 | AZ5: =AT5-AY5 -> 26512.2 | BA5: =ROUND((AZ5*AV5)/100,2) -> 530.24 | BB5: =ROUND(AZ5-BA5,2) -> 25981.96 | BC5: =ROUND((BB5*AW5)/100,2) -> 1039.28 | BD5: =AY5+BA5+BC5 -> 1837.32 | BE5: =ROUND(BD5/AR5,2) -> 183.73 | BF5: =(AT5-BD5) -> 24942.68 | BG5: (740410)-18% | BH5: 0.12 | BI5: =IF(OR($D$3=1,$D$3=4),ROUND((BF5*BH5)/2,2),0) -> 1496.56 | BJ5: =IF($D$3=1,ROUND(((BF5*BH5)/2),2),0) -> 0 | BK5: =IF($D$3=2,ROUND(((BF5*BH5)),2),0) -> 0 | BL5: =IF($D$3=4,ROUND(((BF5*BH5)/2),2),0) -> 1496.56 | BM5: 0.06 | BN5: =IF($D$3=5,ROUND(((BF5*BM5)/2),2),0) -> 0 | BO5: =BI5+BJ5+BK5+BL5+BN5 -> 2993.12 | BP5: =BF5+BO5 -> 27935.8 | BQ5: 120 | BR5: =BF5*$N$3 -> 24942.68 | BS5: DOMESTIC
A6: ='SO UTGST'!A6 -> 2 | B6: ='SO UTGST'!B6 -> HK-FG-DISSIMILAR-10001 | C6: ='SO UTGST'!C6 -> 0 | D6: ='SO UTGST'!D6 -> HK-FG-DISSIMILAR-10001 | E6: ='SO UTGST'!E6 -> KGS | F6: ='SO UTGST'!F6 -> NOS | G6: ='SO UTGST'!G6 -> 20 | H6: ='SO UTGST'!H6 -> 3214 | ... V6: ='SO UTGST'!V6 -> 772213 | W6: 0.05 | X6: ='SO UTGST'!X6 -> 1332.8 | Y6: ='SO UTGST'!Y6 -> 0 | Z6: ='SO UTGST'!Z6 -> 0 | AA6: ='SO UTGST'!AA6 -> 1332.8 | AB6: 0.06 | AC6: ='SO UTGST'!AC6 -> 0 | AD6: ='SO UTGST'!AD6 -> 2665.6 | AE6: ='SO UTGST'!AE6 -> 55977.76 | AF6: ='SO UTGST'!AF6 -> 120 | AG6: ='SO UTGST'!AG6 -> 53312.16 | AH6: ='SO UTGST'!AH6 -> 3 | AI6: ='SO UTGST'!AI6 -> 6.667 | AJ6: ='SO UTGST'!AJ6 -> 1375.002 | ... AQ6: ='SO UTGST'!AQ6 -> DOMESTIC | AR6: 20 | AS6: 4256 | AT6: =AR6*AS6 -> 85120 | AU6: 2 | AV6: 7 | AW6: 9 | AX6: =AT6 -> 85120 | AY6: =ROUND((AX6*AU6)/100,2) -> 1702.4 | AZ6: =AT6-AY6 -> 83417.6 | BA6: =ROUND((AZ6*AV6)/100,2) -> 5839.23 | BB6: =ROUND(AZ6-BA6,2) -> 77578.37 | BC6: =ROUND((BB6*AW6)/100,2) -> 6982.05 | BD6: =AY6+BA6+BC6 -> 14523.68 | BE6: =ROUND(BD6/AR6,2) -> 726.18 | BF6: =(AT6-BD6) -> 70596.32 | BG6: 772213 | BH6: 0.05 | BI6: =IF(OR($D$3=1,$D$3=4),ROUND((BF6*BH6)/2,2),0) -> 1764.91 | BJ6: =IF($D$3=1,ROUND(((BF6*BH6)/2),2),0) -> 0 | BK6: =IF($D$3=2,ROUND(((BF6*BH6)),2),0) -> 0 | BL6: =IF($D$3=4,ROUND(((BF6*BH6)/2),2),0) -> 1764.91 | BM6: 0.06 | BN6: =IF($D$3=5,ROUND(((BF6*BM6)/2),2),0) -> 0 | BO6: =BI6+BJ6+BK6+BL6+BN6 -> 3529.82 | BP6: =BF6+BO6 -> 74126.14 | BQ6: 120 | BR6: =BF6*$N$3 -> 70596.32 | BS6: DOMESTIC
Q7: DISC AMOUNT | S7: =SUM(S5:S6) -> 11814.46 | Z7: NET AMOUNT | AE7: =SUM(AE5:AE6) -> 68850.34 | AF7: SALES AMOUNT | AG7: =AG5 -> 11493.38 | BB7: DISC AMOUNT | BD7: =SUM(BD5:BD6) -> 16361 | BK7: NET AMOUNT | BP7: =SUM(BP5:BP6) -> 102061.94 | BQ7: SALES AMOUNT | BR7: =BR5 -> 24942.68

Sheet SO Amendment AddItem UTGST
A1: Scenario : Local Sales - Stock UOM and Sales UOM (Similar) DOC NO : SORD-2425-00089
A2: Sales Order
A3: GST Sales | D3: 4 | E3: (1 - Local Sales,2 Interstate Sales, 3 Export Sales) | J3: Cur. | K3: INR | M3: Ex. Rate | N3: 1
A4: S. No. | B4: Item | C4: Rev | D4: Item Desc. | E4: Stk. UOM | F4: Sale. UOM | G4: Order Qty (Sale UOM) | H4: Unit Price | I4: Gross Amt. | J4: TD% | K4: SD% | L4: CD% | M4: TD Asbl. Val. | N4: TD Amt. | O4: SD Asbl. Val. | P4: SD Amt. | Q4: CD Asbl. Val. | R4: CD Amt. | S4: Disc. Amt. | T4: Disc.Amt.Per.Qty | U4: Sales Val. | V4: HSN | W4: Tax Rate | X4: CGST | Y4: SGST | Z4: IGST | AA4: UTGST | AB4: CESS % | AC4: CESS AMT | AD4: Tax amt | AE4: Net Amt | AF4: Weight/Vol | AG4: Sales Amt (BC) | AH4: Conv. Factor | AI4: Eqv. Stock Qty | AJ4: Before Stock Qty | AK4: Before Stock Cost | AL4: After Stock Qty | AM4: Warehouse | AN4: Promotional Type | AO4: CESS PCT | AP4: CESS AMT | AQ4: PriceClass | AR4: New Order Qty (Sale UOM) | AS4: New Unit Price | AT4: New Gross Amt. | AU4: New TD% | AV4: New SD% | AW4: New CD% | AX4: New TD Asbl. Val. | AY4: New TD Amt. | AZ4: New SD Asbl. Val. | BA4: New SD Amt. | BB4: New CD Asbl. Val. | BC4: New CD Amt. | BD4: New Disc. Amt. | BE4: New Disc.Amt.Per.Qty | BF4: New Sales Val. | BG4: New HSN | BH4: New Tax Rate | BI4: New CGST | BJ4: New SGST | BK4: New IGST | BL4: New UTGST | BM4: New CESS % | BN4: New CESS AMT | BO4: New Tax amt | BP4: New Net Amt | BQ4: Weight/Vol | BR4: New Sales Amt (BC) | BS4: New PriceClass
A5: ='SO UTGST'!A5 -> 1 | B5: ='SO UTGST'!B5 -> HK-FIFO-LOT-BATCH-10001(FG) | C5: ='SO UTGST'!C5 -> 0 | D5: ='SO UTGST'!D5 -> HK-FIFO-LOT-BATCH-10001(FG) | E5: ='SO UTGST'!E5 -> NOS | F5: ='SO UTGST'!F5 -> NOS | G5: ='SO UTGST'!G5 -> 10 | H5: ='SO UTGST'!H5 -> 1234 | ... V5: ='SO UTGST'!V5 -> (740410)-18% | W5: 0.12 | X5: ='SO UTGST'!X5 -> 689.6 | Y5: ='SO UTGST'!Y5 -> 0 | Z5: ='SO UTGST'!Z5 -> 0 | AA5: ='SO UTGST'!AA5 -> 689.6 | AB5: 0.06 | AC5: ='SO UTGST'!AC5 -> 0 | AD5: ='SO UTGST'!AD5 -> 1379.2 | AE5: ='SO UTGST'!AE5 -> 12872.58 | AF5: ='SO UTGST'!AF5 -> 120 | AG5: ='SO UTGST'!AG5 -> 11493.38 | AH5: ='SO UTGST'!AH5 -> 1 | AI5: ='SO UTGST'!AI5 -> 10 | AJ5: ='SO UTGST'!AJ5 -> 848 | ... AQ5: ='SO UTGST'!AQ5 -> DOMESTIC | AR5: 30 | AS5: 1234 | AT5: =AR5*AS5 -> 37020 | AU5: 1 | AV5: 2 | AW5: 4 | AX5: =AT5 -> 37020 | AY5: =ROUND((AX5*AU5)/100,2) -> 370.2 | AZ5: =AT5-AY5 -> 36649.8 | BA5: =ROUND((AZ5*AV5)/100,2) -> 733 | BB5: =ROUND(AZ5-BA5,2) -> 35916.8 | BC5: =ROUND((BB5*AW5)/100,2) -> 1436.67 | BD5: =AY5+BA5+BC5 -> 2539.87 | BE5: =ROUND(BD5/AR5,2) -> 84.66 | BF5: =(AT5-BD5) -> 34480.13 | BG5: (740410)-18% | BH5: 0.12 | BI5: =IF(OR($D$3=1,$D$3=4),ROUND((BF5*BH5)/2,2),0) -> 2068.81 | BJ5: =IF($D$3=1,ROUND(((BF5*BH5)/2),2),0) -> 0 | BK5: =IF($D$3=2,ROUND(((BF5*BH5)),2),0) -> 0 | BL5: =IF($D$3=4,ROUND(((BF5*BH5)/2),2),0) -> 2068.81 | BM5: 0.06 | BN5: =IF($D$3=5,ROUND(((BF5*BM5)/2),2),0) -> 0 | BO5: =BI5+BJ5+BK5+BL5+BN5 -> 4137.62 | BP5: =BF5+BO5 -> 38617.75 | BQ5: 120 | BR5: =BF5*$N$3 -> 34480.13 | BS5: DOMESTIC
A6: ='SO UTGST'!A6 -> 2 | B6: ='SO UTGST'!B6 -> HK-FG-DISSIMILAR-10001 | C6: ='SO UTGST'!C6 -> 0 | D6: ='SO UTGST'!D6 -> HK-FG-DISSIMILAR-10001 | E6: ='SO UTGST'!E6 -> KGS | F6: ='SO UTGST'!F6 -> NOS | G6: ='SO UTGST'!G6 -> 20 | H6: ='SO UTGST'!H6 -> 3214 | ... V6: ='SO UTGST'!V6 -> 772213 | W6: 0.05 | X6: ='SO UTGST'!X6 -> 1332.8 | Y6: ='SO UTGST'!Y6 -> 0 | Z6: ='SO UTGST'!Z6 -> 0 | AA6: ='SO UTGST'!AA6 -> 1332.8 | AB6: 0.06 | AC6: ='SO UTGST'!AC6 -> 0 | AD6: ='SO UTGST'!AD6 -> 2665.6 | AE6: ='SO UTGST'!AE6 -> 55977.76 | AF6: ='SO UTGST'!AF6 -> 120 | AG6: ='SO UTGST'!AG6 -> 53312.16 | AH6: ='SO UTGST'!AH6 -> 3 | AI6: ='SO UTGST'!AI6 -> 6.667 | AJ6: ='SO UTGST'!AJ6 -> 1375.002 | ... AQ6: ='SO UTGST'!AQ6 -> DOMESTIC | AR6: 40 | AS6: 3214 | AT6: =AR6*AS6 -> 128560 | AU6: 2 | AV6: 7 | AW6: 9 | AX6: =AT6 -> 128560 | AY6: =ROUND((AX6*AU6)/100,2) -> 2571.2 | AZ6: =AT6-AY6 -> 125988.8 | BA6: =ROUND((AZ6*AV6)/100,2) -> 8819.22 | BB6: =ROUND(AZ6-BA6,2) -> 117169.58 | BC6: =ROUND((BB6*AW6)/100,2) -> 10545.26 | BD6: =AY6+BA6+BC6 -> 21935.68 | BE6: =ROUND(BD6/AR6,2) -> 548.39 | BF6: =(AT6-BD6) -> 106624.32 | BG6: 772213 | BH6: 0.05 | BI6: =IF(OR($D$3=1,$D$3=4),ROUND((BF6*BH6)/2,2),0) -> 2665.61 | BJ6: =IF($D$3=1,ROUND(((BF6*BH6)/2),2),0) -> 0 | BK6: =IF($D$3=2,ROUND(((BF6*BH6)),2),0) -> 0 | BL6: =IF($D$3=4,ROUND(((BF6*BH6)/2),2),0) -> 2665.61 | BM6: 0.06 | BN6: =IF($D$3=5,ROUND(((BF6*BM6)/2),2),0) -> 0 | BO6: =BI6+BJ6+BK6+BL6+BN6 -> 5331.22 | BP6: =BF6+BO6 -> 111955.54 | BQ6: 120 | BR6: =BF6*$N$3 -> 106624.32 | BS6: DOMESTIC
A7: 3 | B7: HK-TVS-FG-10001 | C7: 0 | D7: HK-TVS-FG-10001 | E7: MTON | F7: MTON | G7: 0 | H7: 0 | I7: 0 | J7: 0 | K7: 0 | L7: 0 | M7: 0 | N7: 0 | O7: 0 | P7: 0 | Q7: 0 | R7: 0 | S7: 0 | T7: 0 | U7: 0 | V7: 0 | W7: 0 | X7: 0 | Y7: 0 | Z7: 0 | AA7: 0 | AB7: 0 | AC7: 0 | AD7: 0 | AE7: 0 | AF7: 0 | AG7: 0 | AH7: 0 | AI7: 0 | AJ7: 0 | AK7: 0 | AL7: 0 | AM7: 0 | AN7: 0 | AO7: 0 | AP7: 0 | AQ7: DOMESTIC | AR7: 50 | AS7: 6754 | AT7: =AR7*AS7 -> 337700 | AU7: 4 | AV7: 6 | AW7: 8 | AX7: =AT7 -> 337700 | AY7: =ROUND((AX7*AU7)/100,2) -> 13508 | AZ7: =AT7-AY7 -> 324192 | BA7: =ROUND((AZ7*AV7)/100,2) -> 19451.52 | BB7: =ROUND(AZ7-BA7,2) -> 304740.48 | BC7: =ROUND((BB7*AW7)/100,2) -> 24379.24 | BD7: =AY7+BA7+BC7 -> 57338.76 | BE7: =ROUND(BD7/AR7,2) -> 1146.78 | BF7: =(AT7-BD7) -> 280361.24 | BG7: 772213 | BH7: 0.05 | BI7: =IF(OR($D$3=1,$D$3=4),ROUND((BF7*BH7)/2,2),0) -> 7009.03 | BJ7: =IF($D$3=1,ROUND(((BF7*BH7)/2),2),0) -> 0 | BK7: =IF($D$3=2,ROUND(((BF7*BH7)),2),0) -> 0 | BL7: =IF($D$3=4,ROUND(((BF7*BH7)/2),2),0) -> 7009.03 | BM7: 0.06 | BN7: =IF($D$3=5,ROUND(((BF7*BM7)/2),2),0) -> 0 | BO7: =BI7+BJ7+BK7+BL7+BN7 -> 14018.06 | BP7: =BF7+BO7 -> 294379.3 | BQ7: 120 | BR7: =BF7*$N$3 -> 280361.24 | BS7: DOMESTIC
BB8: DISC AMOUNT | BD8: =SUM(BD5:BD7) -> 81814.31 | BK8: NET AMOUNT | BP8: =SUM(BP5:BP7) -> 444952.59 | BQ8: SALES AMOUNT | BR8: =SUM(BR5:BR7) -> 421465.69

Sheet SO Amendment Qty UTGST
A1: Scenario : Local Sales - Stock UOM and Sales UOM (Similar) DOC NO : SORD-2425-00089
A2: Sales Order
A3: GST Sales | D3: 4 | E3: (1 - Local Sales,2 Interstate Sales, 3 Export Sales) | J3: Cur. | K3: INR | M3: Ex. Rate | N3: 1
A4: S. No. | B4: Item | C4: Rev | D4: Item Desc. | E4: Stk. UOM | F4: Sale. UOM | G4: Order Qty (Sale UOM) | H4: Unit Price | I4: Gross Amt. | J4: TD% | K4: SD% | L4: CD% | M4: TD Asbl. Val. | N4: TD Amt. | O4: SD Asbl. Val. | P4: SD Amt. | Q4: CD Asbl. Val. | R4: CD Amt. | S4: Disc. Amt. | T4: Disc.Amt.Per.Qty | U4: Sales Val. | V4: HSN | W4: Tax Rate | X4: CGST | Y4: SGST | Z4: IGST | AA4: UTGST | AB4: CESS % | AC4: CESS AMT | AD4: Tax amt | AE4: Net Amt | AF4: Weight/Vol | AG4: Sales Amt (BC) | AH4: Conv. Factor | AI4: Eqv. Stock Qty | AJ4: Before Stock Qty | AK4: Before Stock Cost | AL4: After Stock Qty | AM4: Warehouse | AN4: Promotional Type | AO4: CESS PCT | AP4: CESS AMT | AQ4: PriceClass | AR4: New Order Qty (Sale UOM) | AS4: New Unit Price | AT4: New Gross Amt. | AU4: New TD% | AV4: New SD% | AW4: New CD% | AX4: New TD Asbl. Val. | AY4: New TD Amt. | AZ4: New SD Asbl. Val. | BA4: New SD Amt. | BB4: New CD Asbl. Val. | BC4: New CD Amt. | BD4: New Disc. Amt. | BE4: New Disc.Amt.Per.Qty | BF4: New Sales Val. | BG4: New HSN | BH4: New Tax Rate | BI4: New CGST | BJ4: New SGST | BK4: New IGST | BL4: New UTGST | BM4: New CESS % | BN4: New CESS AMT | BO4: New Tax amt | BP4: New Net Amt | BQ4: Weight/Vol | BR4: New Sales Amt (BC) | BS4: New PriceClass
A5: ='SO UTGST'!A5 -> 1 | B5: ='SO UTGST'!B5 -> HK-FIFO-LOT-BATCH-10001(FG) | C5: ='SO UTGST'!C5 -> 0 | D5: ='SO UTGST'!D5 -> HK-FIFO-LOT-BATCH-10001(FG) | E5: ='SO UTGST'!E5 -> NOS | F5: ='SO UTGST'!F5 -> NOS | G5: ='SO UTGST'!G5 -> 10 | H5: ='SO UTGST'!H5 -> 1234 | ... V5: ='SO UTGST'!V5 -> (740410)-18% | W5: 0.12 | X5: ='SO UTGST'!X5 -> 689.6 | Y5: ='SO UTGST'!Y5 -> 0 | Z5: ='SO UTGST'!Z5 -> 0 | AA5: ='SO UTGST'!AA5 -> 689.6 | AB5: 0.06 | AC5: ='SO UTGST'!AC5 -> 0 | AD5: ='SO UTGST'!AD5 -> 1379.2 | AE5: ='SO UTGST'!AE5 -> 12872.58 | AF5: ='SO UTGST'!AF5 -> 120 | AG5: ='SO UTGST'!AG5 -> 11493.38 | AH5: ='SO UTGST'!AH5 -> 1 | AI5: ='SO UTGST'!AI5 -> 10 | AJ5: ='SO UTGST'!AJ5 -> 848 | ... AQ5: ='SO UTGST'!AQ5 -> DOMESTIC | AR5: 30 | AS5: 1234 | AT5: =AR5*AS5 -> 37020 | AU5: 1 | AV5: 2 | AW5: 4 | AX5: =AT5 -> 37020 | AY5: =ROUND((AX5*AU5)/100,2) -> 370.2 | AZ5: =AT5-AY5 -> 36649.8 | BA5: =ROUND((AZ5*AV5)/100,2) -> 733 | BB5: =ROUND(AZ5-BA5,2) -> 35916.8 | BC5: =ROUND((BB5*AW5)/100,2) -> 1436.67 | BD5: =AY5+BA5+BC5 -> 2539.87 | BE5: =ROUND(BD5/AR5,2) -> 84.66 | BF5: =(AT5-BD5) -> 34480.13 | BG5: (740410)-18% | BH5: 0.12 | BI5: =IF(OR($D$3=1,$D$3=4),ROUND((BF5*BH5)/2,2),0) -> 2068.81 | BJ5: =IF($D$3=1,ROUND(((BF5*BH5)/2),2),0) -> 0 | BK5: =IF($D$3=2,ROUND(((BF5*BH5)),2),0) -> 0 | BL5: =IF($D$3=4,ROUND(((BF5*BH5)/2),2),0) -> 2068.81 | BM5: 0.06 | BN5: =IF($D$3=5,ROUND(((BF5*BM5)/2),2),0) -> 0 | BO5: =BI5+BJ5+BK5+BL5+BN5 -> 4137.62 | BP5: =BF5+BO5 -> 38617.75 | BQ5: 120 | BR5: =BF5*$N$3 -> 34480.13 | BS5: DOMESTIC
A6: ='SO UTGST'!A6 -> 2 | B6: ='SO UTGST'!B6 -> HK-FG-DISSIMILAR-10001 | C6: ='SO UTGST'!C6 -> 0 | D6: ='SO UTGST'!D6 -> HK-FG-DISSIMILAR-10001 | E6: ='SO UTGST'!E6 -> KGS | F6: ='SO UTGST'!F6 -> NOS | G6: ='SO UTGST'!G6 -> 20 | H6: ='SO UTGST'!H6 -> 3214 | ... V6: ='SO UTGST'!V6 -> 772213 | W6: 0.05 | X6: ='SO UTGST'!X6 -> 1332.8 | Y6: ='SO UTGST'!Y6 -> 0 | Z6: ='SO UTGST'!Z6 -> 0 | AA6: ='SO UTGST'!AA6 -> 1332.8 | AB6: 0.06 | AC6: ='SO UTGST'!AC6 -> 0 | AD6: ='SO UTGST'!AD6 -> 2665.6 | AE6: ='SO UTGST'!AE6 -> 55977.76 | AF6: ='SO UTGST'!AF6 -> 120 | AG6: ='SO UTGST'!AG6 -> 53312.16 | AH6: ='SO UTGST'!AH6 -> 3 | AI6: ='SO UTGST'!AI6 -> 6.667 | AJ6: ='SO UTGST'!AJ6 -> 1375.002 | ... AQ6: ='SO UTGST'!AQ6 -> DOMESTIC | AR6: 40 | AS6: 3214 | AT6: =AR6*AS6 -> 128560 | AU6: 2 | AV6: 7 | AW6: 9 | AX6: =AT6 -> 128560 | AY6: =ROUND((AX6*AU6)/100,2) -> 2571.2 | AZ6: =AT6-AY6 -> 125988.8 | BA6: =ROUND((AZ6*AV6)/100,2) -> 8819.22 | BB6: =ROUND(AZ6-BA6,2) -> 117169.58 | BC6: =ROUND((BB6*AW6)/100,2) -> 10545.26 | BD6: =AY6+BA6+BC6 -> 21935.68 | BE6: =ROUND(BD6/AR6,2) -> 548.39 | BF6: =(AT6-BD6) -> 106624.32 | BG6: 772213 | BH6: 0.05 | BI6: =IF(OR($D$3=1,$D$3=4),ROUND((BF6*BH6)/2,2),0) -> 2665.61 | BJ6: =IF($D$3=1,ROUND(((BF6*BH6)/2),2),0) -> 0 | BK6: =IF($D$3=2,ROUND(((BF6*BH6)),2),0) -> 0 | BL6: =IF($D$3=4,ROUND(((BF6*BH6)/2),2),0) -> 2665.61 | BM6: 0.06 | BN6: =IF($D$3=5,ROUND(((BF6*BM6)/2),2),0) -> 0 | BO6: =BI6+BJ6+BK6+BL6+BN6 -> 5331.22 | BP6: =BF6+BO6 -> 111955.54 | BQ6: 120 | BR6: =BF6*$N$3 -> 106624.32 | BS6: DOMESTIC
Q7: DISC AMOUNT | S7: =SUM(S5:S6) -> 11814.46 | Z7: NET AMOUNT | AE7: =SUM(AE5:AE6) -> 68850.34 | AF7: SALES AMOUNT | AG7: =AG5 -> 11493.38 | BB7: DISC AMOUNT | BD7: =SUM(BD5:BD6) -> 24475.55 | BK7: NET AMOUNT | BP7: =SUM(BP5:BP6) -> 150573.29 | BQ7: SALES AMOUNT | BR7: =BR5 -> 34480.13

Sheet SO Amendment Qty
A1: Scenario : Local Sales - Stock UOM and Sales UOM (Similar) DOC NO : SORD-2425-00089
A2: Sales Order Amendment
A3: GST Sales | D3: =SO!D3 -> 2 | E3: (1 - Local Sales,2 Interstate Sales, 3 Export Sales) | J3: Cur. | K3: INR | M3: Ex. Rate | N3: 1
A4: S. No. | B4: Item | C4: Rev | D4: Item Desc. | E4: Stk. UOM | F4: Sale. UOM | G4: Old Order Qty (Sale UOM) | H4: Old Unit Price | I4: Old Gross Amt. | J4: Old TD% | K4: Old SD% | L4: Old CD% | M4: Old TD Asbl. Val. | N4: Old TD Amt. | O4: Old SD Asbl. Val. | P4: Old SD Amt. | Q4: Old CD Asbl. Val. | R4: Old CD Amt. | S4: Old Disc. Amt. | T4: Old Disc.Amt.Per.Qty | U4: Old Sales Val. | V4: Old HSN | W4: Old Tax Rate | X4: Old CGST | Y4: Old SGST | Z4: Old IGST | AA4: Old Tax amt | AB4: Old Net Amt | AC4: Weight/Vol | AD4: Old Sales Amt (BC) | AE4: Conv. Factor | AF4: Eqv. Stock Qty | AG4: Before Stock Qty | AH4: Before Stock Cost | AI4: After Stock Qty | AJ4: Warehouse | AK4: Promotional Type | AL4: CESS PCT | AM4: CESS AMT | AN4: Old PriceClass | AO4: New Order Qty (Sale UOM) | AP4: New Unit Price | AQ4: New Gross Amt. | AR4: New TD% | AS4: New SD% | AT4: New CD% | AU4: New TD Asbl. Val. | AV4: New TD Amt. | AW4: New SD Asbl. Val. | AX4: New SD Amt. | AY4: New CD Asbl. Val. | AZ4: New CD Amt. | BA4: New Disc. Amt. | BB4: New Disc.Amt.Per.Qty | BC4: New Sales Val. | BD4: New HSN | BE4: New Tax Rate | BF4: New CGST | BG4: New SGST | BH4: New IGST | BI4: New Tax amt | BJ4: New Net Amt | BK4: Weight/Vol | BL4: New Sales Amt (BC) | BM4: New PriceClass | BN4: SoAmdType
A5: 1 | B5: HK-FIFO-LOT-BATCH-10001(FG) | C5: 0 | D5: HK-FIFO-LOT-BATCH-10001(FG) | E5: NOS | F5: NOS | G5: =SO!G5 -> 10 | H5: =SO!H5 -> 1234 | I5: =SO!I5 -> 12340 | J5: =SO!J5 -> 1 | K5: =SO!K5 -> 2 | L5: =SO!L5 -> 4 | M5: =SO!M5 -> 12340 | N5: =SO!N5 -> 123.4 | ... AB5: =SO!AB5 -> 0.06 | AC5: 120 | AD5: =SO!AD5 -> 1379.21 | AE5: 1 | AF5: =G5/AE5 -> 10 | AG5: 848 | AH5: 235.36857 | AI5: =ROUND(AG5-G5,0) -> 838 | AJ5: F100 | AK5: =SO!AK5 -> 235.36857 | AL5: 0 | AM5: =ROUND(((AL5*U5)/100),2) -> 0 | AN5: =SO!AN5 -> Sales Regular | AO5: 20 | AP5: =SO!H5 -> 1234 | AQ5: =AO5*AP5 -> 24680 | AR5: =SO!J5 -> 1 | AS5: =SO!K5 -> 2 | AT5: =SO!L5 -> 4 | AU5: =AQ5 -> 24680 | AV5: =ROUND((AU5*AR5)/100,2) -> 246.8 | AW5: =AQ5-AV5 -> 24433.2 | AX5: =ROUND((AW5*AS5)/100,2) -> 488.66 | AY5: =ROUND(AW5-AX5,2) -> 23944.54 | AZ5: =ROUND((AY5*AT5)/100,2) -> 957.78 | BA5: =AV5+AX5+AZ5 -> 1693.24 | BB5: =ROUND(BA5/AO5,2) -> 84.66 | BC5: =(AQ5-BA5) -> 22986.76 | BD5: =V5 -> (740410)-18% | BE5: 0.12 | BF5: =IF(SO!$D$3=1,ROUND(((BC5*BE5)/2),2),0) -> 0 | BG5: =IF(SO!$D$3=1,ROUND(((BC5*BE5)/2),2),0) -> 0 | BH5: =IF(SO!$D$3=2,ROUND(((BC5*BE5)),2),0) -> 2758.41 | BI5: =BF5+BG5+BH5 -> 2758.41 | BJ5: =BC5+BI5 -> 25745.17 | BK5: 120 | BL5: =BC5*SO!$N$3 -> 22986.76 | BM5: Spare | BN5: Modify
A6: 2 | B6: HK-FG-DISSIMILAR-10001 | C6: 0 | D6: HK-FG-DISSIMILAR-10001 | E6: KGS | F6: NOS | G6: =SO!G6 -> 20 | H6: =SO!H6 -> 3214 | I6: =SO!I6 -> 64280 | J6: =SO!J6 -> 2 | K6: =SO!K6 -> 7 | L6: =SO!L6 -> 9 | M6: =SO!M6 -> 64280 | N6: =SO!N6 -> 1285.6 | ... AB6: =SO!AB6 -> 0.06 | AC6: 120 | AD6: =SO!AD6 -> 2665.61 | AE6: 3 | AF6: =ROUND(G6/AE6,3) -> 6.667 | AG6: 1375.002 | AH6: 123 | AI6: =ROUND((AG6-AF6),3) -> 1368.335 | AJ6: F100 | AK6: =SO!AK6 -> 123 | AL6: 0 | AM6: =ROUND(((AL6*U6)/100),2) -> 0 | AN6: =SO!AN6 -> Sales Regular | AO6: 30 | AP6: =SO!H6 -> 3214 | AQ6: =AO6*AP6 -> 96420 | AR6: =SO!J6 -> 2 | AS6: =SO!K6 -> 7 | AT6: =SO!L6 -> 9 | AU6: =AQ6 -> 96420 | AV6: =ROUND((AU6*AR6)/100,2) -> 1928.4 | AW6: =AQ6-AV6 -> 94491.6 | AX6: =ROUND((AW6*AS6)/100,2) -> 6614.41 | AY6: =ROUND(AW6-AX6,2) -> 87877.19 | AZ6: =ROUND((AY6*AT6)/100,2) -> 7908.95 | BA6: =AV6+AX6+AZ6 -> 16451.76 | BB6: =ROUND(BA6/AO6,2) -> 548.39 | BC6: =(AQ6-BA6) -> 79968.24 | BD6: =V6 -> 772213 | BE6: 0.05 | BF6: =IF(SO!$D$3=1,ROUND(((BC6*BE6)/2),2),0) -> 0 | BG6: =IF(SO!$D$3=1,ROUND(((BC6*BE6)/2),2),0) -> 0 | BH6: =IF(SO!$D$3=2,ROUND(((BC6*BE6)),2),0) -> 3998.41 | BI6: =BF6+BG6+BH6 -> 3998.41 | BJ6: =BC6+BI6 -> 83966.65 | BK6: 120 | BL6: =BC6*SO!$N$3 -> 79968.24 | BM6: Spare | BN6: Modify
Q7: DISC AMOUNT | S7: =SUM(S5:S6) -> 11814.46 | Z7: NET AMOUNT | AB7: =SUM(AB5:AB6) -> 0.12 | AC7: SALES AMOUNT | AD7: =SUM(AD5:AD6) -> 4044.82 | AY7: DISC AMOUNT | BA7: =SUM(BA5:BA6) -> 18145 | BH7: NET AMOUNT | BJ7: =SUM(BJ5:BJ6) -> 109711.82 | BK7: SALES AMOUNT | BL7: =SUM(BL5:BL6) -> 102955

Sheet Disc Change
A1: Scenario : Local Sales - Stock UOM and Sales UOM (Similar) DOC NO : SORD-2425-00089
A2: Sales Order
A3: GST Sales | D3: 2 | E3: (1 - Local Sales,2 Interstate Sales, 3 Export Sales) | J3: Cur. | K3: INR | M3: Ex. Rate | N3: 1
A4: S. No. | B4: Item | C4: Rev | D4: Item Desc. | E4: Stk. UOM | F4: Sale. UOM | G4: Order Qty (Sale UOM) | H4: Unit Price | I4: Gross Amt. | J4: TD% | K4: SD% | L4: CD% | M4: TD Asbl. Val. | N4: TD Amt. | O4: SD Asbl. Val. | P4: SD Amt. | Q4: CD Asbl. Val. | R4: CD Amt. | S4: Disc. Amt. | T4: Disc.Amt.Per.Qty | U4: Sales Val. | V4: HSN | W4: Tax Rate | X4: CGST | Y4: SGST | Z4: IGST | AA4: UTGST | AB4: CESS % | AC4: CESS AMT | AD4: Tax amt | AE4: Net Amt | AF4: Weight/Vol | AG4: Sales Amt (BC) | AH4: Conv. Factor | AI4: Eqv. Stock Qty | AJ4: Before Stock Qty | AK4: Before Stock Cost | AL4: After Stock Qty | AM4: Warehouse | AN4: Promotional Type | AO4: CESS PCT | AP4: CESS AMT | AQ4: PriceClass | AR4: Order Qty (Sale UOM) | AS4: Unit Price | AT4: Gross Amt. | AU4: TD% | AV4: SD% | AW4: CD% | AX4: TD Asbl. Val. | AY4: TD Amt. | AZ4: SD Asbl. Val. | BA4: SD Amt. | BB4: CD Asbl. Val. | BC4: CD Amt. | BD4: Disc. Amt. | BE4: Disc.Amt.Per.Qty | BF4: Sales Val. | BG4: HSN | BH4: Tax Rate | BI4: CGST | BJ4: SGST | BK4: IGST | BL4: UTGST | BM4: CESS % | BN4: CESS AMT | BO4: Tax amt | BP4: Net Amt | BQ4: Weight/Vol | BR4: Sales Amt (BC) | BS4: Promotional Type | BT4: PriceClass | BU4: SoAmdType
A5: =SO!A5 -> 1 | B5: =SO!B5 -> HK-FIFO-LOT-BATCH-10001(FG) | C5: =SO!C5 -> 0 | D5: =SO!D5 -> HK-FIFO-LOT-BATCH-10001(FG) | E5: =SO!E5 -> NOS | F5: =SO!F5 -> NOS | G5: =SO!G5 -> 10 | H5: =SO!H5 -> 1234 | ... V5: =SO!V5 -> (740410)-18% | W5: 0.12 | X5: =SO!X5 -> 0 | Y5: =SO!Y5 -> 0 | Z5: =SO!Z5 -> 1379.21 | AA5: =SO!AA5 -> 0 | AB5: 0.06 | AC5: =SO!AC5 -> 0 | AD5: =SO!AD5 -> 1379.21 | AE5: =SO!AE5 -> 12872.59 | AF5: =SO!AF5 -> 120 | AG5: =SO!AG5 -> 11493.38 | AH5: =SO!AH5 -> 1 | AI5: =SO!AI5 -> 10 | AJ5: =SO!AJ5 -> 848 | ... AQ5: =SO!AQ5 -> DOMESTIC | AR5: 10 | AS5: 1234 | AT5: =AR5*AS5 -> 12340 | AU5: 10 | AV5: 12 | AW5: 14 | AX5: =AT5 -> 12340 | AY5: =ROUND((AX5*AU5)/100,2) -> 1234 | AZ5: =AT5-AY5 -> 11106 | BA5: =ROUND((AZ5*AV5)/100,2) -> 1332.72 | BB5: =ROUND(AZ5-BA5,2) -> 9773.28 | BC5: =ROUND((BB5*AW5)/100,2) -> 1368.26 | BD5: =AY5+BA5+BC5 -> 3934.98 | BE5: =ROUND(BD5/AR5,2) -> 393.5 | BF5: =(AT5-BD5) -> 8405.02 | BG5: (740410)-18% | BH5: 0.12 | BI5: =IF(OR($D$3=1,$D$3=4),ROUND((BF5*BH5)/2,2),0) -> 0 | BJ5: =IF($D$3=1,ROUND(((BF5*BH5)/2),2),0) -> 0 | BK5: =IF($D$3=2,ROUND(((BF5*BH5)),2),0) -> 1008.6 | BL5: =IF($D$3=4,ROUND(((BF5*BH5)/2),2),0) -> 0 | BM5: 0.06 | BN5: =IF($D$3=5,ROUND(((BF5*BM5)/2),2),0) -> 0 | BO5: =BI5+BJ5+BK5+BL5+BN5 -> 1008.6 | BP5: =BF5+BO5 -> 9413.62 | BQ5: 120 | BR5: =BF5*$N$3 -> 8405.02 | BS5: Sales Regular | BT5: DOMESTIC | BU5: Modify
A6: =SO!A6 -> 2 | B6: =SO!B6 -> HK-FG-DISSIMILAR-10001 | C6: =SO!C6 -> 0 | D6: =SO!D6 -> HK-FG-DISSIMILAR-10001 | E6: =SO!E6 -> KGS | F6: =SO!F6 -> NOS | G6: =SO!G6 -> 20 | H6: =SO!H6 -> 3214 | ... V6: =SO!V6 -> 772213 | W6: 0.05 | X6: =SO!X6 -> 0 | Y6: =SO!Y6 -> 0 | Z6: =SO!Z6 -> 2665.61 | AA6: =SO!AA6 -> 0 | AB6: 0.06 | AC6: =SO!AC6 -> 0 | AD6: =SO!AD6 -> 2665.61 | AE6: =SO!AE6 -> 55977.77 | AF6: =SO!AF6 -> 120 | AG6: =SO!AG6 -> 53312.16 | AH6: =SO!AH6 -> 3 | AI6: =SO!AI6 -> 6.667 | AJ6: =SO!AJ6 -> 1375.002 | ... AQ6: =SO!AQ6 -> DOMESTIC | AR6: 20 | AS6: 3214 | AT6: =AR6*AS6 -> 64280 | AU6: 12 | AV6: 17 | AW6: 19 | AX6: =AT6 -> 64280 | AY6: =ROUND((AX6*AU6)/100,2) -> 7713.6 | AZ6: =AT6-AY6 -> 56566.4 | BA6: =ROUND((AZ6*AV6)/100,2) -> 9616.29 | BB6: =ROUND(AZ6-BA6,2) -> 46950.11 | BC6: =ROUND((BB6*AW6)/100,2) -> 8920.52 | BD6: =AY6+BA6+BC6 -> 26250.41 | BE6: =ROUND(BD6/AR6,2) -> 1312.52 | BF6: =(AT6-BD6) -> 38029.59 | BG6: 772213 | BH6: 0.05 | BI6: =IF(OR($D$3=1,$D$3=4),ROUND((BF6*BH6)/2,2),0) -> 0 | BJ6: =IF($D$3=1,ROUND(((BF6*BH6)/2),2),0) -> 0 | BK6: =IF($D$3=2,ROUND(((BF6*BH6)),2),0) -> 1901.48 | BL6: =IF($D$3=4,ROUND(((BF6*BH6)/2),2),0) -> 0 | BM6: 0.06 | BN6: =IF($D$3=5,ROUND(((BF6*BM6)/2),2),0) -> 0 | BO6: =BI6+BJ6+BK6+BL6+BN6 -> 1901.48 | BP6: =BF6+BO6 -> 39931.07 | BQ6: 120 | BR6: =BF6*$N$3 -> 38029.59 | BS6: Sales Regular | BT6: DOMESTIC | BU6: Modify
Q7: DISC AMOUNT | S7: =SUM(S5:S6) -> 11814.46 | Z7: NET AMOUNT | AE7: =SUM(AE5:AE6) -> 68850.36 | AF7: SALES AMOUNT | AG7: =AG5 -> 11493.38 | BB7: DISC AMOUNT | BD7: =SUM(BD5:BD6) -> 30185.39 | BK7: NET AMOUNT | BP7: =SUM(BP5:BP6) -> 49344.69 | BQ7: SALES AMOUNT | BR7: =BR5 -> 8405.02

Sheet Price Change
A1: Scenario : Local Sales - Stock UOM and Sales UOM (Similar) DOC NO : SORD-2425-00089
A2: Sales Order
A3: GST Sales | D3: 2 | E3: (1 - Local Sales,2 Interstate Sales, 3 Export Sales) | J3: Cur. | K3: INR | M3: Ex. Rate | N3: 1
A4: S. No. | B4: Item | C4: Rev | D4: Item Desc. | E4: Stk. UOM | F4: Sale. UOM | G4: Order Qty (Sale UOM) | H4: Unit Price | I4: Gross Amt. | J4: TD% | K4: SD% | L4: CD% | M4: TD Asbl. Val. | N4: TD Amt. | O4: SD Asbl. Val. | P4: SD Amt. | Q4: CD Asbl. Val. | R4: CD Amt. | S4: Disc. Amt. | T4: Disc.Amt.Per.Qty | U4: Sales Val. | V4: HSN | W4: Tax Rate | X4: CGST | Y4: SGST | Z4: IGST | AA4: UTGST | AB4: CESS % | AC4: CESS AMT | AD4: Tax amt | AE4: Net Amt | AF4: Weight/Vol | AG4: Sales Amt (BC) | AH4: Conv. Factor | AI4: Eqv. Stock Qty | AJ4: Before Stock Qty | AK4: Before Stock Cost | AL4: After Stock Qty | AM4: Warehouse | AN4: Promotional Type | AO4: CESS PCT | AP4: CESS AMT | AQ4: PriceClass | AR4: Order Qty (Sale UOM) | AS4: Unit Price | AT4: Gross Amt. | AU4: TD% | AV4: SD% | AW4: CD% | AX4: TD Asbl. Val. | AY4: TD Amt. | AZ4: SD Asbl. Val. | BA4: SD Amt. | BB4: CD Asbl. Val. | BC4: CD Amt. | BD4: Disc. Amt. | BE4: Disc.Amt.Per.Qty | BF4: Sales Val. | BG4: HSN | BH4: Tax Rate | BI4: CGST | BJ4: SGST | BK4: IGST | BL4: UTGST | BM4: CESS % | BN4: CESS AMT | BO4: Tax amt | BP4: Net Amt | BQ4: Weight/Vol | BR4: Sales Amt (BC) | BS4: Promotional Type | BT4: PriceClass | BU4: SoAmdType
A5: =SO!A5 -> 1 | B5: =SO!B5 -> HK-FIFO-LOT-BATCH-10001(FG) | C5: =SO!C5 -> 0 | D5: =SO!D5 -> HK-FIFO-LOT-BATCH-10001(FG) | E5: =SO!E5 -> NOS | F5: =SO!F5 -> NOS | G5: =SO!G5 -> 10 | H5: =SO!H5 -> 1234 | ... V5: =SO!V5 -> (740410)-18% | W5: 0.12 | X5: =SO!X5 -> 0 | Y5: =SO!Y5 -> 0 | Z5: =SO!Z5 -> 1379.21 | AA5: =SO!AA5 -> 0 | AB5: 0.06 | AC5: =SO!AC5 -> 0 | AD5: =SO!AD5 -> 1379.21 | AE5: =SO!AE5 -> 12872.59 | AF5: =SO!AF5 -> 120 | AG5: =SO!AG5 -> 11493.38 | AH5: =SO!AH5 -> 1 | AI5: =SO!AI5 -> 10 | AJ5: =SO!AJ5 -> 848 | ... AQ5: =SO!AQ5 -> DOMESTIC | AR5: 10 | AS5: 2150 | AT5: =AR5*AS5 -> 21500 | AU5: 1 | AV5: 2 | AW5: 4 | AX5: =AT5 -> 21500 | AY5: =ROUND((AX5*AU5)/100,2) -> 215 | AZ5: =AT5-AY5 -> 21285 | BA5: =ROUND((AZ5*AV5)/100,2) -> 425.7 | BB5: =ROUND(AZ5-BA5,2) -> 20859.3 | BC5: =ROUND((BB5*AW5)/100,2) -> 834.37 | BD5: =AY5+BA5+BC5 -> 1475.07 | BE5: =ROUND(BD5/AR5,2) -> 147.51 | BF5: =(AT5-BD5) -> 20024.93 | BG5: (740410)-18% | BH5: 0.12 | BI5: =IF(OR($D$3=1,$D$3=4),ROUND((BF5*BH5)/2,2),0) -> 0 | BJ5: =IF($D$3=1,ROUND(((BF5*BH5)/2),2),0) -> 0 | BK5: =IF($D$3=2,ROUND(((BF5*BH5)),2),0) -> 2402.99 | BL5: =IF($D$3=4,ROUND(((BF5*BH5)/2),2),0) -> 0 | BM5: 0.06 | BN5: =IF($D$3=5,ROUND(((BF5*BM5)/2),2),0) -> 0 | BO5: =BI5+BJ5+BK5+BL5+BN5 -> 2402.99 | BP5: =BF5+BO5 -> 22427.92 | BQ5: 120 | BR5: =BF5*$N$3 -> 20024.93 | BS5: Sales Regular | BT5: DOMESTIC | BU5: Modify
A6: =SO!A6 -> 2 | B6: =SO!B6 -> HK-FG-DISSIMILAR-10001 | C6: =SO!C6 -> 0 | D6: =SO!D6 -> HK-FG-DISSIMILAR-10001 | E6: =SO!E6 -> KGS | F6: =SO!F6 -> NOS | G6: =SO!G6 -> 20 | H6: =SO!H6 -> 3214 | ... V6: =SO!V6 -> 772213 | W6: 0.05 | X6: =SO!X6 -> 0 | Y6: =SO!Y6 -> 0 | Z6: =SO!Z6 -> 2665.61 | AA6: =SO!AA6 -> 0 | AB6: 0.06 | AC6: =SO!AC6 -> 0 | AD6: =SO!AD6 -> 2665.61 | AE6: =SO!AE6 -> 55977.77 | AF6: =SO!AF6 -> 120 | AG6: =SO!AG6 -> 53312.16 | AH6: =SO!AH6 -> 3 | AI6: =SO!AI6 -> 6.667 | AJ6: =SO!AJ6 -> 1375.002 | ... AQ6: =SO!AQ6 -> DOMESTIC | AR6: 20 | AS6: 3265 | AT6: =AR6*AS6 -> 65300 | AU6: 2 | AV6: 7 | AW6: 9 | AX6: =AT6 -> 65300 | AY6: =ROUND((AX6*AU6)/100,2) -> 1306 | AZ6: =AT6-AY6 -> 63994 | BA6: =ROUND((AZ6*AV6)/100,2) -> 4479.58 | BB6: =ROUND(AZ6-BA6,2) -> 59514.42 | BC6: =ROUND((BB6*AW6)/100,2) -> 5356.3 | BD6: =AY6+BA6+BC6 -> 11141.88 | BE6: =ROUND(BD6/AR6,2) -> 557.09 | BF6: =(AT6-BD6) -> 54158.12 | BG6: 772213 | BH6: 0.05 | BI6: =IF(OR($D$3=1,$D$3=4),ROUND((BF6*BH6)/2,2),0) -> 0 | BJ6: =IF($D$3=1,ROUND(((BF6*BH6)/2),2),0) -> 0 | BK6: =IF($D$3=2,ROUND(((BF6*BH6)),2),0) -> 2707.91 | BL6: =IF($D$3=4,ROUND(((BF6*BH6)/2),2),0) -> 0 | BM6: 0.06 | BN6: =IF($D$3=5,ROUND(((BF6*BM6)/2),2),0) -> 0 | BO6: =BI6+BJ6+BK6+BL6+BN6 -> 2707.91 | BP6: =BF6+BO6 -> 56866.03 | BQ6: 120 | BR6: =BF6*$N$3 -> 54158.12 | BS6: Sales Regular | BT6: DOMESTIC | BU6: Modify
Q7: DISC AMOUNT | S7: =SUM(S5:S6) -> 11814.46 | Z7: NET AMOUNT | AE7: =SUM(AE5:AE6) -> 68850.36 | AF7: SALES AMOUNT | AG7: =AG5 -> 11493.38 | BB7: DISC AMOUNT | BD7: =SUM(BD5:BD6) -> 12616.95 | BK7: NET AMOUNT | BP7: =SUM(BP5:BP6) -> 79293.95 | BQ7: SALES AMOUNT | BR7: =BR5 -> 20024.93

Sheet Qty Change
A1: Scenario : Local Sales - Stock UOM and Sales UOM (Similar) DOC NO : SORD-2425-00089
A2: Sales Order
A3: GST Sales | D3: 2 | E3: (1 - Local Sales,2 Interstate Sales, 3 Export Sales) | J3: Cur. | K3: INR | M3: Ex. Rate | N3: 1
A4: S. No. | B4: Item | C4: Rev | D4: Item Desc. | E4: Stk. UOM | F4: Sale. UOM | G4: Order Qty (Sale UOM) | H4: Unit Price | I4: Gross Amt. | J4: TD% | K4: SD% | L4: CD% | M4: TD Asbl. Val. | N4: TD Amt. | O4: SD Asbl. Val. | P4: SD Amt. | Q4: CD Asbl. Val. | R4: CD Amt. | S4: Disc. Amt. | T4: Disc.Amt.Per.Qty | U4: Sales Val. | V4: HSN | W4: Tax Rate | X4: CGST | Y4: SGST | Z4: IGST | AA4: UTGST | AB4: CESS % | AC4: CESS AMT | AD4: Tax amt | AE4: Net Amt | AF4: Weight/Vol | AG4: Sales Amt (BC) | AH4: Conv. Factor | AI4: Eqv. Stock Qty | AJ4: Before Stock Qty | AK4: Before Stock Cost | AL4: After Stock Qty | AM4: Warehouse | AN4: Promotional Type | AO4: CESS PCT | AP4: CESS AMT | AQ4: PriceClass | AR4: Order Qty (Sale UOM) | AS4: Unit Price | AT4: Gross Amt. | AU4: TD% | AV4: SD% | AW4: CD% | AX4: TD Asbl. Val. | AY4: TD Amt. | AZ4: SD Asbl. Val. | BA4: SD Amt. | BB4: CD Asbl. Val. | BC4: CD Amt. | BD4: Disc. Amt. | BE4: Disc.Amt.Per.Qty | BF4: Sales Val. | BG4: HSN | BH4: Tax Rate | BI4: CGST | BJ4: SGST | BK4: IGST | BL4: UTGST | BM4: CESS % | BN4: CESS AMT | BO4: Tax amt | BP4: Net Amt | BQ4: Weight/Vol | BR4: Sales Amt (BC) | BS4: Promotional Type | BT4: PriceClass | BU4: SoAmdType
A5: =SO!A5 -> 1 | B5: =SO!B5 -> HK-FIFO-LOT-BATCH-10001(FG) | C5: =SO!C5 -> 0 | D5: =SO!D5 -> HK-FIFO-LOT-BATCH-10001(FG) | E5: =SO!E5 -> NOS | F5: =SO!F5 -> NOS | G5: =SO!G5 -> 10 | H5: =SO!H5 -> 1234 | ... V5: =SO!V5 -> (740410)-18% | W5: 0.12 | X5: =SO!X5 -> 0 | Y5: =SO!Y5 -> 0 | Z5: =SO!Z5 -> 1379.21 | AA5: =SO!AA5 -> 0 | AB5: 0.06 | AC5: =SO!AC5 -> 0 | AD5: =SO!AD5 -> 1379.21 | AE5: =SO!AE5 -> 12872.59 | AF5: =SO!AF5 -> 120 | AG5: =SO!AG5 -> 11493.38 | AH5: =SO!AH5 -> 1 | AI5: =SO!AI5 -> 10 | AJ5: =SO!AJ5 -> 848 | ... AQ5: =SO!AQ5 -> DOMESTIC | AR5: 30 | AS5: 1234 | AT5: =AR5*AS5 -> 37020 | AU5: 1 | AV5: 2 | AW5: 4 | AX5: =AT5 -> 37020 | AY5: =ROUND((AX5*AU5)/100,2) -> 370.2 | AZ5: =AT5-AY5 -> 36649.8 | BA5: =ROUND((AZ5*AV5)/100,2) -> 733 | BB5: =ROUND(AZ5-BA5,2) -> 35916.8 | BC5: =ROUND((BB5*AW5)/100,2) -> 1436.67 | BD5: =AY5+BA5+BC5 -> 2539.87 | BE5: =ROUND(BD5/AR5,2) -> 84.66 | BF5: =(AT5-BD5) -> 34480.13 | BG5: (740410)-18% | BH5: 0.12 | BI5: =IF(OR($D$3=1,$D$3=4),ROUND((BF5*BH5)/2,2),0) -> 0 | BJ5: =IF($D$3=1,ROUND(((BF5*BH5)/2),2),0) -> 0 | BK5: =IF($D$3=2,ROUND(((BF5*BH5)),2),0) -> 4137.62 | BL5: =IF($D$3=4,ROUND(((BF5*BH5)/2),2),0) -> 0 | BM5: 0.06 | BN5: =IF($D$3=5,ROUND(((BF5*BM5)/2),2),0) -> 0 | BO5: =BI5+BJ5+BK5+BL5+BN5 -> 4137.62 | BP5: =BF5+BO5 -> 38617.75 | BQ5: 120 | BR5: =BF5*$N$3 -> 34480.13 | BS5: Sales Regular | BT5: DOMESTIC | BU5: Modify
A6: =SO!A6 -> 2 | B6: =SO!B6 -> HK-FG-DISSIMILAR-10001 | C6: =SO!C6 -> 0 | D6: =SO!D6 -> HK-FG-DISSIMILAR-10001 | E6: =SO!E6 -> KGS | F6: =SO!F6 -> NOS | G6: =SO!G6 -> 20 | H6: =SO!H6 -> 3214 | ... V6: =SO!V6 -> 772213 | W6: 0.05 | X6: =SO!X6 -> 0 | Y6: =SO!Y6 -> 0 | Z6: =SO!Z6 -> 2665.61 | AA6: =SO!AA6 -> 0 | AB6: 0.06 | AC6: =SO!AC6 -> 0 | AD6: =SO!AD6 -> 2665.61 | AE6: =SO!AE6 -> 55977.77 | AF6: =SO!AF6 -> 120 | AG6: =SO!AG6 -> 53312.16 | AH6: =SO!AH6 -> 3 | AI6: =SO!AI6 -> 6.667 | AJ6: =SO!AJ6 -> 1375.002 | ... AQ6: =SO!AQ6 -> DOMESTIC | AR6: 50 | AS6: 3214 | AT6: =AR6*AS6 -> 160700 | AU6: 2 | AV6: 7 | AW6: 9 | AX6: =AT6 -> 160700 | AY6: =ROUND((AX6*AU6)/100,2) -> 3214 | AZ6: =AT6-AY6 -> 157486 | BA6: =ROUND((AZ6*AV6)/100,2) -> 11024.02 | BB6: =ROUND(AZ6-BA6,2) -> 146461.98 | BC6: =ROUND((BB6*AW6)/100,2) -> 13181.58 | BD6: =AY6+BA6+BC6 -> 27419.6 | BE6: =ROUND(BD6/AR6,2) -> 548.39 | BF6: =(AT6-BD6) -> 133280.4 | BG6: 772213 | BH6: 0.05 | BI6: =IF(OR($D$3=1,$D$3=4),ROUND((BF6*BH6)/2,2),0) -> 0 | BJ6: =IF($D$3=1,ROUND(((BF6*BH6)/2),2),0) -> 0 | BK6: =IF($D$3=2,ROUND(((BF6*BH6)),2),0) -> 6664.02 | BL6: =IF($D$3=4,ROUND(((BF6*BH6)/2),2),0) -> 0 | BM6: 0.06 | BN6: =IF($D$3=5,ROUND(((BF6*BM6)/2),2),0) -> 0 | BO6: =BI6+BJ6+BK6+BL6+BN6 -> 6664.02 | BP6: =BF6+BO6 -> 139944.42 | BQ6: 120 | BR6: =BF6*$N$3 -> 133280.4 | BS6: Sales Regular | BT6: DOMESTIC | BU6: Modify
Q7: DISC AMOUNT | S7: =SUM(S5:S6) -> 11814.46 | Z7: NET AMOUNT | AE7: =SUM(AE5:AE6) -> 68850.36 | AF7: SALES AMOUNT | AG7: =AG5 -> 11493.38 | BB7: DISC AMOUNT | BD7: =SUM(BD5:BD6) -> 29959.47 | BK7: NET AMOUNT | BP7: =SUM(BP5:BP6) -> 178562.17 | BQ7: SALES AMOUNT | BR7: =BR5 -> 34480.13

Sheet So Amend Price Local
A1: Scenario : Local Sales - Stock UOM and Sales UOM (Similar) DOC NO : SORD-2425-00089
A2: Sales Order
A3: GST Sales | D3: 1 | E3: (1 - Local Sales,2 Interstate Sales, 3 Import Sales) | J3: Cur. | K3: INR | M3: Ex. Rate | N3: 1
A4: S. No. | B4: Item | C4: Rev | D4: Item Desc. | E4: Stk. UOM | F4: Sale. UOM | G4: Order Qty (Sale UOM) | H4: Unit Price | I4: Gross Amt. | J4: TD% | K4: SD% | L4: CD% | M4: TD Asbl. Val. | N4: TD Amt. | O4: SD Asbl. Val. | P4: SD Amt. | Q4: CD Asbl. Val. | R4: CD Amt. | S4: Disc. Amt. | T4: Disc.Amt.Per.Qty | U4: Sales Val. | V4: HSN | W4: Tax Rate | X4: CGST | Y4: SGST | Z4: IGST | AA4: UTGST | AB4: CESS % | AC4: CESS AMT | AD4: Tax amt | AE4: Net Amt | AF4: Weight/Vol | AG4: Sales Amt (BC) | AH4: Conv. Factor | AI4: Eqv. Stock Qty | AJ4: Before Stock Qty | AK4: Before Stock Cost | AL4: After Stock Qty | AM4: Warehouse | AN4: Promotional Type | AO4: CESS PCT | AP4: CESS AMT | AQ4: PriceClass | AR4: Order Qty (Sale UOM) | AS4: Unit Price | AT4: Gross Amt. | AU4: TD% | AV4: SD% | AW4: CD% | AX4: TD Asbl. Val. | AY4: TD Amt. | AZ4: SD Asbl. Val. | BA4: SD Amt. | BB4: CD Asbl. Val. | BC4: CD Amt. | BD4: Disc. Amt. | BE4: Disc.Amt.Per.Qty | BF4: Sales Val. | BG4: HSN | BH4: Tax Rate | BI4: CGST | BJ4: SGST | BK4: IGST | BL4: UTGST | BM4: CESS % | BN4: CESS AMT | BO4: Tax amt | BP4: Net Amt | BQ4: Weight/Vol | BR4: Sales Amt (BC) | BS4: Promotional Type | BT4: PriceClass | BU4: SoAmdType
A5: 1 | B5: HK-FIFO-LOT-BATCH-10001(FG) | C5: 0 | D5: HK-FIFO-LOT-BATCH-10001(FG) | E5: NOS | F5: NOS | G5: 10 | H5: 1500 | I5: =G5*H5 -> 15000 | J5: 2 | K5: 3 | L5: 5 | M5: =I5 -> 15000 | N5: =ROUND((M5*J5)/100,2) -> 300 | O5: =I5-N5 -> 14700 | P5: =ROUND((O5*K5)/100,2) -> 441 | Q5: =ROUND(O5-P5,2) -> 14259 | R5: =ROUND((Q5*L5)/100,2) -> 712.95 | S5: =ROUND(N5+P5+R5,2) -> 1453.95 | T5: =ROUND(S5/G5,2) -> 145.4 | U5: =(I5-S5) -> 13546.05 | V5: HSN1 | W5: 0.12 | X5: =IF(OR($D$3=1,$D$3=4),ROUND((U5*W5)/2,2),0) -> 812.76 | Y5: =IF($D$3=1,ROUND(((U5*W5)/2),2),0) -> 812.76 | Z5: =IF($D$3=2,ROUND(((U5*W5)),2),0) -> 0 | AA5: =IF($D$3=4,ROUND(((U5*W5)/2),2),0) -> 0 | AB5: 0.06 | AC5: =IF($D$3=5,ROUND(((U5*AB5)/2),2),0) -> 0 | AD5: =X5+Y5+Z5+AA5+AC5 -> 1625.52 | AE5: =U5+AD5 -> 15171.57 | AF5: 120 | AG5: =U5*$N$3 -> 13546.05 | AH5: 1 | AI5: =G5/AH5 -> 10 | AJ5: 848 | AK5: 235.36857 | AL5: =ROUND(AJ5-G5,0) -> 838 | AM5: F100 | AN5: Sales Regular | AO5: 0 | AP5: =ROUND(((AO5*U5)/100),2) -> 0 | AQ5: DOMESTIC | AR5: 10 | AS5: 2567 | AT5: =AR5*AS5 -> 25670 | AU5: 2 | AV5: 3 | AW5: 5 | AX5: =AT5 -> 25670 | AY5: =ROUND((AX5*AU5)/100,2) -> 513.4 | AZ5: =AT5-AY5 -> 25156.6 | BA5: =ROUND((AZ5*AV5)/100,2) -> 754.7 | BB5: =ROUND(AZ5-BA5,2) -> 24401.9 | BC5: =ROUND((BB5*AW5)/100,2) -> 1220.1 | BD5: =ROUND(AY5+BA5+BC5,2) -> 2488.2 | BE5: =ROUND(BD5/AR5,2) -> 248.82 | BF5: =(AT5-BD5) -> 23181.8 | BG5: HSN1 | BH5: 0.12 | BI5: =IF(OR($D$3=1,$D$3=4),ROUND((BF5*BH5)/2,2),0) -> 1390.91 | BJ5: =IF($D$3=1,ROUND(((BF5*BH5)/2),2),0) -> 1390.91 | BK5: =IF($D$3=2,ROUND(((BF5*BH5)),2),0) -> 0 | BL5: =IF($D$3=4,ROUND(((BF5*BH5)/2),2),0) -> 0 | BM5: 0.06 | BN5: =IF($D$3=5,ROUND(((BF5*BM5)/2),2),0) -> 0 | BO5: =BI5+BJ5+BK5+BL5+BN5 -> 2781.82 | BP5: =BF5+BO5 -> 25963.62 | BQ5: 120 | BR5: =BF5*$N$3 -> 23181.8 | BS5: Sales Regular | BT5: DOMESTIC | BU5: Modify
A6: 2 | B6: HK-FG-DISSIMILAR-10001 | C6: 0 | D6: HK-FG-DISSIMILAR-10001 | E6: KGS | F6: NOS | G6: 10 | H6: 2000 | I6: =G6*H6 -> 20000 | J6: 5 | K6: 7 | L6: 9 | M6: =I6 -> 20000 | N6: =ROUND((M6*J6)/100,2) -> 1000 | O6: =I6-N6 -> 19000 | P6: =ROUND((O6*K6)/100,2) -> 1330 | Q6: =ROUND(O6-P6,2) -> 17670 | R6: =ROUND((Q6*L6)/100,2) -> 1590.3 | S6: =ROUND(N6+P6+R6,2) -> 3920.3 | T6: =ROUND(S6/G6,2) -> 392.03 | U6: =(I6-S6) -> 16079.7 | V6: HSN1 | W6: 0.05 | X6: =IF(OR($D$3=1,$D$3=4),ROUND((U6*W6)/2,2),0) -> 401.99 | Y6: =IF($D$3=1,ROUND(((U6*W6)/2),2),0) -> 401.99 | Z6: =IF($D$3=2,ROUND(((U6*W6)),2),0) -> 0 | AA6: =IF($D$3=4,ROUND(((U6*W6)/2),2),0) -> 0 | AB6: 0.06 | AC6: =IF($D$3=5,ROUND(((U6*AB6)/2),2),0) -> 0 | AD6: =X6+Y6+Z6+AA6+AC6 -> 803.98 | AE6: =U6+AD6 -> 16883.68 | AF6: 120 | AG6: =U6*$N$3 -> 16079.7 | AH6: 3 | AI6: =ROUND(G6/AH6,3) -> 3.333 | AJ6: 1375.002 | AK6: 123 | AL6: =ROUND((AJ6-AI6),3) -> 1371.669 | AM6: F100 | AN6: Sales Regular | AO6: 0 | AP6: =ROUND(((AO6*U6)/100),2) -> 0 | AQ6: DOMESTIC | AR6: 20 | AS6: 3265 | AT6: =AR6*AS6 -> 65300 | AU6: 5 | AV6: 7 | AW6: 9 | AX6: =AT6 -> 65300 | AY6: =ROUND((AX6*AU6)/100,2) -> 3265 | AZ6: =AT6-AY6 -> 62035 | BA6: =ROUND((AZ6*AV6)/100,2) -> 4342.45 | BB6: =ROUND(AZ6-BA6,2) -> 57692.55 | BC6: =ROUND((BB6*AW6)/100,2) -> 5192.33 | BD6: =ROUND(AY6+BA6+BC6,2) -> 12799.78 | BE6: =ROUND(BD6/AR6,2) -> 639.99 | BF6: =(AT6-BD6) -> 52500.22 | BG6: HSN1 | BH6: 0.05 | BI6: =IF(OR($D$3=1,$D$3=4),ROUND((BF6*BH6)/2,2),0) -> 1312.51 | BJ6: =IF($D$3=1,ROUND(((BF6*BH6)/2),2),0) -> 1312.51 | BK6: =IF($D$3=2,ROUND(((BF6*BH6)),2),0) -> 0 | BL6: =IF($D$3=4,ROUND(((BF6*BH6)/2),2),0) -> 0 | BM6: 0.06 | BN6: =IF($D$3=5,ROUND(((BF6*BM6)/2),2),0) -> 0 | BO6: =BI6+BJ6+BK6+BL6+BN6 -> 2625.02 | BP6: =BF6+BO6 -> 55125.24 | BQ6: 120 | BR6: =BF6*$N$3 -> 52500.22 | BS6: Sales Regular | BT6: DOMESTIC | BU6: Modify
Q7: DISC AMOUNT | Z7: NET AMOUNT | AE7: =SUM(AE5:AE6) -> 32055.25 | AF7: SALES AMOUNT | AG7: =AG5 -> 13546.05 | BB7: DISC AMOUNT | BK7: NET AMOUNT | BP7: =SUM(BP5:BP6) -> 81088.86 | BQ7: SALES AMOUNT | BR7: =BR5 -> 23181.8

Sheet So Amend Disc Local
A1: Scenario : Local Sales - Stock UOM and Sales UOM (Similar) DOC NO : SORD-2425-00089
A2: Sales Order
A3: GST Sales | D3: 1 | E3: (1 - Local Sales,2 Interstate Sales, 3 Import Sales) | J3: Cur. | K3: INR | M3: Ex. Rate | N3: 1
A4: S. No. | B4: Item | C4: Rev | D4: Item Desc. | E4: Stk. UOM | F4: Sale. UOM | G4: Order Qty (Sale UOM) | H4: Unit Price | I4: Gross Amt. | J4: TD% | K4: SD% | L4: CD% | M4: TD Asbl. Val. | N4: TD Amt. | O4: SD Asbl. Val. | P4: SD Amt. | Q4: CD Asbl. Val. | R4: CD Amt. | S4: Disc. Amt. | T4: Disc.Amt.Per.Qty | U4: Sales Val. | V4: HSN | W4: Tax Rate | X4: CGST | Y4: SGST | Z4: IGST | AA4: UTGST | AB4: CESS % | AC4: CESS AMT | AD4: Tax amt | AE4: Net Amt | AF4: Weight/Vol | AG4: Sales Amt (BC) | AH4: Conv. Factor | AI4: Eqv. Stock Qty | AJ4: Before Stock Qty | AK4: Before Stock Cost | AL4: After Stock Qty | AM4: Warehouse | AN4: Promotional Type | AO4: CESS PCT | AP4: CESS AMT | AQ4: PriceClass | AR4: Order Qty (Sale UOM) | AS4: Unit Price | AT4: Gross Amt. | AU4: TD% | AV4: SD% | AW4: CD% | AX4: TD Asbl. Val. | AY4: TD Amt. | AZ4: SD Asbl. Val. | BA4: SD Amt. | BB4: CD Asbl. Val. | BC4: CD Amt. | BD4: Disc. Amt. | BE4: Disc.Amt.Per.Qty | BF4: Sales Val. | BG4: HSN | BH4: Tax Rate | BI4: CGST | BJ4: SGST | BK4: IGST | BL4: UTGST | BM4: CESS % | BN4: CESS AMT | BO4: Tax amt | BP4: Net Amt | BQ4: Weight/Vol | BR4: Sales Amt (BC) | BS4: Promotional Type | BT4: PriceClass | BU4: SoAmdType
A5: 1 | B5: HK-FIFO-LOT-BATCH-10001(FG) | C5: 0 | D5: HK-FIFO-LOT-BATCH-10001(FG) | E5: NOS | F5: NOS | G5: 10 | H5: 1500 | I5: =G5*H5 -> 15000 | J5: 2 | K5: 3 | L5: 5 | M5: =I5 -> 15000 | N5: =ROUND((M5*J5)/100,2) -> 300 | O5: =I5-N5 -> 14700 | P5: =ROUND((O5*K5)/100,2) -> 441 | Q5: =ROUND(O5-P5,2) -> 14259 | R5: =ROUND((Q5*L5)/100,2) -> 712.95 | S5: =ROUND(N5+P5+R5,2) -> 1453.95 | T5: =ROUND(S5/G5,2) -> 145.4 | U5: =(I5-S5) -> 13546.05 | V5: HSN1 | W5: 0.12 | X5: =IF(OR($D$3=1,$D$3=4),ROUND((U5*W5)/2,2),0) -> 812.76 | Y5: =IF($D$3=1,ROUND(((U5*W5)/2),2),0) -> 812.76 | Z5: =IF($D$3=2,ROUND(((U5*W5)),2),0) -> 0 | AA5: =IF($D$3=4,ROUND(((U5*W5)/2),2),0) -> 0 | AB5: 0.06 | AC5: =IF($D$3=5,ROUND(((U5*AB5)/2),2),0) -> 0 | AD5: =X5+Y5+Z5+AA5+AC5 -> 1625.52 | AE5: =U5+AD5 -> 15171.57 | AF5: 120 | AG5: =U5*$N$3 -> 13546.05 | AH5: 1 | AI5: =G5/AH5 -> 10 | AJ5: 848 | AK5: 235.36857 | AL5: =ROUND(AJ5-G5,0) -> 838 | AM5: F100 | AN5: Sales Regular | AO5: 0 | AP5: =ROUND(((AO5*U5)/100),2) -> 0 | AQ5: DOMESTIC | AR5: 10 | AS5: 1500 | AT5: =AR5*AS5 -> 15000 | AU5: 12 | AV5: 13 | AW5: 15 | AX5: =AT5 -> 15000 | AY5: =ROUND((AX5*AU5)/100,2) -> 1800 | AZ5: =AT5-AY5 -> 13200 | BA5: =ROUND((AZ5*AV5)/100,2) -> 1716 | BB5: =ROUND(AZ5-BA5,2) -> 11484 | BC5: =ROUND((BB5*AW5)/100,2) -> 1722.6 | BD5: =ROUND(AY5+BA5+BC5,2) -> 5238.6 | BE5: =ROUND(BD5/AR5,2) -> 523.86 | BF5: =(AT5-BD5) -> 9761.4 | BG5: HSN1 | BH5: 0.12 | BI5: =IF(OR($D$3=1,$D$3=4),ROUND((BF5*BH5)/2,2),0) -> 585.68 | BJ5: =IF($D$3=1,ROUND(((BF5*BH5)/2),2),0) -> 585.68 | BK5: =IF($D$3=2,ROUND(((BF5*BH5)),2),0) -> 0 | BL5: =IF($D$3=4,ROUND(((BF5*BH5)/2),2),0) -> 0 | BM5: 0.06 | BN5: =IF($D$3=5,ROUND(((BF5*BM5)/2),2),0) -> 0 | BO5: =BI5+BJ5+BK5+BL5+BN5 -> 1171.36 | BP5: =BF5+BO5 -> 10932.76 | BQ5: 120 | BR5: =BF5*$N$3 -> 9761.4 | BS5: Sales Regular | BT5: DOMESTIC | BU5: Modify
A6: 2 | B6: HK-FG-DISSIMILAR-10001 | C6: 0 | D6: HK-FG-DISSIMILAR-10001 | E6: KGS | F6: NOS | G6: 10 | H6: 2000 | I6: =G6*H6 -> 20000 | J6: 5 | K6: 7 | L6: 9 | M6: =I6 -> 20000 | N6: =ROUND((M6*J6)/100,2) -> 1000 | O6: =I6-N6 -> 19000 | P6: =ROUND((O6*K6)/100,2) -> 1330 | Q6: =ROUND(O6-P6,2) -> 17670 | R6: =ROUND((Q6*L6)/100,2) -> 1590.3 | S6: =ROUND(N6+P6+R6,2) -> 3920.3 | T6: =ROUND(S6/G6,2) -> 392.03 | U6: =(I6-S6) -> 16079.7 | V6: HSN1 | W6: 0.05 | X6: =IF(OR($D$3=1,$D$3=4),ROUND((U6*W6)/2,2),0) -> 401.99 | Y6: =IF($D$3=1,ROUND(((U6*W6)/2),2),0) -> 401.99 | Z6: =IF($D$3=2,ROUND(((U6*W6)),2),0) -> 0 | AA6: =IF($D$3=4,ROUND(((U6*W6)/2),2),0) -> 0 | AB6: 0.06 | AC6: =IF($D$3=5,ROUND(((U6*AB6)/2),2),0) -> 0 | AD6: =X6+Y6+Z6+AA6+AC6 -> 803.98 | AE6: =U6+AD6 -> 16883.68 | AF6: 120 | AG6: =U6*$N$3 -> 16079.7 | AH6: 3 | AI6: =ROUND(G6/AH6,3) -> 3.333 | AJ6: 1375.002 | AK6: 123 | AL6: =ROUND((AJ6-AI6),3) -> 1371.669 | AM6: F100 | AN6: Sales Regular | AO6: 0 | AP6: =ROUND(((AO6*U6)/100),2) -> 0 | AQ6: DOMESTIC | AR6: 20 | AS6: 2000 | AT6: =AR6*AS6 -> 40000 | AU6: 15 | AV6: 17 | AW6: 19 | AX6: =AT6 -> 40000 | AY6: =ROUND((AX6*AU6)/100,2) -> 6000 | AZ6: =AT6-AY6 -> 34000 | BA6: =ROUND((AZ6*AV6)/100,2) -> 5780 | BB6: =ROUND(AZ6-BA6,2) -> 28220 | BC6: =ROUND((BB6*AW6)/100,2) -> 5361.8 | BD6: =ROUND(AY6+BA6+BC6,2) -> 17141.8 | BE6: =ROUND(BD6/AR6,2) -> 857.09 | BF6: =(AT6-BD6) -> 22858.2 | BG6: HSN1 | BH6: 0.05 | BI6: =IF(OR($D$3=1,$D$3=4),ROUND((BF6*BH6)/2,2),0) -> 571.46 | BJ6: =IF($D$3=1,ROUND(((BF6*BH6)/2),2),0) -> 571.46 | BK6: =IF($D$3=2,ROUND(((BF6*BH6)),2),0) -> 0 | BL6: =IF($D$3=4,ROUND(((BF6*BH6)/2),2),0) -> 0 | BM6: 0.06 | BN6: =IF($D$3=5,ROUND(((BF6*BM6)/2),2),0) -> 0 | BO6: =BI6+BJ6+BK6+BL6+BN6 -> 1142.92 | BP6: =BF6+BO6 -> 24001.12 | BQ6: 120 | BR6: =BF6*$N$3 -> 22858.2 | BS6: Sales Regular | BT6: DOMESTIC | BU6: Modify
Q7: DISC AMOUNT | Z7: NET AMOUNT | AE7: =SUM(AE5:AE6) -> 32055.25 | AF7: SALES AMOUNT | AG7: =AG5 -> 13546.05 | BB7: DISC AMOUNT | BK7: NET AMOUNT | BP7: =SUM(BP5:BP6) -> 34933.88 | BQ7: SALES AMOUNT | BR7: =BR5 -> 9761.4

Sheet So Amend Qty Local
A1: Scenario : Local Sales - Stock UOM and Sales UOM (Similar) DOC NO : SORD-2425-00089
A2: Sales Order
A3: GST Sales | D3: 1 | E3: (1 - Local Sales,2 Interstate Sales, 3 Import Sales) | J3: Cur. | K3: INR | M3: Ex. Rate | N3: 1
A4: S. No. | B4: Item | C4: Rev | D4: Item Desc. | E4: Stk. UOM | F4: Sale. UOM | G4: Order Qty (Sale UOM) | H4: Unit Price | I4: Gross Amt. | J4: TD% | K4: SD% | L4: CD% | M4: TD Asbl. Val. | N4: TD Amt. | O4: SD Asbl. Val. | P4: SD Amt. | Q4: CD Asbl. Val. | R4: CD Amt. | S4: Disc. Amt. | T4: Disc.Amt.Per.Qty | U4: Sales Val. | V4: HSN | W4: Tax Rate | X4: CGST | Y4: SGST | Z4: IGST | AA4: UTGST | AB4: CESS % | AC4: CESS AMT | AD4: Tax amt | AE4: Net Amt | AF4: Weight/Vol | AG4: Sales Amt (BC) | AH4: Conv. Factor | AI4: Eqv. Stock Qty | AJ4: Before Stock Qty | AK4: Before Stock Cost | AL4: After Stock Qty | AM4: Warehouse | AN4: Promotional Type | AO4: CESS PCT | AP4: CESS AMT | AQ4: PriceClass | AR4: Order Qty (Sale UOM) | AS4: Unit Price | AT4: Gross Amt. | AU4: TD% | AV4: SD% | AW4: CD% | AX4: TD Asbl. Val. | AY4: TD Amt. | AZ4: SD Asbl. Val. | BA4: SD Amt. | BB4: CD Asbl. Val. | BC4: CD Amt. | BD4: Disc. Amt. | BE4: Disc.Amt.Per.Qty | BF4: Sales Val. | BG4: HSN | BH4: Tax Rate | BI4: CGST | BJ4: SGST | BK4: IGST | BL4: UTGST | BM4: CESS % | BN4: CESS AMT | BO4: Tax amt | BP4: Net Amt | BQ4: Weight/Vol | BR4: Sales Amt (BC) | BS4: Promotional Type | BT4: PriceClass | BU4: SoAmdType
A5: 1 | B5: HK-FIFO-LOT-BATCH-10001(FG) | C5: 0 | D5: HK-FIFO-LOT-BATCH-10001(FG) | E5: NOS | F5: NOS | G5: 10 | H5: 1500 | I5: =G5*H5 -> 15000 | J5: 2 | K5: 3 | L5: 5 | M5: =I5 -> 15000 | N5: =ROUND((M5*J5)/100,2) -> 300 | O5: =I5-N5 -> 14700 | P5: =ROUND((O5*K5)/100,2) -> 441 | Q5: =ROUND(O5-P5,2) -> 14259 | R5: =ROUND((Q5*L5)/100,2) -> 712.95 | S5: =ROUND(N5+P5+R5,2) -> 1453.95 | T5: =ROUND(S5/G5,2) -> 145.4 | U5: =(I5-S5) -> 13546.05 | V5: HSN1 | W5: 0.12 | X5: =IF(OR($D$3=1,$D$3=4),ROUND((U5*W5)/2,2),0) -> 812.76 | Y5: =IF($D$3=1,ROUND(((U5*W5)/2),2),0) -> 812.76 | Z5: =IF($D$3=2,ROUND(((U5*W5)),2),0) -> 0 | AA5: =IF($D$3=4,ROUND(((U5*W5)/2),2),0) -> 0 | AB5: 0.06 | AC5: =IF($D$3=5,ROUND(((U5*AB5)/2),2),0) -> 0 | AD5: =X5+Y5+Z5+AA5+AC5 -> 1625.52 | AE5: =U5+AD5 -> 15171.57 | AF5: 120 | AG5: =U5*$N$3 -> 13546.05 | AH5: 1 | AI5: =G5/AH5 -> 10 | AJ5: 848 | AK5: 235.36857 | AL5: =ROUND(AJ5-G5,0) -> 838 | AM5: F100 | AN5: Sales Regular | AO5: 0 | AP5: =ROUND(((AO5*U5)/100),2) -> 0 | AQ5: DOMESTIC | AR5: 20 | AS5: 1500 | AT5: =AR5*AS5 -> 30000 | AU5: 2 | AV5: 3 | AW5: 5 | AX5: =AT5 -> 30000 | AY5: =ROUND((AX5*AU5)/100,2) -> 600 | AZ5: =AT5-AY5 -> 29400 | BA5: =ROUND((AZ5*AV5)/100,2) -> 882 | BB5: =ROUND(AZ5-BA5,2) -> 28518 | BC5: =ROUND((BB5*AW5)/100,2) -> 1425.9 | BD5: =ROUND(AY5+BA5+BC5,2) -> 2907.9 | BE5: =ROUND(BD5/AR5,2) -> 145.4 | BF5: =(AT5-BD5) -> 27092.1 | BG5: HSN1 | BH5: 0.12 | BI5: =IF(OR($D$3=1,$D$3=4),ROUND((BF5*BH5)/2,2),0) -> 1625.53 | BJ5: =IF($D$3=1,ROUND(((BF5*BH5)/2),2),0) -> 1625.53 | BK5: =IF($D$3=2,ROUND(((BF5*BH5)),2),0) -> 0 | BL5: =IF($D$3=4,ROUND(((BF5*BH5)/2),2),0) -> 0 | BM5: 0.06 | BN5: =IF($D$3=5,ROUND(((BF5*BM5)/2),2),0) -> 0 | BO5: =BI5+BJ5+BK5+BL5+BN5 -> 3251.06 | BP5: =BF5+BO5 -> 30343.16 | BQ5: 120 | BR5: =BF5*$N$3 -> 27092.1 | BS5: Sales Regular | BT5: DOMESTIC | BU5: Modify
A6: 2 | B6: HK-FG-DISSIMILAR-10001 | C6: 0 | D6: HK-FG-DISSIMILAR-10001 | E6: KGS | F6: NOS | G6: 10 | H6: 2000 | I6: =G6*H6 -> 20000 | J6: 5 | K6: 7 | L6: 9 | M6: =I6 -> 20000 | N6: =ROUND((M6*J6)/100,2) -> 1000 | O6: =I6-N6 -> 19000 | P6: =ROUND((O6*K6)/100,2) -> 1330 | Q6: =ROUND(O6-P6,2) -> 17670 | R6: =ROUND((Q6*L6)/100,2) -> 1590.3 | S6: =ROUND(N6+P6+R6,2) -> 3920.3 | T6: =ROUND(S6/G6,2) -> 392.03 | U6: =(I6-S6) -> 16079.7 | V6: HSN1 | W6: 0.05 | X6: =IF(OR($D$3=1,$D$3=4),ROUND((U6*W6)/2,2),0) -> 401.99 | Y6: =IF($D$3=1,ROUND(((U6*W6)/2),2),0) -> 401.99 | Z6: =IF($D$3=2,ROUND(((U6*W6)),2),0) -> 0 | AA6: =IF($D$3=4,ROUND(((U6*W6)/2),2),0) -> 0 | AB6: 0.06 | AC6: =IF($D$3=5,ROUND(((U6*AB6)/2),2),0) -> 0 | AD6: =X6+Y6+Z6+AA6+AC6 -> 803.98 | AE6: =U6+AD6 -> 16883.68 | AF6: 120 | AG6: =U6*$N$3 -> 16079.7 | AH6: 3 | AI6: =ROUND(G6/AH6,3) -> 3.333 | AJ6: 1375.002 | AK6: 123 | AL6: =ROUND((AJ6-AI6),3) -> 1371.669 | AM6: F100 | AN6: Sales Regular | AO6: 0 | AP6: =ROUND(((AO6*U6)/100),2) -> 0 | AQ6: DOMESTIC | AR6: 30 | AS6: 2000 | AT6: =AR6*AS6 -> 60000 | AU6: 5 | AV6: 7 | AW6: 9 | AX6: =AT6 -> 60000 | AY6: =ROUND((AX6*AU6)/100,2) -> 3000 | AZ6: =AT6-AY6 -> 57000 | BA6: =ROUND((AZ6*AV6)/100,2) -> 3990 | BB6: =ROUND(AZ6-BA6,2) -> 53010 | BC6: =ROUND((BB6*AW6)/100,2) -> 4770.9 | BD6: =ROUND(AY6+BA6+BC6,2) -> 11760.9 | BE6: =ROUND(BD6/AR6,2) -> 392.03 | BF6: =(AT6-BD6) -> 48239.1 | BG6: HSN1 | BH6: 0.05 | BI6: =IF(OR($D$3=1,$D$3=4),ROUND((BF6*BH6)/2,2),0) -> 1205.98 | BJ6: =IF($D$3=1,ROUND(((BF6*BH6)/2),2),0) -> 1205.98 | BK6: =IF($D$3=2,ROUND(((BF6*BH6)),2),0) -> 0 | BL6: =IF($D$3=4,ROUND(((BF6*BH6)/2),2),0) -> 0 | BM6: 0.06 | BN6: =IF($D$3=5,ROUND(((BF6*BM6)/2),2),0) -> 0 | BO6: =BI6+BJ6+BK6+BL6+BN6 -> 2411.96 | BP6: =BF6+BO6 -> 50651.06 | BQ6: 120 | BR6: =BF6*$N$3 -> 48239.1 | BS6: Sales Regular | BT6: DOMESTIC | BU6: Modify
Q7: DISC AMOUNT | Z7: NET AMOUNT | AE7: =SUM(AE5:AE6) -> 32055.25 | AF7: SALES AMOUNT | AG7: =AG5 -> 13546.05 | BB7: DISC AMOUNT | BK7: NET AMOUNT | BP7: =SUM(BP5:BP6) -> 80994.22 | BQ7: SALES AMOUNT | BR7: =BR5 -> 27092.1

Sheet SO
A1: Scenario : Local Sales - Stock UOM and Sales UOM (Similar) DOC NO : SORD-2425-00089
A2: Sales Order
A3: GST Sales | D3: 2 | E3: (1 - Local Sales,2 Interstate Sales, 3 Export Sales) | J3: Cur. | K3: INR | M3: Ex. Rate | N3: 1
A4: S. No. | B4: Item | C4: Rev | D4: Item Desc. | E4: Stk. UOM | F4: Sale. UOM | G4: Order Qty (Sale UOM) | H4: Unit Price | I4: Gross Amt. | J4: TD% | K4: SD% | L4: CD% | M4: TD Asbl. Val. | N4: TD Amt. | O4: SD Asbl. Val. | P4: SD Amt. | Q4: CD Asbl. Val. | R4: CD Amt. | S4: Disc. Amt. | T4: Disc.Amt.Per.Qty | U4: Sales Val. | V4: HSN | W4: Tax Rate | X4: CGST | Y4: SGST | Z4: IGST | AA4: UTGST | AB4: CESS % | AC4: CESS AMT | AD4: Tax amt | AE4: Net Amt | AF4: Weight/Vol | AG4: Sales Amt (BC) | AH4: Conv. Factor | AI4: Eqv. Stock Qty | AJ4: Before Stock Qty | AK4: Before Stock Cost | AL4: After Stock Qty | AM4: Warehouse | AN4: Promotional Type | AO4: CESS PCT | AP4: CESS AMT | AQ4: PriceClass
A5: 1 | B5: HK-FIFO-LOT-BATCH-10001(FG) | C5: 0 | D5: HK-FIFO-LOT-BATCH-10001(FG) | E5: NOS | F5: NOS | G5: 10 | H5: 1234 | I5: =G5*H5 -> 12340 | J5: 1 | K5: 2 | L5: 4 | M5: =I5 -> 12340 | N5: =ROUND((M5*J5)/100,2) -> 123.4 | O5: =I5-N5 -> 12216.6 | P5: =ROUND((O5*K5)/100,2) -> 244.33 | Q5: =ROUND(O5-P5,2) -> 11972.27 | R5: =ROUND((Q5*L5)/100,2) -> 478.89 | S5: =N5+P5+R5 -> 846.62 | T5: =ROUND(S5/G5,2) -> 84.66 | U5: =(I5-S5) -> 11493.38 | V5: (740410)-18% | W5: 0.12 | X5: =IF(OR($D$3=1,$D$3=4),ROUND((U5*W5)/2,2),0) -> 0 | Y5: =IF($D$3=1,ROUND(((U5*W5)/2),2),0) -> 0 | Z5: =IF($D$3=2,ROUND(((U5*W5)),2),0) -> 1379.21 | AA5: =IF($D$3=4,ROUND(((U5*W5)/2),2),0) -> 0 | AB5: 0.06 | AC5: =IF($D$3=5,ROUND(((U5*AB5)/2),2),0) -> 0 | AD5: =X5+Y5+Z5+AA5+AC5 -> 1379.21 | AE5: =U5+AD5 -> 12872.59 | AF5: 120 | AG5: =U5*$N$3 -> 11493.38 | AH5: 1 | AI5: =G5/AH5 -> 10 | AJ5: 848 | AK5: 235.36857 | AL5: =ROUND(AJ5-G5,0) -> 838 | AM5: F100 | AN5: Sales Regular | AO5: 0 | AP5: =ROUND(((AO5*U5)/100),2) -> 0 | AQ5: DOMESTIC
A6: 2 | B6: HK-FG-DISSIMILAR-10001 | C6: 0 | D6: HK-FG-DISSIMILAR-10001 | E6: KGS | F6: NOS | G6: 20 | H6: 3214 | I6: =G6*H6 -> 64280 | J6: 2 | K6: 7 | L6: 9 | M6: =I6 -> 64280 | N6: =ROUND((M6*J6)/100,2) -> 1285.6 | O6: =I6-N6 -> 62994.4 | P6: =ROUND((O6*K6)/100,2) -> 4409.61 | Q6: =ROUND(O6-P6,2) -> 58584.79 | R6: =ROUND((Q6*L6)/100,2) -> 5272.63 | S6: =N6+P6+R6 -> 10967.84 | T6: =ROUND(S6/G6,2) -> 548.39 | U6: =(I6-S6) -> 53312.16 | V6: 772213 | W6: 0.05 | X6: =IF(OR($D$3=1,$D$3=4),ROUND((U6*W6)/2,2),0) -> 0 | Y6: =IF($D$3=1,ROUND(((U6*W6)/2),2),0) -> 0 | Z6: =IF($D$3=2,ROUND(((U6*W6)),2),0) -> 2665.61 | AA6: =IF($D$3=4,ROUND(((U6*W6)/2),2),0) -> 0 | AB6: 0.06 | AC6: =IF($D$3=5,ROUND(((U6*AB6)/2),2),0) -> 0 | AD6: =X6+Y6+Z6+AA6+AC6 -> 2665.61 | AE6: =U6+AD6 -> 55977.77 | AF6: 120 | AG6: =U6*$N$3 -> 53312.16 | AH6: 3 | AI6: =ROUND(G6/AH6,3) -> 6.667 | AJ6: 1375.002 | AK6: 123 | AL6: =ROUND((AJ6-AI6),3) -> 1368.335 | AM6: F100 | AN6: Sales Regular | AO6: 0 | AP6: =ROUND(((AO6*U6)/100),2) -> 0 | AQ6: DOMESTIC
Q7: DISC AMOUNT | S7: =SUM(S5:S6) -> 11814.46 | Z7: NET AMOUNT | AE7: =SUM(AE5:AE6) -> 68850.36 | AF7: SALES AMOUNT | AG7: =AG5 -> 11493.38

Sheet SoAmendment PriceChange
A1: Scenario : Local Sales - Stock UOM and Sales UOM (Similar) DOC NO : SORD-2425-00089
A2: Sales Order Amendment
A3: GST Sales | D3: =SO!D3 -> 2 | E3: (1 - Local Sales,2 Interstate Sales, 3 Export Sales) | J3: Cur. | K3: INR | M3: Ex. Rate | N3: 1
A4: S. No. | B4: Item | C4: Rev | D4: Item Desc. | E4: Stk. UOM | F4: Sale. UOM | G4: Old Order Qty (Sale UOM) | H4: Old Unit Price | I4: Old Gross Amt. | J4: Old TD% | K4: Old SD% | L4: Old CD% | M4: Old TD Asbl. Val. | N4: Old TD Amt. | O4: Old SD Asbl. Val. | P4: Old SD Amt. | Q4: Old CD Asbl. Val. | R4: Old CD Amt. | S4: Old Disc. Amt. | T4: Old Disc.Amt.Per.Qty | U4: Old Sales Val. | V4: Old HSN | W4: Old Tax Rate | X4: Old CGST | Y4: Old SGST | Z4: Old IGST | AA4: Old Tax amt | AB4: Old Net Amt | AC4: Weight/Vol | AD4: Old Sales Amt (BC) | AE4: Conv. Factor | AF4: Eqv. Stock Qty | AG4: Before Stock Qty | AH4: Before Stock Cost | AI4: After Stock Qty | AJ4: Warehouse | AK4: Promotional Type | AL4: CESS PCT | AM4: CESS AMT | AN4: Old PriceClass | AO4: New Order Qty (Sale UOM) | AP4: New Unit Price | AQ4: New Gross Amt. | AR4: New TD% | AS4: New SD% | AT4: New CD% | AU4: New TD Asbl. Val. | AV4: New TD Amt. | AW4: New SD Asbl. Val. | AX4: New SD Amt. | AY4: New CD Asbl. Val. | AZ4: New CD Amt. | BA4: New Disc. Amt. | BB4: New Disc.Amt.Per.Qty | BC4: New Sales Val. | BD4: New HSN | BE4: New Tax Rate | BF4: New CGST | BG4: New SGST | BH4: New IGST | BI4: New Tax amt | BJ4: New Net Amt | BK4: Weight/Vol | BL4: New Sales Amt (BC) | BM4: New PriceClass | BN4: SoAmdType
A5: 1 | B5: HK-FIFO-LOT-BATCH-10001(FG) | C5: 0 | D5: HK-FIFO-LOT-BATCH-10001(FG) | E5: NOS | F5: NOS | G5: =SO!G5 -> 10 | H5: =SO!H5 -> 1234 | I5: =SO!I5 -> 12340 | J5: =SO!J5 -> 1 | K5: =SO!K5 -> 2 | L5: =SO!L5 -> 4 | M5: =SO!M5 -> 12340 | N5: =SO!N5 -> 123.4 | ... AB5: =SO!AB5 -> 0.06 | AC5: 120 | AD5: =SO!AD5 -> 1379.21 | AE5: 1 | AF5: =G5/AE5 -> 10 | AG5: 848 | AH5: 235.36857 | AI5: =ROUND(AG5-G5,0) -> 838 | AJ5: F100 | AK5: =SO!AK5 -> 235.36857 | AL5: 0 | AM5: =ROUND(((AL5*U5)/100),2) -> 0 | AN5: =SO!AN5 -> Sales Regular | AO5: =G5 -> 10 | AP5: 2350 | AQ5: =AO5*AP5 -> 23500 | AR5: =J5 -> 1 | AS5: =K5 -> 2 | AT5: =L5 -> 4 | AU5: =AQ5 -> 23500 | AV5: =ROUND((AU5*AR5)/100,2) -> 235 | AW5: =AQ5-AV5 -> 23265 | AX5: =ROUND((AW5*AS5)/100,2) -> 465.3 | AY5: =ROUND(AW5-AX5,2) -> 22799.7 | AZ5: =ROUND((AY5*AT5)/100,2) -> 911.99 | BA5: =AV5+AX5+AZ5 -> 1612.29 | BB5: =ROUND(BA5/AO5,2) -> 161.23 | BC5: =(AQ5-BA5) -> 21887.71 | BD5: =V5 -> (740410)-18% | BE5: 0.12 | BF5: =IF(SO!$D$3=1,ROUND(((BC5*BE5)/2),2),0) -> 0 | BG5: =IF(SO!$D$3=1,ROUND(((BC5*BE5)/2),2),0) -> 0 | BH5: =IF(SO!$D$3=2,ROUND(((BC5*BE5)),2),0) -> 2626.53 | BI5: =BF5+BG5+BH5 -> 2626.53 | BJ5: =BC5+BI5 -> 24514.24 | BK5: 120 | BL5: =BC5*SO!$N$3 -> 21887.71 | BM5: Spare | BN5: Modify
A6: 2 | B6: HK-FG-DISSIMILAR-10001 | C6: 0 | D6: HK-FG-DISSIMILAR-10001 | E6: KGS | F6: NOS | G6: =SO!G6 -> 20 | H6: =SO!H6 -> 3214 | I6: =SO!I6 -> 64280 | J6: =SO!J6 -> 2 | K6: =SO!K6 -> 7 | L6: =SO!L6 -> 9 | M6: =SO!M6 -> 64280 | N6: =SO!N6 -> 1285.6 | ... AB6: =SO!AB6 -> 0.06 | AC6: 120 | AD6: =SO!AD6 -> 2665.61 | AE6: 3 | AF6: =ROUND(G6/AE6,3) -> 6.667 | AG6: 1375.002 | AH6: 123 | AI6: =ROUND((AG6-AF6),3) -> 1368.335 | AJ6: F100 | AK6: =SO!AK6 -> 123 | AL6: 0 | AM6: =ROUND(((AL6*U6)/100),2) -> 0 | AN6: =SO!AN6 -> Sales Regular | AO6: =G6 -> 20 | AP6: 4550 | AQ6: =AO6*AP6 -> 91000 | AR6: =J6 -> 2 | AS6: =K6 -> 7 | AT6: =L6 -> 9 | AU6: =AQ6 -> 91000 | AV6: =ROUND((AU6*AR6)/100,2) -> 1820 | AW6: =AQ6-AV6 -> 89180 | AX6: =ROUND((AW6*AS6)/100,2) -> 6242.6 | AY6: =ROUND(AW6-AX6,2) -> 82937.4 | AZ6: =ROUND((AY6*AT6)/100,2) -> 7464.37 | BA6: =AV6+AX6+AZ6 -> 15526.97 | BB6: =ROUND(BA6/AO6,2) -> 776.35 | BC6: =(AQ6-BA6) -> 75473.03 | BD6: =V6 -> 772213 | BE6: 0.05 | BF6: =IF(SO!$D$3=1,ROUND(((BC6*BE6)/2),2),0) -> 0 | BG6: =IF(SO!$D$3=1,ROUND(((BC6*BE6)/2),2),0) -> 0 | BH6: =IF(SO!$D$3=2,ROUND(((BC6*BE6)),2),0) -> 3773.65 | BI6: =BF6+BG6+BH6 -> 3773.65 | BJ6: =BC6+BI6 -> 79246.68 | BK6: 120 | BL6: =BC6*SO!$N$3 -> 75473.03 | BM6: Spare | BN6: Modify
Q7: DISC AMOUNT | S7: =SUM(S5:S6) -> 11814.46 | Z7: NET AMOUNT | AB7: =SUM(AB5:AB6) -> 0.12 | AC7: SALES AMOUNT | AD7: =SUM(AD5:AD6) -> 4044.82 | AY7: DISC AMOUNT | BA7: =SUM(BA5:BA6) -> 17139.26 | BH7: NET AMOUNT | BJ7: =SUM(BJ5:BJ6) -> 103760.92 | BK7: SALES AMOUNT | BL7: =SUM(BL5:BL6) -> 97360.74

Sheet SO Amendment DiscountChange
A1: Scenario : Local Sales - Stock UOM and Sales UOM (Similar) DOC NO : SORD-2425-00089
A2: Sales Order Amendment
A3: GST Sales | D3: =SO!D3 -> 2 | E3: (1 - Local Sales,2 Interstate Sales, 3 Export Sales) | J3: Cur. | K3: INR | M3: Ex. Rate | N3: 1
A4: S. No. | B4: Item | C4: Rev | D4: Item Desc. | E4: Stk. UOM | F4: Sale. UOM | G4: Old Order Qty (Sale UOM) | H4: Old Unit Price | I4: Old Gross Amt. | J4: Old TD% | K4: Old SD% | L4: Old CD% | M4: Old TD Asbl. Val. | N4: Old TD Amt. | O4: Old SD Asbl. Val. | P4: Old SD Amt. | Q4: Old CD Asbl. Val. | R4: Old CD Amt. | S4: Old Disc. Amt. | T4: Old Disc.Amt.Per.Qty | U4: Old Sales Val. | V4: Old HSN | W4: Old Tax Rate | X4: Old CGST | Y4: Old SGST | Z4: Old IGST | AA4: Old Tax amt | AB4: Old Net Amt | AC4: Weight/Vol | AD4: Old Sales Amt (BC) | AE4: Conv. Factor | AF4: Eqv. Stock Qty | AG4: Before Stock Qty | AH4: Before Stock Cost | AI4: After Stock Qty | AJ4: Warehouse | AK4: Promotional Type | AL4: CESS PCT | AM4: CESS AMT | AN4: Old PriceClass | AO4: New Order Qty (Sale UOM) | AP4: New Unit Price | AQ4: New Gross Amt. | AR4: New TD% | AS4: New SD% | AT4: New CD% | AU4: New TD Asbl. Val. | AV4: New TD Amt. | AW4: New SD Asbl. Val. | AX4: New SD Amt. | AY4: New CD Asbl. Val. | AZ4: New CD Amt. | BA4: New Disc. Amt. | BB4: New Disc.Amt.Per.Qty | BC4: New Sales Val. | BD4: New HSN | BE4: New Tax Rate | BF4: New CGST | BG4: New SGST | BH4: New IGST | BI4: New Tax amt | BJ4: New Net Amt | BK4: Weight/Vol | BL4: New Sales Amt (BC) | BM4: New PriceClass | BN4: SoAmdType
A5: 1 | B5: HK-FIFO-LOT-BATCH-10001(FG) | C5: 0 | D5: HK-FIFO-LOT-BATCH-10001(FG) | E5: NOS | F5: NOS | G5: =SO!G5 -> 10 | H5: =SO!H5 -> 1234 | I5: =SO!I5 -> 12340 | J5: =SO!J5 -> 1 | K5: =SO!K5 -> 2 | L5: =SO!L5 -> 4 | M5: =SO!M5 -> 12340 | N5: =SO!N5 -> 123.4 | ... AB5: =SO!AB5 -> 0.06 | AC5: 120 | AD5: =SO!AD5 -> 1379.21 | AE5: 1 | AF5: =G5/AE5 -> 10 | AG5: 848 | AH5: 235.36857 | AI5: =ROUND(AG5-G5,0) -> 838 | AJ5: F100 | AK5: =SO!AK5 -> 235.36857 | AL5: 0 | AM5: =ROUND(((AL5*U5)/100),2) -> 0 | AN5: =SO!AN5 -> Sales Regular | AO5: =G5 -> 10 | AP5: =H5 -> 1234 | AQ5: =AO5*AP5 -> 12340 | AR5: 10 | AS5: 5 | AT5: 2 | AU5: =AQ5 -> 12340 | AV5: =ROUND((AU5*AR5)/100,2) -> 1234 | AW5: =AQ5-AV5 -> 11106 | AX5: =ROUND((AW5*AS5)/100,2) -> 555.3 | AY5: =ROUND(AW5-AX5,2) -> 10550.7 | AZ5: =ROUND((AY5*AT5)/100,2) -> 211.01 | BA5: =AV5+AX5+AZ5 -> 2000.31 | BB5: =ROUND(BA5/AO5,2) -> 200.03 | BC5: =(AQ5-BA5) -> 10339.69 | BD5: =V5 -> (740410)-18% | BE5: 0.12 | BF5: =IF(SO!$D$3=1,ROUND(((BC5*BE5)/2),2),0) -> 0 | BG5: =IF(SO!$D$3=1,ROUND(((BC5*BE5)/2),2),0) -> 0 | BH5: =IF(SO!$D$3=2,ROUND(((BC5*BE5)),2),0) -> 1240.76 | BI5: =BF5+BG5+BH5 -> 1240.76 | BJ5: =BC5+BI5 -> 11580.45 | BK5: 120 | BL5: =BC5*SO!$N$3 -> 10339.69 | BM5: Spare | BN5: Modify
A6: 2 | B6: HK-FG-DISSIMILAR-10001 | C6: 0 | D6: HK-FG-DISSIMILAR-10001 | E6: KGS | F6: NOS | G6: =SO!G6 -> 20 | H6: =SO!H6 -> 3214 | I6: =SO!I6 -> 64280 | J6: =SO!J6 -> 2 | K6: =SO!K6 -> 7 | L6: =SO!L6 -> 9 | M6: =SO!M6 -> 64280 | N6: =SO!N6 -> 1285.6 | ... AB6: =SO!AB6 -> 0.06 | AC6: 120 | AD6: =SO!AD6 -> 2665.61 | AE6: 3 | AF6: =ROUND(G6/AE6,3) -> 6.667 | AG6: 1375.002 | AH6: 123 | AI6: =ROUND((AG6-AF6),3) -> 1368.335 | AJ6: F100 | AK6: =SO!AK6 -> 123 | AL6: 0 | AM6: =ROUND(((AL6*U6)/100),2) -> 0 | AN6: =SO!AN6 -> Sales Regular | AO6: =G6 -> 20 | AP6: =H6 -> 3214 | AQ6: =AO6*AP6 -> 64280 | AR6: 20 | AS6: 10 | AT6: 5 | AU6: =AQ6 -> 64280 | AV6: =ROUND((AU6*AR6)/100,2) -> 12856 | AW6: =AQ6-AV6 -> 51424 | AX6: =ROUND((AW6*AS6)/100,2) -> 5142.4 | AY6: =ROUND(AW6-AX6,2) -> 46281.6 | AZ6: =ROUND((AY6*AT6)/100,2) -> 2314.08 | BA6: =AV6+AX6+AZ6 -> 20312.48 | BB6: =ROUND(BA6/AO6,2) -> 1015.62 | BC6: =(AQ6-BA6) -> 43967.52 | BD6: =V6 -> 772213 | BE6: 0.05 | BF6: =IF(SO!$D$3=1,ROUND(((BC6*BE6)/2),2),0) -> 0 | BG6: =IF(SO!$D$3=1,ROUND(((BC6*BE6)/2),2),0) -> 0 | BH6: =IF(SO!$D$3=2,ROUND(((BC6*BE6)),2),0) -> 2198.38 | BI6: =BF6+BG6+BH6 -> 2198.38 | BJ6: =BC6+BI6 -> 46165.9 | BK6: 120 | BL6: =BC6*SO!$N$3 -> 43967.52 | BM6: Spare | BN6: Modify
Q7: DISC AMOUNT | S7: =SUM(S5:S6) -> 11814.46 | Z7: NET AMOUNT | AB7: =SUM(AB5:AB6) -> 0.12 | AC7: SALES AMOUNT | AD7: =SUM(AD5:AD6) -> 4044.82 | AY7: DISC AMOUNT | BA7: =SUM(BA5:BA6) -> 22312.79 | BH7: NET AMOUNT | BJ7: =SUM(BJ5:BJ6) -> 57746.35 | BK7: SALES AMOUNT | BL7: =SUM(BL5:BL6) -> 54307.21

Sheet SO Amendment Different PC
A1: Scenario : Local Sales - Stock UOM and Sales UOM (Similar) DOC NO : SORD-2425-00089
A2: Sales Order Amendment
A3: GST Sales | D3: =SO!D3 -> 2 | E3: (1 - Local Sales,2 Interstate Sales, 3 Export Sales) | J3: Cur. | K3: INR | M3: Ex. Rate | N3: 1
A4: S. No. | B4: Item | C4: Rev | D4: Item Desc. | E4: Stk. UOM | F4: Sale. UOM | G4: Old Order Qty (Sale UOM) | H4: Old Unit Price | I4: Old Gross Amt. | J4: Old TD% | K4: Old SD% | L4: Old CD% | M4: Old TD Asbl. Val. | N4: Old TD Amt. | O4: Old SD Asbl. Val. | P4: Old SD Amt. | Q4: Old CD Asbl. Val. | R4: Old CD Amt. | S4: Old Disc. Amt. | T4: Old Disc.Amt.Per.Qty | U4: Old Sales Val. | V4: Old HSN | W4: Old Tax Rate | X4: Old CGST | Y4: Old SGST | Z4: Old IGST | AA4: Old Tax amt | AB4: Old Net Amt | AC4: Weight/Vol | AD4: Old Sales Amt (BC) | AE4: Conv. Factor | AF4: Eqv. Stock Qty | AG4: Before Stock Qty | AH4: Before Stock Cost | AI4: After Stock Qty | AJ4: Warehouse | AK4: Promotional Type | AL4: CESS PCT | AM4: CESS AMT | AN4: Old PriceClass | AO4: New Order Qty (Sale UOM) | AP4: New Unit Price | AQ4: New Gross Amt. | AR4: New TD% | AS4: New SD% | AT4: New CD% | AU4: New TD Asbl. Val. | AV4: New TD Amt. | AW4: New SD Asbl. Val. | AX4: New SD Amt. | AY4: New CD Asbl. Val. | AZ4: New CD Amt. | BA4: New Disc. Amt. | BB4: New Disc.Amt.Per.Qty | BC4: New Sales Val. | BD4: New HSN | BE4: New Tax Rate | BF4: New CGST | BG4: New SGST | BH4: New IGST | BI4: New Tax amt | BJ4: New Net Amt | BK4: Weight/Vol | BL4: New Sales Amt (BC) | BM4: New PriceClass | BN4: SoAmdType
A5: 1 | B5: HK-FIFO-LOT-BATCH-10001(FG) | C5: 0 | D5: HK-FIFO-LOT-BATCH-10001(FG) | E5: NOS | F5: NOS | G5: =SO!G5 -> 10 | H5: =SO!H5 -> 1234 | I5: =SO!I5 -> 12340 | J5: =SO!J5 -> 1 | K5: =SO!K5 -> 2 | L5: =SO!L5 -> 4 | M5: =SO!M5 -> 12340 | N5: =SO!N5 -> 123.4 | ... AB5: =SO!AB5 -> 0.06 | AC5: 120 | AD5: =SO!AD5 -> 1379.21 | AE5: 1 | AF5: =G5/AE5 -> 10 | AG5: 848 | AH5: 235.36857 | AI5: =ROUND(AG5-G5,0) -> 838 | AJ5: F100 | AK5: =SO!AK5 -> 235.36857 | AL5: 0 | AM5: =ROUND(((AL5*U5)/100),2) -> 0 | AN5: =SO!AN5 -> Sales Regular | AO5: 20 | AP5: 2350 | AQ5: =AO5*AP5 -> 47000 | AR5: 10 | AS5: 5 | AT5: 2 | AU5: =AQ5 -> 47000 | AV5: =ROUND((AU5*AR5)/100,2) -> 4700 | AW5: =AQ5-AV5 -> 42300 | AX5: =ROUND((AW5*AS5)/100,2) -> 2115 | AY5: =ROUND(AW5-AX5,2) -> 40185 | AZ5: =ROUND((AY5*AT5)/100,2) -> 803.7 | BA5: =AV5+AX5+AZ5 -> 7618.7 | BB5: =ROUND(BA5/AO5,2) -> 380.94 | BC5: =(AQ5-BA5) -> 39381.3 | BD5: HSN1 | BE5: 0.12 | BF5: =IF(SO!$D$3=1,ROUND(((BC5*BE5)/2),2),0) -> 0 | BG5: =IF(SO!$D$3=1,ROUND(((BC5*BE5)/2),2),0) -> 0 | BH5: =IF(SO!$D$3=2,ROUND(((BC5*BE5)),2),0) -> 4725.76 | BI5: =BF5+BG5+BH5 -> 4725.76 | BJ5: =BC5+BI5 -> 44107.06 | BK5: 120 | BL5: =BC5*SO!$N$3 -> 39381.3 | BM5: Spare | BN5: Modify
A6: 2 | B6: HK-FG-DISSIMILAR-10001 | C6: 0 | D6: HK-FG-DISSIMILAR-10001 | E6: KGS | F6: NOS | G6: =SO!G6 -> 20 | H6: =SO!H6 -> 3214 | I6: =SO!I6 -> 64280 | J6: =SO!J6 -> 2 | K6: =SO!K6 -> 7 | L6: =SO!L6 -> 9 | M6: =SO!M6 -> 64280 | N6: =SO!N6 -> 1285.6 | ... AB6: =SO!AB6 -> 0.06 | AC6: 120 | AD6: =SO!AD6 -> 2665.61 | AE6: 3 | AF6: =ROUND(G6/AE6,3) -> 6.667 | AG6: 1375.002 | AH6: 123 | AI6: =ROUND((AG6-AF6),3) -> 1368.335 | AJ6: F100 | AK6: =SO!AK6 -> 123 | AL6: 0 | AM6: =ROUND(((AL6*U6)/100),2) -> 0 | AN6: =SO!AN6 -> Sales Regular | AO6: 30 | AP6: 4550 | AQ6: =AO6*AP6 -> 136500 | AR6: 20 | AS6: 10 | AT6: 5 | AU6: =AQ6 -> 136500 | AV6: =ROUND((AU6*AR6)/100,2) -> 27300 | AW6: =AQ6-AV6 -> 109200 | AX6: =ROUND((AW6*AS6)/100,2) -> 10920 | AY6: =ROUND(AW6-AX6,2) -> 98280 | AZ6: =ROUND((AY6*AT6)/100,2) -> 4914 | BA6: =AV6+AX6+AZ6 -> 43134 | BB6: =ROUND(BA6/AO6,2) -> 1437.8 | BC6: =(AQ6-BA6) -> 93366 | BD6: HSN1 | BE6: 0.05 | BF6: =IF(SO!$D$3=1,ROUND(((BC6*BE6)/2),2),0) -> 0 | BG6: =IF(SO!$D$3=1,ROUND(((BC6*BE6)/2),2),0) -> 0 | BH6: =IF(SO!$D$3=2,ROUND(((BC6*BE6)),2),0) -> 4668.3 | BI6: =BF6+BG6+BH6 -> 4668.3 | BJ6: =BC6+BI6 -> 98034.3 | BK6: 120 | BL6: =BC6*SO!$N$3 -> 93366 | BM6: Spare | BN6: Modify
Q7: DISC AMOUNT | S7: =SUM(S5:S6) -> 11814.46 | Z7: NET AMOUNT | AB7: =SUM(AB5:AB6) -> 0.12 | AC7: SALES AMOUNT | AD7: =SUM(AD5:AD6) -> 4044.82 | AY7: DISC AMOUNT | BA7: =SUM(BA5:BA6) -> 50752.7 | BH7: NET AMOUNT | BJ7: =SUM(BJ5:BJ6) -> 142141.36 | BK7: SALES AMOUNT | BL7: =SUM(BL5:BL6) -> 132747.3

Sheet SO Amendment AdditionOfItem
A1: Scenario : Local Sales - Stock UOM and Sales UOM (Similar) DOC NO : SORD-2425-00089
A2: Sales Order Amendment
A3: GST Sales | D3: =SO!D3 -> 2 | E3: (1 - Local Sales,2 Interstate Sales, 3 Export Sales) | J3: Cur. | K3: INR | M3: Ex. Rate | N3: 1
A4: S. No. | B4: Item | C4: Rev | D4: Item Desc. | E4: Stk. UOM | F4: Sale. UOM | G4: Old Order Qty (Sale UOM) | H4: Old Unit Price | I4: Old Gross Amt. | J4: Old TD% | K4: Old SD% | L4: Old CD% | M4: Old TD Asbl. Val. | N4: Old TD Amt. | O4: Old SD Asbl. Val. | P4: Old SD Amt. | Q4: Old CD Asbl. Val. | R4: Old CD Amt. | S4: Old Disc. Amt. | T4: Old Disc.Amt.Per.Qty | U4: Old Sales Val. | V4: Old HSN | W4: Old Tax Rate | X4: Old CGST | Y4: Old SGST | Z4: Old IGST | AA4: Old Tax amt | AB4: Old Net Amt | AC4: Weight/Vol | AD4: Old Sales Amt (BC) | AE4: Conv. Factor | AF4: Eqv. Stock Qty | AG4: Before Stock Qty | AH4: Before Stock Cost | AI4: After Stock Qty | AJ4: Warehouse | AK4: Promotional Type | AL4: CESS PCT | AM4: CESS AMT | AN4: Old PriceClass | AO4: New Order Qty (Sale UOM) | AP4: New Unit Price | AQ4: New Gross Amt. | AR4: New TD% | AS4: New SD% | AT4: New CD% | AU4: New TD Asbl. Val. | AV4: New TD Amt. | AW4: New SD Asbl. Val. | AX4: New SD Amt. | AY4: New CD Asbl. Val. | AZ4: New CD Amt. | BA4: New Disc. Amt. | BB4: New Disc.Amt.Per.Qty | BC4: New Sales Val. | BD4: New HSN | BE4: New Tax Rate | BF4: New CGST | BG4: New SGST | BH4: New IGST | BI4: New Tax amt | BJ4: New Net Amt | BK4: Weight/Vol | BL4: New Sales Amt (BC) | BM4: New PriceClass | BN4: SoAmdType
A5: 1 | B5: HK-FIFO-LOT-BATCH-10001(FG) | C5: 0 | D5: HK-FIFO-LOT-BATCH-10001(FG) | E5: NOS | F5: NOS | G5: =SO!G5 -> 10 | H5: =SO!H5 -> 1234 | I5: =SO!I5 -> 12340 | J5: =SO!J5 -> 1 | K5: =SO!K5 -> 2 | L5: =SO!L5 -> 4 | M5: =SO!M5 -> 12340 | N5: =SO!N5 -> 123.4 | ... AB5: =SO!AB5 -> 0.06 | AC5: 120 | AD5: =SO!AD5 -> 1379.21 | AE5: 1 | AF5: =G5/AE5 -> 10 | AG5: 848 | AH5: 235.36857 | AI5: =ROUND(AG5-G5,0) -> 838 | AJ5: F100 | AK5: Sales Regular | AL5: 0 | AM5: =ROUND(((AL5*U5)/100),2) -> 0 | AN5: =SO!AN5 -> Sales Regular | AO5: =G5 -> 10 | AP5: =H5 -> 1234 | AQ5: =AO5*AP5 -> 12340 | AR5: =J5 -> 1 | AS5: =K5 -> 2 | AT5: =L5 -> 4 | AU5: =M5 -> 12340 | AV5: =N5 -> 123.4 | AW5: =O5 -> 12216.6 | AX5: =P5 -> 244.33 | AY5: =Q5 -> 11972.27 | ... BD5: =V5 -> (740410)-18% | BE5: 0.12 | BF5: =IF(SO!$D$3=1,ROUND(((BC5*BE5)/2),2),0) -> 0 | BG5: =IF(SO!$D$3=1,ROUND(((BC5*BE5)/2),2),0) -> 0 | BH5: =IF(SO!$D$3=2,ROUND(((BC5*BE5)),2),0) -> 1379.21 | BI5: =BF5+BG5+BH5 -> 1379.21 | BJ5: =BC5+BI5 -> 12872.59 | BK5: 120 | BL5: =BC5*SO!$N$3 -> 11493.38 | BM5: =AN5 -> Sales Regular | BN5: Modify
A6: 2 | B6: HK-FG-DISSIMILAR-10001 | C6: 0 | D6: HK-FG-DISSIMILAR-10001 | E6: KGS | F6: NOS | G6: =SO!G6 -> 20 | H6: =SO!H6 -> 3214 | I6: =SO!I6 -> 64280 | J6: =SO!J6 -> 2 | K6: =SO!K6 -> 7 | L6: =SO!L6 -> 9 | M6: =SO!M6 -> 64280 | N6: =SO!N6 -> 1285.6 | ... AB6: =SO!AB6 -> 0.06 | AC6: 120 | AD6: =SO!AD6 -> 2665.61 | AE6: 3 | AF6: =ROUND(G6/AE6,3) -> 6.667 | AG6: 1375.002 | AH6: 123 | AI6: =ROUND((AG6-AF6),3) -> 1368.335 | AJ6: F100 | AK6: Sales Regular | AL6: 0 | AM6: =ROUND(((AL6*U6)/100),2) -> 0 | AN6: =SO!AN6 -> Sales Regular | AO6: =G6 -> 20 | AP6: =H6 -> 3214 | AQ6: =AO6*AP6 -> 64280 | AR6: =J6 -> 2 | AS6: =K6 -> 7 | AT6: =L6 -> 9 | AU6: =M6 -> 64280 | AV6: =N6 -> 1285.6 | AW6: =O6 -> 62994.4 | AX6: =P6 -> 4409.61 | AY6: =Q6 -> 58584.79 | ... BD6: =V6 -> 772213 | BE6: 0.05 | BF6: =IF(SO!$D$3=1,ROUND(((BC6*BE6)/2),2),0) -> 0 | BG6: =IF(SO!$D$3=1,ROUND(((BC6*BE6)/2),2),0) -> 0 | BH6: =IF(SO!$D$3=2,ROUND(((BC6*BE6)),2),0) -> 2665.61 | BI6: =BF6+BG6+BH6 -> 2665.61 | BJ6: =BC6+BI6 -> 55977.77 | BK6: 120 | BL6: =BC6*SO!$N$3 -> 53312.16 | BM6: =AN6 -> Sales Regular | BN6: Modify
A7: 3 | B7: HK-TVS-FG-10001 | C7: 0 | D7: HK-TVS-FG-10001 | E7: MTON | F7: MTON | G7: 0 | H7: 0 | I7: 0 | J7: 0 | K7: 0 | L7: 0 | M7: 0 | N7: 0 | O7: 0 | P7: 0 | Q7: 0 | R7: 0 | S7: 0 | T7: 0 | U7: 0 | V7: 0 | W7: 0 | X7: 0 | Y7: 0 | Z7: 0 | AA7: 0 | AB7: 0 | AC7: 0 | AD7: 0 | AE7: .0001 | AN7: DOMESTIC | AO7: 15 | AP7: 5780 | AQ7: =AO7*AP7 -> 86700 | AR7: 20 | AS7: 10 | AT7: 5 | AU7: =AQ7 -> 86700 | AV7: =ROUND((AU7*AR7)/100,2) -> 17340 | AW7: =AQ7-AV7 -> 69360 | AX7: =ROUND((AW7*AS7)/100,2) -> 6936 | AY7: =ROUND(AW7-AX7,2) -> 62424 | AZ7: =ROUND((AY7*AT7)/100,2) -> 3121.2 | BA7: =AV7+AX7+AZ7 -> 27397.2 | BB7: =ROUND(BA7/AO7,2) -> 1826.48 | BC7: =(AQ7-BA7) -> 59302.8 | BD7: HSN1 | BE7: 0.18 | BF7: =IF(SO!$D$3=1,ROUND(((BC7*BE7)/2),2),0) -> 0 | BG7: =IF(SO!$D$3=1,ROUND(((BC7*BE7)/2),2),0) -> 0 | BH7: =IF(SO!$D$3=2,ROUND(((BC7*BE7)),2),0) -> 10674.5 | BI7: =BF7+BG7+BH7 -> 10674.5 | BJ7: =BC7+BI7 -> 69977.3 | BK7: 120 | BL7: =BC7*SO!$N$3 -> 59302.8 | BM7: Spare | BN7: Addition
Q8: DISC AMOUNT | S8: =SUM(S5:S7) -> 11814.46 | Z8: NET AMOUNT | AB8: =SUM(AB5:AB7) -> 0.12 | AC8: SALES AMOUNT | AD8: =SUM(AD5:AD7) -> 4044.82 | AY8: DISC AMOUNT | BA8: =SUM(BA5:BA6) -> 11814.46 | BH8: NET AMOUNT | BJ8: =SUM(BJ5:BJ7) -> 138827.66 | BK8: SALES AMOUNT | BL8: =SUM(BL5:BL7) -> 124108.34

Sheet Add of Item
A1: Scenario : Local Sales - Stock UOM and Sales UOM (Similar) DOC NO : SORD-2425-00089
A2: Sales Order
A3: GST Sales | D3: 2 | E3: (1 - Local Sales,2 Interstate Sales, 3 Export Sales) | J3: Cur. | K3: INR | M3: Ex. Rate | N3: 1
A4: S. No. | B4: Item | C4: Rev | D4: Item Desc. | E4: Stk. UOM | F4: Sale. UOM | G4: Order Qty (Sale UOM) | H4: Unit Price | I4: Gross Amt. | J4: TD% | K4: SD% | L4: CD% | M4: TD Asbl. Val. | N4: TD Amt. | O4: SD Asbl. Val. | P4: SD Amt. | Q4: CD Asbl. Val. | R4: CD Amt. | S4: Disc. Amt. | T4: Disc.Amt.Per.Qty | U4: Sales Val. | V4: HSN | W4: Tax Rate | X4: CGST | Y4: SGST | Z4: IGST | AA4: UTGST | AB4: CESS % | AC4: CESS AMT | AD4: Tax amt | AE4: Net Amt | AF4: Weight/Vol | AG4: Sales Amt (BC) | AH4: Conv. Factor | AI4: Eqv. Stock Qty | AJ4: Before Stock Qty | AK4: Before Stock Cost | AL4: After Stock Qty | AM4: Warehouse | AN4: Promotional Type | AO4: CESS PCT | AP4: CESS AMT | AQ4: PriceClass | AR4: Order Qty (Sale UOM) | AS4: Unit Price | AT4: Gross Amt. | AU4: TD% | AV4: SD% | AW4: CD% | AX4: TD Asbl. Val. | AY4: TD Amt. | AZ4: SD Asbl. Val. | BA4: SD Amt. | BB4: CD Asbl. Val. | BC4: CD Amt. | BD4: Disc. Amt. | BE4: Disc.Amt.Per.Qty | BF4: Sales Val. | BG4: HSN | BH4: Tax Rate | BI4: CGST | BJ4: SGST | BK4: IGST | BL4: UTGST | BM4: CESS % | BN4: CESS AMT | BO4: Tax amt | BP4: Net Amt | BQ4: Weight/Vol | BR4: Sales Amt (BC) | BS4: Promotional Type | BT4: PriceClass | BU4: SoAmdType
A5: =SO!A5 -> 1 | B5: =SO!B5 -> HK-FIFO-LOT-BATCH-10001(FG) | C5: =SO!C5 -> 0 | D5: =SO!D5 -> HK-FIFO-LOT-BATCH-10001(FG) | E5: =SO!E5 -> NOS | F5: =SO!F5 -> NOS | G5: =SO!G5 -> 10 | H5: =SO!H5 -> 1234 | ... V5: =SO!V5 -> (740410)-18% | W5: 0.12 | X5: =SO!X5 -> 0 | Y5: =SO!Y5 -> 0 | Z5: =SO!Z5 -> 1379.21 | AA5: =SO!AA5 -> 0 | AB5: 0.06 | AC5: =SO!AC5 -> 0 | AD5: =SO!AD5 -> 1379.21 | AE5: =SO!AE5 -> 12872.59 | AF5: =SO!AF5 -> 120 | AG5: =SO!AG5 -> 11493.38 | AH5: =SO!AH5 -> 1 | AI5: =SO!AI5 -> 10 | AJ5: =SO!AJ5 -> 848 | ... AQ5: =SO!AQ5 -> DOMESTIC | AR5: 10 | AS5: 1234 | AT5: =AR5*AS5 -> 12340 | AU5: 1 | AV5: 2 | AW5: 4 | AX5: =AT5 -> 12340 | AY5: =ROUND((AX5*AU5)/100,2) -> 123.4 | AZ5: =AT5-AY5 -> 12216.6 | BA5: =ROUND((AZ5*AV5)/100,2) -> 244.33 | BB5: =ROUND(AZ5-BA5,2) -> 11972.27 | BC5: =ROUND((BB5*AW5)/100,2) -> 478.89 | BD5: =AY5+BA5+BC5 -> 846.62 | BE5: =ROUND(BD5/AR5,2) -> 84.66 | BF5: =(AT5-BD5) -> 11493.38 | BG5: (740410)-18% | BH5: 0.12 | BI5: =IF(OR($D$3=1,$D$3=4),ROUND((BF5*BH5)/2,2),0) -> 0 | BJ5: =IF($D$3=1,ROUND(((BF5*BH5)/2),2),0) -> 0 | BK5: =IF($D$3=2,ROUND(((BF5*BH5)),2),0) -> 1379.21 | BL5: =IF($D$3=4,ROUND(((BF5*BH5)/2),2),0) -> 0 | BM5: 0.06 | BN5: =IF($D$3=5,ROUND(((BF5*BM5)/2),2),0) -> 0 | BO5: =BI5+BJ5+BK5+BL5+BN5 -> 1379.21 | BP5: =BF5+BO5 -> 12872.59 | BQ5: 120 | BR5: =BF5*$N$3 -> 11493.38 | BS5: Sales Regular | BT5: DOMESTIC | BU5: Modify
A6: =SO!A6 -> 2 | B6: =SO!B6 -> HK-FG-DISSIMILAR-10001 | C6: =SO!C6 -> 0 | D6: =SO!D6 -> HK-FG-DISSIMILAR-10001 | E6: =SO!E6 -> KGS | F6: =SO!F6 -> NOS | G6: =SO!G6 -> 20 | H6: =SO!H6 -> 3214 | ... V6: =SO!V6 -> 772213 | W6: 0.05 | X6: =SO!X6 -> 0 | Y6: =SO!Y6 -> 0 | Z6: =SO!Z6 -> 2665.61 | AA6: =SO!AA6 -> 0 | AB6: 0.06 | AC6: =SO!AC6 -> 0 | AD6: =SO!AD6 -> 2665.61 | AE6: =SO!AE6 -> 55977.77 | AF6: =SO!AF6 -> 120 | AG6: =SO!AG6 -> 53312.16 | AH6: =SO!AH6 -> 3 | AI6: =SO!AI6 -> 6.667 | AJ6: =SO!AJ6 -> 1375.002 | ... AQ6: =SO!AQ6 -> DOMESTIC | AR6: 20 | AS6: 3214 | AT6: =AR6*AS6 -> 64280 | AU6: 2 | AV6: 7 | AW6: 9 | AX6: =AT6 -> 64280 | AY6: =ROUND((AX6*AU6)/100,2) -> 1285.6 | AZ6: =AT6-AY6 -> 62994.4 | BA6: =ROUND((AZ6*AV6)/100,2) -> 4409.61 | BB6: =ROUND(AZ6-BA6,2) -> 58584.79 | BC6: =ROUND((BB6*AW6)/100,2) -> 5272.63 | BD6: =AY6+BA6+BC6 -> 10967.84 | BE6: =ROUND(BD6/AR6,2) -> 548.39 | BF6: =(AT6-BD6) -> 53312.16 | BG6: 772213 | BH6: 0.05 | BI6: =IF(OR($D$3=1,$D$3=4),ROUND((BF6*BH6)/2,2),0) -> 0 | BJ6: =IF($D$3=1,ROUND(((BF6*BH6)/2),2),0) -> 0 | BK6: =IF($D$3=2,ROUND(((BF6*BH6)),2),0) -> 2665.61 | BL6: =IF($D$3=4,ROUND(((BF6*BH6)/2),2),0) -> 0 | BM6: 0.06 | BN6: =IF($D$3=5,ROUND(((BF6*BM6)/2),2),0) -> 0 | BO6: =BI6+BJ6+BK6+BL6+BN6 -> 2665.61 | BP6: =BF6+BO6 -> 55977.77 | BQ6: 120 | BR6: =BF6*$N$3 -> 53312.16 | BS6: Sales Regular | BT6: DOMESTIC | BU6: Modify
A7: 3 | B7: HK-TVS-FG-10001 | C7: 0 | D7: HK-TVS-FG-10001 | E7: MTON | F7: MTON | G7: 0 | H7: 0 | I7: 0 | J7: 0 | K7: 0 | L7: 0 | M7: 0 | N7: 0 | O7: 0 | P7: 0 | Q7: 0 | R7: 0 | S7: 0 | T7: 0 | U7: 0 | V7: 0 | W7: 0 | X7: 0 | Y7: 0 | Z7: 0 | AA7: 0 | AB7: 0 | AC7: 0 | AD7: 0 | AE7: 0 | AF7: 0 | AG7: 0 | AH7: 0 | AI7: 0 | AJ7: 0 | AK7: 0 | AL7: 0 | AM7: 0 | AN7: 0 | AO7: 0 | AP7: 0 | AQ7: DOMESTIC | AR7: 35 | AS7: 8716 | AT7: =AR7*AS7 -> 305060 | AU7: 5 | AV7: 9 | AW7: 11 | AX7: =AT7 -> 305060 | AY7: =ROUND((AX7*AU7)/100,2) -> 15253 | AZ7: =AT7-AY7 -> 289807 | BA7: =ROUND((AZ7*AV7)/100,2) -> 26082.63 | BB7: =ROUND(AZ7-BA7,2) -> 263724.37 | BC7: =ROUND((BB7*AW7)/100,2) -> 29009.68 | BD7: =AY7+BA7+BC7 -> 70345.31 | BE7: =ROUND(BD7/AR7,2) -> 2009.87 | BF7: =(AT7-BD7) -> 234714.69 | BG7: 772213 | BH7: 0.05 | BI7: =IF(OR($D$3=1,$D$3=4),ROUND((BF7*BH7)/2,2),0) -> 0 | BJ7: =IF($D$3=1,ROUND(((BF7*BH7)/2),2),0) -> 0 | BK7: =IF($D$3=2,ROUND(((BF7*BH7)),2),0) -> 11735.73 | BL7: =IF($D$3=4,ROUND(((BF7*BH7)/2),2),0) -> 0 | BM7: 0.06 | BN7: =IF($D$3=5,ROUND(((BF7*BM7)/2),2),0) -> 0 | BO7: =BI7+BJ7+BK7+BL7+BN7 -> 11735.73 | BP7: =BF7+BO7 -> 246450.42 | BQ7: 120 | BR7: =BF7*$N$3 -> 234714.69 | BS7: Sales Regular | BT7: DOMESTIC | BU7: Addition
Q8: DISC AMOUNT | S8: =SUM(S5:S6) -> 11814.46 | Z8: NET AMOUNT | AE8: =SUM(AE5:AE6) -> 68850.36 | AF8: SALES AMOUNT | AG8: =AG5 -> 11493.38 | BB8: DISC AMOUNT | BD8: =SUM(BD5:BD7) -> 82159.77 | BK8: NET AMOUNT | BP8: =SUM(BP5:BP7) -> 315300.78 | BQ8: SALES AMOUNT | BR8: =SUM(BR5:BR7) -> 299520.23

Sheet So Amend AddOfItem Local
A1: Scenario : Local Sales - Stock UOM and Sales UOM (Similar) DOC NO : SORD-2425-00089
A2: Sales Order
A3: GST Sales | D3: 1 | E3: (1 - Local Sales,2 Interstate Sales, 3 Import Sales) | J3: Cur. | K3: INR | M3: Ex. Rate | N3: 1
A4: S. No. | B4: Item | C4: Rev | D4: Item Desc. | E4: Stk. UOM | F4: Sale. UOM | G4: Order Qty (Sale UOM) | H4: Unit Price | I4: Gross Amt. | J4: TD% | K4: SD% | L4: CD% | M4: TD Asbl. Val. | N4: TD Amt. | O4: SD Asbl. Val. | P4: SD Amt. | Q4: CD Asbl. Val. | R4: CD Amt. | S4: Disc. Amt. | T4: Disc.Amt.Per.Qty | U4: Sales Val. | V4: HSN | W4: Tax Rate | X4: CGST | Y4: SGST | Z4: IGST | AA4: UTGST | AB4: CESS % | AC4: CESS AMT | AD4: Tax amt | AE4: Net Amt | AF4: Weight/Vol | AG4: Sales Amt (BC) | AH4: Conv. Factor | AI4: Eqv. Stock Qty | AJ4: Before Stock Qty | AK4: Before Stock Cost | AL4: After Stock Qty | AM4: Warehouse | AN4: Promotional Type | AO4: CESS PCT | AP4: CESS AMT | AQ4: PriceClass | AR4: Order Qty (Sale UOM) | AS4: Unit Price | AT4: Gross Amt. | AU4: TD% | AV4: SD% | AW4: CD% | AX4: TD Asbl. Val. | AY4: TD Amt. | AZ4: SD Asbl. Val. | BA4: SD Amt. | BB4: CD Asbl. Val. | BC4: CD Amt. | BD4: Disc. Amt. | BE4: Disc.Amt.Per.Qty | BF4: Sales Val. | BG4: HSN | BH4: Tax Rate | BI4: CGST | BJ4: SGST | BK4: IGST | BL4: UTGST | BM4: CESS % | BN4: CESS AMT | BO4: Tax amt | BP4: Net Amt | BQ4: Weight/Vol | BR4: Sales Amt (BC) | BS4: Promotional Type | BT4: PriceClass | BU4: SoAmdType
A5: 1 | B5: HK-FIFO-LOT-BATCH-10001(FG) | C5: 0 | D5: HK-FIFO-LOT-BATCH-10001(FG) | E5: NOS | F5: NOS | G5: 10 | H5: 1500 | I5: =G5*H5 -> 15000 | J5: 2 | K5: 3 | L5: 5 | M5: =I5 -> 15000 | N5: =ROUND((M5*J5)/100,2) -> 300 | O5: =I5-N5 -> 14700 | P5: =ROUND((O5*K5)/100,2) -> 441 | Q5: =ROUND(O5-P5,2) -> 14259 | R5: =ROUND((Q5*L5)/100,2) -> 712.95 | S5: =ROUND(N5+P5+R5,2) -> 1453.95 | T5: =ROUND(S5/G5,2) -> 145.4 | U5: =(I5-S5) -> 13546.05 | V5: HSN1 | W5: 0.12 | X5: =IF(OR($D$3=1,$D$3=4),ROUND((U5*W5)/2,2),0) -> 812.76 | Y5: =IF($D$3=1,ROUND(((U5*W5)/2),2),0) -> 812.76 | Z5: =IF($D$3=2,ROUND(((U5*W5)),2),0) -> 0 | AA5: =IF($D$3=4,ROUND(((U5*W5)/2),2),0) -> 0 | AB5: 0.06 | AC5: =IF($D$3=5,ROUND(((U5*AB5)/2),2),0) -> 0 | AD5: =X5+Y5+Z5+AA5+AC5 -> 1625.52 | AE5: =U5+AD5 -> 15171.57 | AF5: 120 | AG5: =U5*$N$3 -> 13546.05 | AH5: 1 | AI5: =G5/AH5 -> 10 | AJ5: 848 | AK5: 235.36857 | AL5: =ROUND(AJ5-G5,0) -> 838 | AM5: F100 | AN5: Sales Regular | AO5: 0 | AP5: =ROUND(((AO5*U5)/100),2) -> 0 | AQ5: DOMESTIC | AR5: 20 | AS5: 1500 | AT5: =AR5*AS5 -> 30000 | AU5: 2 | AV5: 3 | AW5: 5 | AX5: =AT5 -> 30000 | AY5: =ROUND((AX5*AU5)/100,2) -> 600 | AZ5: =AT5-AY5 -> 29400 | BA5: =ROUND((AZ5*AV5)/100,2) -> 882 | BB5: =ROUND(AZ5-BA5,2) -> 28518 | BC5: =ROUND((BB5*AW5)/100,2) -> 1425.9 | BD5: =ROUND(AY5+BA5+BC5,2) -> 2907.9 | BE5: =ROUND(BD5/AR5,2) -> 145.4 | BF5: =(AT5-BD5) -> 27092.1 | BG5: HSN1 | BH5: 0.12 | BI5: =IF(OR($D$3=1,$D$3=4),ROUND((BF5*BH5)/2,2),0) -> 1625.53 | BJ5: =IF($D$3=1,ROUND(((BF5*BH5)/2),2),0) -> 1625.53 | BK5: =IF($D$3=2,ROUND(((BF5*BH5)),2),0) -> 0 | BL5: =IF($D$3=4,ROUND(((BF5*BH5)/2),2),0) -> 0 | BM5: 0.06 | BN5: =IF($D$3=5,ROUND(((BF5*BM5)/2),2),0) -> 0 | BO5: =BI5+BJ5+BK5+BL5+BN5 -> 3251.06 | BP5: =BF5+BO5 -> 30343.16 | BQ5: 120 | BR5: =BF5*$N$3 -> 27092.1 | BS5: Sales Regular | BT5: DOMESTIC | BU5: Modify
A6: 2 | B6: HK-FG-DISSIMILAR-10001 | C6: 0 | D6: HK-FG-DISSIMILAR-10001 | E6: KGS | F6: NOS | G6: 10 | H6: 2000 | I6: =G6*H6 -> 20000 | J6: 5 | K6: 7 | L6: 9 | M6: =I6 -> 20000 | N6: =ROUND((M6*J6)/100,2) -> 1000 | O6: =I6-N6 -> 19000 | P6: =ROUND((O6*K6)/100,2) -> 1330 | Q6: =ROUND(O6-P6,2) -> 17670 | R6: =ROUND((Q6*L6)/100,2) -> 1590.3 | S6: =ROUND(N6+P6+R6,2) -> 3920.3 | T6: =ROUND(S6/G6,2) -> 392.03 | U6: =(I6-S6) -> 16079.7 | V6: HSN1 | W6: 0.05 | X6: =IF(OR($D$3=1,$D$3=4),ROUND((U6*W6)/2,2),0) -> 401.99 | Y6: =IF($D$3=1,ROUND(((U6*W6)/2),2),0) -> 401.99 | Z6: =IF($D$3=2,ROUND(((U6*W6)),2),0) -> 0 | AA6: =IF($D$3=4,ROUND(((U6*W6)/2),2),0) -> 0 | AB6: 0.06 | AC6: =IF($D$3=5,ROUND(((U6*AB6)/2),2),0) -> 0 | AD6: =X6+Y6+Z6+AA6+AC6 -> 803.98 | AE6: =U6+AD6 -> 16883.68 | AF6: 120 | AG6: =U6*$N$3 -> 16079.7 | AH6: 3 | AI6: =ROUND(G6/AH6,3) -> 3.333 | AJ6: 1375.002 | AK6: 123 | AL6: =ROUND((AJ6-AI6),3) -> 1371.669 | AM6: F100 | AN6: Sales Regular | AO6: 0 | AP6: =ROUND(((AO6*U6)/100),2) -> 0 | AQ6: DOMESTIC | AR6: 30 | AS6: 2000 | AT6: =AR6*AS6 -> 60000 | AU6: 5 | AV6: 7 | AW6: 9 | AX6: =AT6 -> 60000 | AY6: =ROUND((AX6*AU6)/100,2) -> 3000 | AZ6: =AT6-AY6 -> 57000 | BA6: =ROUND((AZ6*AV6)/100,2) -> 3990 | BB6: =ROUND(AZ6-BA6,2) -> 53010 | BC6: =ROUND((BB6*AW6)/100,2) -> 4770.9 | BD6: =ROUND(AY6+BA6+BC6,2) -> 11760.9 | BE6: =ROUND(BD6/AR6,2) -> 392.03 | BF6: =(AT6-BD6) -> 48239.1 | BG6: HSN1 | BH6: 0.05 | BI6: =IF(OR($D$3=1,$D$3=4),ROUND((BF6*BH6)/2,2),0) -> 1205.98 | BJ6: =IF($D$3=1,ROUND(((BF6*BH6)/2),2),0) -> 1205.98 | BK6: =IF($D$3=2,ROUND(((BF6*BH6)),2),0) -> 0 | BL6: =IF($D$3=4,ROUND(((BF6*BH6)/2),2),0) -> 0 | BM6: 0.06 | BN6: =IF($D$3=5,ROUND(((BF6*BM6)/2),2),0) -> 0 | BO6: =BI6+BJ6+BK6+BL6+BN6 -> 2411.96 | BP6: =BF6+BO6 -> 50651.06 | BQ6: 120 | BR6: =BF6*$N$3 -> 48239.1 | BS6: Sales Regular | BT6: DOMESTIC | BU6: Modify
A7: 3 | B7: HK-TVS-FG-10001 | C7: 0 | D7: HK-TVS-FG-10001 | E7: MTON | F7: MTON | G7: 0 | H7: 0 | I7: 0 | J7: 0 | K7: 0 | L7: 0 | M7: 0 | N7: 0 | O7: 0 | P7: 0 | Q7: 0 | R7: 0 | S7: 0 | T7: 0 | U7: 0 | V7: 0 | W7: 0 | X7: 0 | Y7: 0 | Z7: 0 | AA7: 0 | AB7: 0 | AC7: 0 | AD7: 0 | AE7: 0 | AF7: 0 | AG7: 0 | AH7: 0 | AI7: 0 | AJ7: 0 | AK7: 0 | AL7: 0 | AM7: 0 | AN7: 0 | AO7: 0 | AP7: 0 | AQ7: DOMESTIC | AR7: 35 | AS7: 8716 | AT7: =AR7*AS7 -> 305060 | AU7: 5 | AV7: 9 | AW7: 11 | AX7: =AT7 -> 305060 | AY7: =ROUND((AX7*AU7)/100,2) -> 15253 | AZ7: =AT7-AY7 -> 289807 | BA7: =ROUND((AZ7*AV7)/100,2) -> 26082.63 | BB7: =ROUND(AZ7-BA7,2) -> 263724.37 | BC7: =ROUND((BB7*AW7)/100,2) -> 29009.68 | BD7: =AY7+BA7+BC7 -> 70345.31 | BE7: =ROUND(BD7/AR7,2) -> 2009.87 | BF7: =(AT7-BD7) -> 234714.69 | BG7: 772213 | BH7: 0.05 | BI7: =IF(OR($D$3=1,$D$3=4),ROUND((BF7*BH7)/2,2),0) -> 5867.87 | BJ7: =IF($D$3=1,ROUND(((BF7*BH7)/2),2),0) -> 5867.87 | BK7: =IF($D$3=2,ROUND(((BF7*BH7)),2),0) -> 0 | BL7: =IF($D$3=4,ROUND(((BF7*BH7)/2),2),0) -> 0 | BM7: 0.06 | BN7: =IF($D$3=5,ROUND(((BF7*BM7)/2),2),0) -> 0 | BO7: =BI7+BJ7+BK7+BL7+BN7 -> 11735.74 | BP7: =BF7+BO7 -> 246450.43 | BQ7: 120 | BR7: =BF7*$N$3 -> 234714.69 | BS7: Sales Regular | BT7: DOMESTIC | BU7: Addition
Q8: DISC AMOUNT | Z8: NET AMOUNT | AE8: =SUM(AE5:AE6) -> 32055.25 | AF8: SALES AMOUNT | AG8: =AG5 -> 13546.05 | BB8: DISC AMOUNT | BK8: NET AMOUNT | BP8: =SUM(BP5:BP6) -> 80994.22 | BQ8: SALES AMOUNT | BR8: =BR5 -> 27092.1

Sheet SO Amendment With Charges
A1: Scenario : Local Sales - Stock UOM and Sales UOM (Similar) DOC NO : SORD-2425-00089
A2: Sales Order
A3: GST Sales | D3: 2 | E3: (1 - Local Sales,2 Interstate Sales, 3 Import Sales) | J3: Cur. | K3: INR | M3: Ex. Rate | N3: 1
A4: S. No. | B4: Item | C4: Rev | D4: Item Desc. | E4: Stk. UOM | F4: Sale. UOM | G4: Order Qty (Sale UOM) | H4: Unit Price | I4: Gross Amt. | J4: TD% | K4: SD% | L4: CD% | M4: TD Asbl. Val. | N4: TD Amt. | O4: SD Asbl. Val. | P4: SD Amt. | Q4: CD Asbl. Val. | R4: CD Amt. | S4: Disc. Amt. | T4: Disc.Amt.Per.Qty | U4: Sales Val. | V4: HSN | W4: Tax Rate | X4: CGST | Y4: SGST | Z4: IGST | AA4: Tax amt | AB4: Net Amt | AC4: Weight/Vol | AD4: Sales Amt (BC) | AE4: Conv. Factor | AF4: Eqv. Stock Qty | AG4: Before Stock Qty | AH4: Before Stock Cost | AI4: After Stock Qty | AJ4: Warehouse | AK4: Promotional Type | AL4: CESS PCT | AM4: CESS AMT | AN4: PriceClass
A5: 1 | B5: HK-FIFO-LOT-BATCH-10001(FG) | C5: 0 | D5: HK-FIFO-LOT-BATCH-10001(FG) | E5: NOS | F5: NOS | G5: 10 | H5: 1679 | I5: =G5*H5 -> 16790 | J5: 12.5 | K5: 11.3 | L5: 25.6 | M5: =I5 -> 16790 | N5: =ROUND((M5*J5)/100,2) -> 2098.75 | O5: =I5-N5 -> 14691.25 | P5: =ROUND((O5*K5)/100,2) -> 1660.11 | Q5: =ROUND(O5-P5,2) -> 13031.14 | R5: =ROUND((Q5*L5)/100,2) -> 3335.97 | S5: =ROUND(N5+P5+R5,2) -> 7094.83 | T5: =ROUND(S5/G5,2) -> 709.48 | U5: =(I5-S5) -> 9695.17 | V5: HSN1 | W5: 0.12 | X5: =IF($D$3=1,ROUND(((U5*W5)/2),2),0) -> 0 | Y5: =IF($D$3=1,ROUND(((U5*W5)/2),2),0) -> 0 | Z5: =IF($D$3=2,ROUND(((U5*W5)),2),0) -> 1163.42 | AA5: =ROUND((X5+Y5+Z5+AM5),2) -> 1163.42 | AB5: =U5+AA5 -> 10858.59 | AC5: 120 | AD5: =U5*$N$3 -> 9695.17 | AE5: 1 | AF5: =G5/AE5 -> 10 | AG5: 848 | AH5: 235.36857 | AI5: =ROUND(AG5-G5,0) -> 838 | AJ5: F100 | AK5: Sales Regular | AL5: 0 | AM5: =ROUND(((AL5*U5)/100),2) -> 0 | AN5: DOMESTIC
A6: 2 | B6: HK-FG-DISSIMILAR-10001 | C6: 0 | D6: HK-FG-DISSIMILAR-10001 | E6: KGS | F6: NOS | G6: 10 | H6: 2367 | I6: =G6*H6 -> 23670 | J6: 1.2 | K6: 1.34 | L6: 1.65 | M6: =I6 -> 23670 | N6: =ROUND((M6*J6)/100,2) -> 284.04 | O6: =I6-N6 -> 23385.96 | P6: =ROUND((O6*K6)/100,2) -> 313.37 | Q6: =ROUND(O6-P6,2) -> 23072.59 | R6: =ROUND((Q6*L6)/100,2) -> 380.7 | S6: =N6+P6+R6 -> 978.11 | T6: =ROUND(S6/G6,2) -> 97.81 | U6: =(I6-S6) -> 22691.89 | V6: HSN1 | W6: 0.05 | X6: =IF($D$3=1,ROUND(((U6*W6)/2),2),0) -> 0 | Y6: =IF($D$3=1,ROUND(((U6*W6)/2),2),0) -> 0 | Z6: =IF($D$3=2,ROUND(((U6*W6)),2),0) -> 1134.59 | AA6: =X6+Y6+Z6 -> 1134.59 | AB6: =U6+AA6 -> 23826.48 | AC6: 120 | AD6: =U6*$N$3 -> 22691.89 | AE6: 3 | AF6: =ROUND(G6/AE6,3) -> 3.333 | AG6: 1375.002 | AH6: 123 | AI6: =ROUND((AG6-AF6),3) -> 1371.669 | AJ6: F100 | AK6: Sales Regular | AL6: 0 | AM6: =ROUND(((AL6*U6)/100),2) -> 0 | AN6: DOMESTIC
I7: =SUM(I5:I6) -> 40460 | Q7: DISC AMOUNT | U7: =SUM(U5:U6) -> 32387.06 | Z7: NET AMOUNT | AB7: =SUM(AB5:AB6) -> 34685.07 | AC7: SALES AMOUNT | AD7: =AD5 -> 9695.17
C9: Charges
C10: Sno | D10: Item | E10: Rev | F10: Desc | G10: Basiss | H10: Old Pct | I10: Old Value | J10: Old SAC | K10: Old Tax Rate | L10: Old CGST | M10: Old SGST | N10: Old IGST | O10: Old Tax amt | P10: New Value | Q10: New SAC | R10: New Tax Rate | S10: New CGST | T10: New SGST | U10: New IGST | V10: New Tax amt | W10: AmdType
C11: 1 | D11: TVS-CH-00002 | E11: 0 | F11: FRIEGHT CHARGES | G11: % | H11: 20 | I11: =ROUND(((U7*H11)/100),2) -> 6477.41 | J11: 4901 | K11: 0.12 | L11: =IF($D$3=1,ROUND(((I11*K11)/2),2),0) -> 0 | M11: =IF($D$3=1,ROUND(((I11*K11)/2),2),0) -> 0 | N11: =IF($D$3=2,ROUND(((I11*K11)),2),0) -> 777.29 | O11: =L11+M11+N11 -> 777.29 | P11: 5000 | Q11: 4901 | R11: 0.12 | S11: =IF($D$3=1,ROUND(((P11*R11)/2),2),0) -> 0 | T11: =IF($D$3=1,ROUND(((P11*R11)/2),2),0) -> 0 | U11: =IF($D$3=2,ROUND(((P11*R11)),2),0) -> 600 | V11: =S11+T11+U11 -> 600 | W11: Modify
C12: 2 | D12: TVS-CH-00003 | E12: 0 | F12: PACKING CHARGES | G12: Value | I12: 15000 | J12: 112341 | K12: 0.12 | L12: =IF($D$3=1,ROUND(((I12*K12)/2),2),0) -> 0 | M12: =IF($D$3=1,ROUND(((I12*K12)/2),2),0) -> 0 | N12: =IF($D$3=2,ROUND(((I12*K12)),2),0) -> 1800 | O12: =L12+M12+N12 -> 1800 | P12: 10000 | Q12: 112341 | R12: 0.12 | S12: =IF($D$3=1,ROUND(((P12*R12)/2),2),0) -> 0 | T12: =IF($D$3=1,ROUND(((P12*R12)/2),2),0) -> 0 | U12: =IF($D$3=2,ROUND(((P12*R12)),2),0) -> 1200 | V12: =S12+T12+U12 -> 1200 | W12: Modify
C13: 3 | D13: TVS-CH-00011 | E13: 0 | F13: TVS-CH-00011 | G13: Value | H13: 0 | I13: 0 | J13: 0 | K13: 0 | L13: 0 | M13: 0 | N13: 0 | O13: 0 | P13: 1256 | Q13: 112341 | R13: 0.12 | S13: =IF($D$3=1,ROUND(((P13*R13)/2),2),0) -> 0 | T13: =IF($D$3=1,ROUND(((P13*R13)/2),2),0) -> 0 | U13: =IF($D$3=2,ROUND(((P13*R13)),2),0) -> 150.72 | V13: =S13+T13+U13 -> 150.72 | W13: AOI
H14: Total | I14: =SUM(I11:I12) -> 21477.41 | L14: =SUM(L11:L12) -> 0 | M14: =SUM(M11:M12) -> 0 | N14: =SUM(N11:N12) -> 2577.29 | O14: =SUM(O11:O12) -> 2577.29
